Workbook

Sheet Test Case Summary
A1: Pig Style (Megaways) - QA Test Suite
A3: Client | B3: FEG (Fortuna Entertainment Group)
A4: Game | B4: Pig Style - 6-reel Megaways, up to 117,649 ways
A5: Source: Game Rules | B5: Pig_Style_GR_Eng_2.docx
A6: Source: Math File | B6: pig_style_R7_1.xlsx (R7.1)
A7: Prepared by | B7: Pixentech QA
A8: Prepared on | B8: 23 Oct 2026
A9: Test case ID format | B9: PS-<AREA>-NNN
A10: Bet convention | B10: Math pays are credits at total bet 20. Win = Bet x Pay / 20 x Ways x product of wild multipliers
A12: Sheet | B12: Total TCs | C12: P0 | D12: P1 | E12: P2 | F12: P3 | G12: Automation: Yes | H12: Automation: Partial | I12: Requires Spec/Confirmation
A13: Functional Testing | B13: =COUNTA('Functional Testing'!A:A)-1 -> 90 | C13: =COUNTIF('Functional Testing'!K:K,"P0") -> 49 | D13: =COUNTIF('Functional Testing'!K:K,"P1") -> 28 | E13: =COUNTIF('Functional Testing'!K:K,"P2") -> 11 | F13: =COUNTIF('Functional Testing'!K:K,"P3") -> 2 | G13: =COUNTIF('Functional Testing'!N:N,"Yes") -> 66 | H13: =COUNTIF('Functional Testing'!N:N,"Partial") -> 17 | I13: =COUNTIF('Functional Testing'!I:I,"Requires Specification*") -> 10
A14: Math Validation | B14: =COUNTA('Math Validation'!A:A)-1 -> 63 | C14: =COUNTIF('Math Validation'!K:K,"P0") -> 45 | D14: =COUNTIF('Math Validation'!K:K,"P1") -> 10 | E14: =COUNTIF('Math Validation'!K:K,"P2") -> 8 | F14: =COUNTIF('Math Validation'!K:K,"P3") -> 0 | G14: =COUNTIF('Math Validation'!N:N,"Yes") -> 57 | H14: =COUNTIF('Math Validation'!N:N,"Partial") -> 0 | I14: =COUNTIF('Math Validation'!I:I,"Requires Specification*") -> 12
A15: Feature Testing | B15: =COUNTA('Feature Testing'!A:A)-1 -> 59 | C15: =COUNTIF('Feature Testing'!K:K,"P0") -> 40 | D15: =COUNTIF('Feature Testing'!K:K,"P1") -> 18 | E15: =COUNTIF('Feature Testing'!K:K,"P2") -> 1 | F15: =COUNTIF('Feature Testing'!K:K,"P3") -> 0 | G15: =COUNTIF('Feature Testing'!N:N,"Yes") -> 50 | H15: =COUNTIF('Feature Testing'!N:N,"Partial") -> 6 | I15: =COUNTIF('Feature Testing'!I:I,"Requires Specification*") -> 10
A16: Edge & Boundary Cases | B16: =COUNTA('Edge & Boundary Cases'!A:A)-1 -> 42 | C16: =COUNTIF('Edge & Boundary Cases'!K:K,"P0") -> 16 | D16: =COUNTIF('Edge & Boundary Cases'!K:K,"P1") -> 17 | E16: =COUNTIF('Edge & Boundary Cases'!K:K,"P2") -> 7 | F16: =COUNTIF('Edge & Boundary Cases'!K:K,"P3") -> 2 | G16: =COUNTIF('Edge & Boundary Cases'!N:N,"Yes") -> 40 | H16: =COUNTIF('Edge & Boundary Cases'!N:N,"Partial") -> 0 | I16: =COUNTIF('Edge & Boundary Cases'!I:I,"Requires Specification*") -> 4
A17: Regression Suite | B17: =COUNTA('Regression Suite'!A:A)-1 -> 162 | C17: =COUNTIF('Regression Suite'!K:K,"P0") -> 15 | D17: =COUNTIF('Regression Suite'!K:K,"P1") -> 119 | E17: =COUNTIF('Regression Suite'!K:K,"P2") -> 28 | F17: =COUNTIF('Regression Suite'!K:K,"P3") -> 0 | G17: =COUNTIF('Regression Suite'!N:N,"Yes") -> 152 | H17: =COUNTIF('Regression Suite'!N:N,"Partial") -> 5 | I17: =COUNTIF('Regression Suite'!I:I,"Requires Specification*") -> 18
A18: UI-UX Testing | B18: =COUNTA('UI-UX Testing'!A:A)-1 -> 47 | C18: =COUNTIF('UI-UX Testing'!K:K,"P0") -> 1 | D18: =COUNTIF('UI-UX Testing'!K:K,"P1") -> 19 | E18: =COUNTIF('UI-UX Testing'!K:K,"P2") -> 18 | F18: =COUNTIF('UI-UX Testing'!K:K,"P3") -> 9 | G18: =COUNTIF('UI-UX Testing'!N:N,"Yes") -> 1 | H18: =COUNTIF('UI-UX Testing'!N:N,"Partial") -> 41 | I18: =COUNTIF('UI-UX Testing'!I:I,"Requires Specification*") -> 1
A19: Compatibility Testing | B19: =COUNTA('Compatibility Testing'!A:A)-1 -> 21 | C19: =COUNTIF('Compatibility Testing'!K:K,"P0") -> 3 | D19: =COUNTIF('Compatibility Testing'!K:K,"P1") -> 9 | E19: =COUNTIF('Compatibility Testing'!K:K,"P2") -> 7 | F19: =COUNTIF('Compatibility Testing'!K:K,"P3") -> 2 | G19: =COUNTIF('Compatibility Testing'!N:N,"Yes") -> 0 | H19: =COUNTIF('Compatibility Testing'!N:N,"Partial") -> 13 | I19: =COUNTIF('Compatibility Testing'!I:I,"Requires Specification*") -> 0
A20: Interruption & Recovery | B20: =COUNTA('Interruption & Recovery'!A:A)-1 -> 30 | C20: =COUNTIF('Interruption & Recovery'!K:K,"P0") -> 24 | D20: =COUNTIF('Interruption & Recovery'!K:K,"P1") -> 6 | E20: =COUNTIF('Interruption & Recovery'!K:K,"P2") -> 0 | F20: =COUNTIF('Interruption & Recovery'!K:K,"P3") -> 0 | G20: =COUNTIF('Interruption & Recovery'!N:N,"Yes") -> 30 | H20: =COUNTIF('Interruption & Recovery'!N:N,"Partial") -> 0 | I20: =COUNTIF('Interruption & Recovery'!I:I,"Requires Specification*") -> 2
A21: STR - Transaction Testing | B21: =COUNTA('STR - Transaction Testing'!A:A)-1 -> 27 | C21: =COUNTIF('STR - Transaction Testing'!K:K,"P0") -> 23 | D21: =COUNTIF('STR - Transaction Testing'!K:K,"P1") -> 4 | E21: =COUNTIF('STR - Transaction Testing'!K:K,"P2") -> 0 | F21: =COUNTIF('STR - Transaction Testing'!K:K,"P3") -> 0 | G21: =COUNTIF('STR - Transaction Testing'!N:N,"Yes") -> 22 | H21: =COUNTIF('STR - Transaction Testing'!N:N,"Partial") -> 4 | I21: =COUNTIF('STR - Transaction Testing'!I:I,"Requires Specification*") -> 1
A22: Error Handling | B22: =COUNTA('Error Handling'!A:A)-1 -> 20 | C22: =COUNTIF('Error Handling'!K:K,"P0") -> 8 | D22: =COUNTIF('Error Handling'!K:K,"P1") -> 11 | E22: =COUNTIF('Error Handling'!K:K,"P2") -> 1 | F22: =COUNTIF('Error Handling'!K:K,"P3") -> 0 | G22: =COUNTIF('Error Handling'!N:N,"Yes") -> 20 | H22: =COUNTIF('Error Handling'!N:N,"Partial") -> 0 | I22: =COUNTIF('Error Handling'!I:I,"Requires Specification*") -> 0
A23: Total (incl. Regression) | B23: =SUM(B13:B22) -> 561 | C23: =SUM(C13:C22) -> 224 | D23: =SUM(D13:D22) -> 241 | E23: =SUM(E13:E22) -> 81 | F23: =SUM(F13:F22) -> 15 | G23: =SUM(G13:G22) -> 438 | H23: =SUM(H13:H22) -> 86 | I23: =SUM(I13:I22) -> 58
A24: Total unique (excl. Regression) | B24: =B23-B17 -> 399 | C24: =C23-C17 -> 209 | D24: =D23-D17 -> 122 | E24: =E23-E17 -> 53 | F24: =F23-F17 -> 15 | G24: =G23-G17 -> 286 | H24: =H23-H17 -> 81 | I24: =I23-I17 -> 40
A26: Legend
A27: P0 | B27: Release blocker: money, math, compliance, state integrity
A28: P1 | B28: Major functionality; must pass before client release
A29: P2 | B29: Important but has workaround / cosmetic with impact
A30: P3 | B30: Minor / cosmetic
A31: Yellow cells | B31: Columns to fill during execution: Actual Result, Status, Defect ID
A32: Orange Expected Result | B32: Case depends on a spec item marked 'Requires Specification/Confirmation' (see Defect-Observation Log)
A33: Status values | B33: Not Run, Pass, Fail, Blocked, N/A, Spec Confirmation
A34: Regression Suite priority | B34: Execution order: P0 = Smoke (every build), P1 = Core (money, math, features, state), P2 = Extended. Source priority kept in Remarks
A35: Math Reference sheet | B35: Paytable and weights extracted from the math file, with x-bet values as formulas
A37: Example of a completed row (for format reference only)
A38: Test Case ID | B38: PS-FUN-021
A39: Actual Result | B39: Win field 0.75; balance 99.75 from 100.00 at bet 1.00
A40: Status | B40: Pass
A41: Defect ID | B41: (blank when passed, e.g. PS-DEF-012 when failed)

Sheet Functional Testing
A1: Test Case ID | B1: Module | C1: Feature | D1: Sub-Feature | E1: Test Scenario | F1: Preconditions | G1: Test Data | H1: Detailed Test Steps | I1: Expected Result | J1: Actual Result | K1: Priority | L1: Severity | M1: Test Type | N1: Automation Candidate | O1: Environment | P1: Browser/Device | Q1: Status | R1: Defect ID | S1: Remarks
A2: PS-FUN-001 | B2: Functional | C2: Game Launch | D2: Initial load | E2: Verify the game launches from the operator lobby in real-money mode and lands on the base game with correct initial state | F2: Valid player session with funded wallet; game enabled for operator | G2: Balance: 500.00 EUR; default bet as configured | H2: 1. Log in to the operator lobby 2. Launch Pig Style 3. Wait for the loader to complete 4. Observe reels, bet field, balance field and win field | I2: Loader completes without error; 6 reels displayed; balance equals wallet balance (500.00); bet field shows configured default bet; win field shows 0.00 or blank; Play button enabled | K2: P0 | L2: Critical | M2: Functional | N2: Yes | O2: QA / Staging (Game Client + RGS) | P2: Desktop + Mobile (all supported) | Q2: Not Run | S2: Ref: GR-01, GR-19, GR-21
A3: PS-FUN-002 | B3: Functional | C3: Game Launch | D3: Splash screen | E3: Verify the splash/intro screen displays on first launch and can be dismissed to reach the base game | F3: First launch for the player (no prior splash preference) | G3: N/A | H3: 1. Launch the game 2. Observe splash screen 3. Press Continue/Play on the splash 4. Reopen game after enabling 'do not show' option in Splash Screen Settings (if present) | I3: Splash shown on first launch and dismisses to base game; when disabled via Splash Screen Settings the game opens directly to base game on next launch | K3: P2 | L3: Medium | M3: Functional | N3: Yes | O3: QA / Staging (Game Client + RGS) | P3: Desktop + Mobile (all supported) | Q3: Not Run | S3: Ref: GR-46
A4: PS-FUN-003 | B4: Functional | C4: Game Launch | D4: Currency | E4: Verify all monetary fields render in the session currency | F4: Sessions available in EUR, RON and one non-decimal currency if supported | G4: Currencies: EUR, RON | H4: 1. Launch the game with EUR session 2. Check bet, balance, win, paytable and Buy cost values 3. Repeat with RON session | I4: All monetary values show the session currency symbol/code with correct decimal precision; no mixing of currencies; paytable values recalculated in session currency | K4: P1 | L4: High | M4: Functional | N4: Partial | O4: QA / Staging (Game Client + RGS) | P4: Desktop + Mobile (all supported) | Q4: Not Run | S4: Ref: GR-19
A5: PS-FUN-004 | B5: Functional | C5: Game Launch | D5: Demo / Fun mode | E5: Verify the game launches in fun mode with virtual balance and no wallet transactions | F5: Fun mode URL available from operator | G5: Fun balance as configured by RGS | H5: 1. Launch game in fun mode 2. Place 5 spins 3. Check RGS/wallet logs | I5: Game playable with virtual balance; no debit/credit calls to the real-money wallet; fun mode indicator shown if required by operator | K5: P2 | L5: Medium | M5: Functional | N5: Partial | O5: QA / Staging (Game Client + RGS) | P5: Desktop + Mobile (all supported) | Q5: Not Run | S5: Ref: GR-19
A6: PS-FUN-005 | B6: Functional | C6: Base Game | D6: Reel layout | E6: Verify the base game shows 6 reels and each reel displays between 2 and 7 symbols per spin | F6: Base game loaded | G6: Observe 50 spins | H6: 1. Spin 50 times at any bet 2. For each spin, count visible symbol rows on every reel 3. Record min and max per reel | I6: Every reel shows a symbol count in the range 2..7 on every spin; no reel shows 1 or 8+ positions; reel heights vary independently per reel | K6: P0 | L6: Critical | M6: Functional | N6: Yes | O6: QA / Staging (Game Client + RGS) | P6: Desktop + Mobile (all supported) | Q6: Not Run | S6: Ref: GR-01, GR-02, M-06
A7: PS-FUN-006 | B7: Functional | C7: Base Game | D7: Ways counter | E7: Verify the ways-to-win counter equals the product of the symbol counts on all 6 reels | F7: Base game loaded; ways counter visible | G7: Example rows [2,3,4,5,6,7] => 2x3x4x5x6x7 = 5,040 ways | H7: 1. Spin until a result is observed 2. Count rows on each reel 3. Multiply counts 4. Compare to on-screen ways counter | I7: Ways counter equals product of reel heights for every spin (e.g. 5,040 for [2,3,4,5,6,7]); counter updates when the reels stop | K7: P0 | L7: Critical | M7: Functional | N7: Yes | O7: QA / Staging (Game Client + RGS) | P7: Desktop + Mobile (all supported) | Q7: Not Run | S7: Ref: GR-01, GR-02, M-06
A8: PS-FUN-007 | B8: Functional | C8: Base Game | D8: Ways counter | E8: Verify the maximum ways value 117,649 is displayed when all reels show 7 symbols | F8: Test tool / forced outcome to set all reel heights to 7 | G8: Rows [7,7,7,7,7,7] => 7^6 = 117,649 | H8: 1. Force reel heights 7 on all reels 2. Spin 3. Read ways counter | I8: Ways counter shows 117,649 formatted with thousands separator; no truncation | K8: P1 | L8: High | M8: Functional | N8: Yes | O8: QA / Staging (Game Client + RGS) | P8: Desktop Chrome (latest) | Q8: Not Run | S8: Ref: GR-01, M-06
A9: PS-FUN-008 | B9: Functional | C9: Base Game | D9: Ways counter | E9: Verify the minimum ways value 64 is displayed when all reels show 2 symbols | F9: Test tool / forced outcome | G9: Rows [2,2,2,2,2,2] => 2^6 = 64 | H9: 1. Force reel heights 2 on all reels 2. Spin 3. Read ways counter | I9: Ways counter shows 64 | K9: P2 | L9: Medium | M9: Functional | N9: Yes | O9: QA / Staging (Game Client + RGS) | P9: Desktop Chrome (latest) | Q9: Not Run | S9: Ref: GR-01, M-06
A10: PS-FUN-009 | B10: Functional | C10: Spin | D10: Start spin | E10: Verify pressing the Play button starts exactly one game round at the selected bet | F10: Balance >= selected bet | G10: Bet: 1.00; Balance: 100.00 | H10: 1. Note balance 2. Press Play once 3. Wait for round to complete | I10: One round starts; balance reduces by exactly 1.00 at spin start; one bet transaction in RGS; reels spin and stop; any win added after evaluation | K10: P0 | L10: Critical | M10: Functional | N10: Yes | O10: QA / Staging (Game Client + RGS) | P10: Desktop + Mobile (all supported) | Q10: Not Run | S10: Ref: GR-22
A11: PS-FUN-010 | B11: Functional | C11: Spin | D11: Space bar | E11: Verify pressing the space bar starts a game round on desktop | F11: Desktop browser; game canvas focused; no popup open | G11: Bet: 1.00 | H11: 1. Click on the game area to focus 2. Press space bar once 3. Observe round | I11: One round starts exactly as with the Play button; balance debited once | K11: P1 | L11: Medium | M11: Functional | N11: Yes | O11: QA / Staging (Game Client + RGS) | P11: Desktop Chrome (latest) | Q11: Not Run | S11: Ref: GR-44
A12: PS-FUN-011 | B12: Functional | C12: Spin | D12: Space bar | E12: Verify the space bar does not start a spin while a menu, bet panel, paytable or Buy Feature interface is open | F12: Desktop | G12: Bet: 1.00 | H12: 1. Open bet panel and press space 2. Open Menu and press space 3. Open Game Info and press space 4. Open Buy Feature interface and press space | I12: No spin starts and no balance change in any case; open panel remains stable | K12: P1 | L12: High | M12: Negative | N12: Yes | O12: QA / Staging (Game Client + RGS) | P12: Desktop Chrome (latest) | Q12: Not Run | S12: Ref: GR-44
A13: PS-FUN-012 | B13: Functional | C13: Spin | D13: Quick Stop | E13: Verify pressing the spin button again during reel spin stops the reels early without changing the outcome | F13: Quick Stop available in jurisdiction | G13: Bet: 1.00; compare result with RGS response | H13: 1. Press Play 2. Immediately press the spin button again 3. Compare final reel result and win with RGS round response | I13: Reels stop early; displayed symbols and win identical to RGS outcome; no second round started; no extra debit | K13: P1 | L13: High | M13: Functional | N13: Yes | O13: QA / Staging (Game Client + RGS) | P13: Desktop + Mobile (all supported) | Q13: Not Run | S13: Ref: GR-31
... A91: PS-FUN-090 | B91: Functional | C91: Compliance | D91: Pay table ID | E91: Verify the Pay table ID shown in rules matches the deployed math/config identifier | F91: Game Info open; deployed config ID known | G91: Rules: 'Pig Style'; math file game name: 'DogHouseMegaways9700' | H91: 1. Read Pay table ID 2. Compare with RGS math configuration ID | I91: Requires Specification/Confirmation: Math summary carries game name 'DogHouseMegaways9700'. Expected: identifier consistent between rules, math file and deployed config | K91: P1 | L91: High | M91: Compliance | N91: No | O91: QA / Staging (Game Client + RGS) | P91: Desktop + Mobile (all supported) | Q91: Not Run | S91: Ref: GR-59, M-20 | OBS-13

Sheet Math Validation
A1: Test Case ID | B1: Module | C1: Feature | D1: Sub-Feature | E1: Test Scenario | F1: Preconditions | G1: Test Data | H1: Detailed Test Steps | I1: Expected Result | J1: Actual Result | K1: Priority | L1: Severity | M1: Test Type | N1: Automation Candidate | O1: Environment | P1: Browser/Device | Q1: Status | R1: Defect ID | S1: Remarks
A2: PS-MTH-001 | B2: Math | C2: RTP | D2: Total RTP | E2: Verify total game RTP from a large simulation matches the math file | F2: Math simulation harness / RGS bulk-play tool (certified RNG, production math R7.1) | G2: Math: total RTP 96.98864% (1e9 sims); SD 16.80 x bet. 99% CI half-width = 2.576 x 16.80 / sqrt(N): N=1e8 => +/-0.433%; N=1e9 => +/-0.137% | H2: 1. Run N=1e9 base-game spins at bet 20 credits with random FS choice policy as used in math (see OBS-14) 2. Compute RTP = total win / total bet | I2: Simulated RTP within 96.98864% +/- 0.137% (99% CI). Fail outside the interval | K2: P0 | L2: Critical | M2: Math | N2: Yes | O2: QA / Staging (Game Client + RGS) | P2: N/A (RGS / Simulation) | Q2: Not Run | S2: Ref: M-01, M-03, GR-54 | OBS-14
A3: PS-MTH-002 | B3: Math | C3: RTP | D3: Base game RTP component | E3: Verify base game (non-FS) RTP contribution | F3: Math simulation harness / RGS bulk-play tool (certified RNG, production math R7.1) | G3: Math: base game RTP 68.92386% | H3: 1. From the same simulation sum base-game wins only 2. Divide by total bet | I3: Base RTP within 68.924% +/- statistical tolerance | K3: P0 | L3: Critical | M3: Math | N3: Yes | O3: QA / Staging (Game Client + RGS) | P3: N/A (RGS / Simulation) | Q3: Not Run | S3: Ref: M-01
A4: PS-MTH-003 | B4: Math | C4: RTP | D4: FS RTP component | E4: Verify Free Spins RTP contribution | F4: Math simulation harness / RGS bulk-play tool (certified RNG, production math R7.1) | G4: Math: FS RTP 28.06479%; avg FS win per trigger = 75.46x bet (E5) | H4: 1. Sum FS wins / total bet 2. Compute mean FS win per trigger / bet | I4: FS RTP ~28.065%; mean FS win ~75.46x bet within tolerance | K4: P0 | L4: Critical | M4: Math | N4: Yes | O4: QA / Staging (Game Client + RGS) | P4: N/A (RGS / Simulation) | Q4: Not Run | S4: Ref: M-01, M-18
A5: PS-MTH-004 | B5: Math | C5: RTP | D5: Per FS option RTP | E5: Verify RTP of Sticky Wilds FS and Raining Wilds FS when chosen at natural trigger | F5: Math simulation harness / RGS bulk-play tool (certified RNG, production math R7.1) | G5: Math file does not publish separate natural-trigger RTP per FS option | H5: 1. Simulate always-Sticky policy 2. Simulate always-Raining policy 3. Compute RTP for each | I5: Requires Specification/Confirmation: Expected per-option RTP values must be supplied by math provider. Both options must meet jurisdiction minimum RTP | K5: P0 | L5: Critical | M5: Math | N5: Yes | O5: QA / Staging (Game Client + RGS) | P5: N/A (RGS / Simulation) | Q5: Not Run | S5: Ref: M-01, GR-16 | OBS-14
A6: PS-MTH-005 | B6: Math | C6: RTP | D6: Buy FG1 RTP (Raining Wilds) | E6: Verify RTP of Buy Feature for FG1 (Raining Wilds: 15/18/25/30 FS) | F6: Math simulation harness / RGS bulk-play tool (certified RNG, production math R7.1) | G6: Math: Buy FG1 RTP 97.08362% (1e7 sims), SD 1.618 per buy (x cost). Cost 100x bet | H6: 1. Simulate 1e7 buys at bet 20 (cost 2000) 2. RTP = total win / total cost | I6: RTP within 97.084% +/- 2.576 x 1.618/sqrt(1e7) = +/-0.13% | K6: P0 | L6: Critical | M6: Math | N6: Yes | O6: QA / Staging (Game Client + RGS) | P6: N/A (RGS / Simulation) | Q6: Not Run | S6: Ref: M-15, GR-55
A7: PS-MTH-006 | B7: Math | C7: RTP | D7: Buy FG2 RTP (Sticky Wilds) | E7: Verify RTP of Buy Feature for FG2 (Sticky Wilds: 7/12/15/20 FS) | F7: Math simulation harness / RGS bulk-play tool (certified RNG, production math R7.1) | G7: Math: Buy FG2 RTP 97.10962%, SD 3.711 per buy | H7: 1. Simulate 1e7 buys 2. Compute RTP | I7: RTP within 97.110% +/- 2.576 x 3.711/sqrt(1e7) = +/-0.30% | K7: P0 | L7: Critical | M7: Math | N7: Yes | O7: QA / Staging (Game Client + RGS) | P7: N/A (RGS / Simulation) | Q7: Not Run | S7: Ref: M-16, GR-55
A8: PS-MTH-007 | B8: Math | C8: RTP | D8: Buy RTP >= base | E8: Verify Buy Feature RTP is not lower than base game RTP where jurisdiction requires | F8: Math summary | G8: Base 96.99%; Buy FG1 97.08%; Buy FG2 97.11% | H8: 1. Compare values | I8: Both Buy RTPs >= base RTP (97.08 and 97.11 >= 96.99): Pass | K8: P1 | L8: High | M8: Math | N8: No | O8: QA / Staging (Game Client + RGS) | P8: N/A (RGS / Simulation) | Q8: Not Run | S8: Ref: M-01, M-15, M-16
A9: PS-MTH-008 | B9: Math | C9: Hit Frequency | D9: Base hit frequency | E9: Verify hit frequency of winning base rounds | F9: Math simulation harness / RGS bulk-play tool (certified RNG, production math R7.1) | G9: Math: 31.6018% (1 in 3.164). 99% CI at N=1e7: +/-0.038% | H9: 1. Simulate 1e7 base spins 2. Count rounds with win > 0 | I9: Hit frequency within 31.602% +/- 0.038% | K9: P1 | L9: High | M9: Math | N9: Yes | O9: QA / Staging (Game Client + RGS) | P9: N/A (RGS / Simulation) | Q9: Not Run | S9: Ref: M-02
A10: PS-MTH-009 | B10: Math | C10: Hit Frequency | D10: Buy hit frequency | E10: Verify hit frequency of bought features | F10: Math simulation harness / RGS bulk-play tool (certified RNG, production math R7.1) | G10: Math: Buy FG1 99.99702%; Buy FG2 97.41966% | H10: 1. Simulate 1e7 buys per option 2. Count features with total win > 0 | I10: Values within statistical tolerance of math | K10: P2 | L10: Medium | M10: Math | N10: Yes | O10: QA / Staging (Game Client + RGS) | P10: N/A (RGS / Simulation) | Q10: Not Run | S10: Ref: M-15, M-16
A11: PS-MTH-010 | B11: Math | C11: Volatility | D11: Volatility index | E11: Verify volatility index / SD from simulation | F11: Math simulation harness / RGS bulk-play tool (certified RNG, production math R7.1) | G11: Math: SD 16.80; VI 90%=27.64, 95%=32.93, 99%=43.28 | H11: 1. Compute SD of round win (x bet) | I11: SD within +/-5% of 16.80; volatility classification in marketing material consistent (high volatility) | K11: P2 | L11: Medium | M11: Math | N11: Yes | O11: QA / Staging (Game Client + RGS) | P11: N/A (RGS / Simulation) | Q11: Not Run | S11: Ref: M-03
A12: PS-MTH-011 | B12: Math | C12: FS Trigger | D12: Trigger frequency | E12: Verify base game Free Spins trigger frequency | F12: Math simulation harness / RGS bulk-play tool (certified RNG, production math R7.1) | G12: Math: 1 in 268.89 spins (p = 0.003719). N=1e8 => expected 371,897 triggers; 99% CI +/- 1,571 | H12: 1. Simulate 1e8 spins 2. Count triggers | I12: Trigger count within expected +/- 99% CI | K12: P0 | L12: Critical | M12: Math | N12: Yes | O12: QA / Staging (Game Client + RGS) | P12: N/A (RGS / Simulation) | Q12: Not Run | S12: Ref: M-10, GR-14
A13: PS-MTH-012 | B13: Math | C13: FS Trigger | D13: Trigger by reel set | E13: Verify only reel sets BG1 and BG6 can produce a Free Spins trigger | F13: Math simulation harness / RGS bulk-play tool (certified RNG, production math R7.1) | G13: Math: FG trigger odds BG1 1 in 57.10, BG6 1 in 2.44, BG2-5/7-9 infinite | H13: 1. Log reel set ID per spin 2. Cross-tab triggers by reel set | I13: All triggers come from BG1 or BG6; observed odds within tolerance of 57.10 and 2.44 | K13: P1 | L13: High | M13: Math | N13: Yes | O13: QA / Staging (Game Client + RGS) | P13: N/A (RGS / Simulation) | Q13: Not Run | S13: Ref: M-09, M-10
... A64: PS-MTH-063 | B64: Math | C64: FS | D64: No natural wild on FS strips | E64: Verify Wilds in FS come only from feature placement (FS reel strips contain no WC) | F64: FG strips | G64: WC weight 0 on FG1/FG2 strips | H64: 1. Review strips | I64: No WC on FS strips | K64: P2 | L64: Medium | M64: Math | N64: No | O64: QA / Staging (Game Client + RGS) | P64: N/A (RGS / Simulation) | Q64: Not Run | S64: Ref: M-11, M-12

Sheet Feature Testing
A1: Test Case ID | B1: Module | C1: Feature | D1: Sub-Feature | E1: Test Scenario | F1: Preconditions | G1: Test Data | H1: Detailed Test Steps | I1: Expected Result | J1: Actual Result | K1: Priority | L1: Severity | M1: Test Type | N1: Automation Candidate | O1: Environment | P1: Browser/Device | Q1: Status | R1: Defect ID | S1: Remarks
A2: PS-FEA-001 | B2: Feature | C2: Sticky Wilds FS | D2: Min trigger | E2: Verify minimum trigger (3 BN) starts Sticky Wilds FS with 7 spins | F2: Forced 3 BN trigger | G2: 3 BN | H2: 1. Trigger 2. Select Sticky Wilds | I2: FS intro shown; counter 7; feature UI (counter, total win) visible | K2: P0 | L2: Critical | M2: Positive | N2: Yes | O2: QA / Staging (Game Client + RGS) | P2: Desktop + Mobile (all supported) | Q2: Not Run | S2: Ref: GR-05, GR-17, M-12
A3: PS-FEA-002 | B3: Feature | C3: Sticky Wilds FS | D3: Max trigger | E3: Verify maximum trigger (6 BN) starts Sticky Wilds FS with 20 spins | F3: Forced 6 BN trigger (1 on each reel) | G3: 6 BN | H3: 1. Trigger 2. Select option | I3: Counter 20 | K3: P0 | L3: Critical | M3: Boundary | N3: Yes | O3: QA / Staging (Game Client + RGS) | P3: Desktop + Mobile (all supported) | Q3: Not Run | S3: Ref: GR-05, GR-17, M-12 | OBS-16
A4: PS-FEA-003 | B4: Feature | C4: Sticky Wilds FS | D4: Completion | E4: Verify Sticky Wilds FS ends after the last spin and shows total feature win, then returns to base game | F4: Feature in progress | G4: Any | H4: 1. Play all spins 2. Observe end screen 3. Dismiss | I4: Counter reaches 0; summary shows total FS win = sum of spin wins; balance credited; base game restored at same bet | K4: P0 | L4: Critical | M4: Positive | N4: Yes | O4: QA / Staging (Game Client + RGS) | P4: Desktop + Mobile (all supported) | Q4: Not Run | S4: Ref: GR-05, GR-17, GR-12
A5: PS-FEA-004 | B5: Feature | C5: Sticky Wilds FS | D5: Counter | E5: Verify the Free Spins counter decrements by exactly 1 per spin in Sticky Wilds FS | F5: Feature in progress | G5: Award 7 | H5: 1. Observe counter before and after each spin | I5: Counter decrements by 1 each spin; never skips or repeats; no negative values | K5: P1 | L5: High | M5: Positive | N5: Yes | O5: QA / Staging (Game Client + RGS) | P5: Desktop + Mobile (all supported) | Q5: Not Run | S5: Ref: GR-05, GR-17
A6: PS-FEA-005 | B6: Feature | C6: Sticky Wilds FS | D6: Zero win feature | E6: Verify Sticky Wilds FS with no wins completes correctly showing total 0.00 | F6: Forced all-losing FS | G6: Award 7 | H6: 1. Play feature | I6: Feature ends with total 0.00; no credit transaction or 0.00 credit per RGS spec; base game restored | K6: P1 | L6: High | M6: Boundary | N6: Yes | O6: QA / Staging (Game Client + RGS) | P6: Desktop Chrome (latest) | Q6: Not Run | S6: Ref: GR-05, GR-17
A7: PS-FEA-006 | B7: Feature | C7: Sticky Wilds FS | D7: No retrigger | E7: Verify Bonus symbols do not appear and feature cannot retrigger in Sticky Wilds FS | F7: Feature in progress | G7: Award 20 | H7: 1. Play full feature observing reels | I7: No BN lands; no additional spins awarded | K7: P0 | L7: Critical | M7: Negative | N7: Yes | O7: QA / Staging (Game Client + RGS) | P7: Desktop + Mobile (all supported) | Q7: Not Run | S7: Ref: GR-18, M-08
A8: PS-FEA-007 | B8: Feature | C8: Sticky Wilds FS | D8: Bet | E8: Verify Sticky Wilds FS plays at trigger bet with no per-spin debit | F8: Trigger at max bet | G8: Max bet | H8: 1. Trigger at max bet 2. Play feature 3. Check balance during feature | I8: No debits; wins scaled to max bet | K8: P0 | L8: Critical | M8: Positive | N8: Yes | O8: QA / Staging (Game Client + RGS) | P8: Desktop + Mobile (all supported) | Q8: Not Run | S8: Ref: GR-15
A9: PS-FEA-008 | B9: Feature | C9: Sticky Wilds FS | D9: Win accumulation | E9: Verify total win meter accumulates each spin win during Sticky Wilds FS | F9: Forced wins on spins 1 and 3 | G9: Spin1 1.50, Spin3 3.00 | H9: 1. Play 2. Observe total meter | I9: Meter 1.50 after spin 1, 4.50 after spin 3; final summary 4.50 | K9: P0 | L9: Critical | M9: Positive | N9: Yes | O9: QA / Staging (Game Client + RGS) | P9: Desktop + Mobile (all supported) | Q9: Not Run | S9: Ref: GR-12
A10: PS-FEA-009 | B10: Feature | C10: Sticky Wilds FS | D10: Crediting timing | E10: Verify when Sticky Wilds FS winnings reach the player balance | F10: Feature in progress | G10: Forced wins | H10: 1. Note balance before feature 2. Observe balance during and after | I10: Requires Specification/Confirmation: Rules state 'All Free Spins winnings are awarded when the feature ends' under Raining Wilds only (OBS-08). Expected: balance unchanged during feature; credited once at end | K10: P0 | L10: Critical | M10: Positive | N10: Yes | O10: QA / Staging (Game Client + RGS) | P10: Desktop + Mobile (all supported) | Q10: Not Run | S10: Ref: GR-12 | OBS-08
A11: PS-FEA-010 | B11: Feature | C11: Sticky Wilds FS | D11: Refresh mid-feature | E11: Verify Sticky Wilds FS resumes after browser refresh with same remaining spins, wilds and total win | F11: Feature at spin 3 of 7 | G11: N/A | H11: 1. Refresh page after spin 3 completes 2. Reload game | I11: Feature resumes at spin 4; remaining count, accumulated win and (for Sticky) all sticky wilds with multipliers restored | K11: P0 | L11: Critical | M11: Recovery | N11: Yes | O11: QA / Staging (Game Client + RGS) | P11: Desktop + Mobile (all supported) | Q11: Not Run | S11: Ref: GR-56
A12: PS-FEA-011 | B12: Feature | C12: Sticky Wilds FS | D12: Refresh during spin | E12: Verify refresh while a Sticky Wilds FS spin is animating restores the already-determined result | F12: Feature spin in progress | G12: N/A | H12: 1. Start FS spin 2. Refresh before reels stop 3. Reload | I12: Result of that spin shown once (not replayed as new); counter reflects consumed spin; no duplicate win | K12: P0 | L12: Critical | M12: Recovery | N12: Yes | O12: QA / Staging (Game Client + RGS) | P12: Desktop + Mobile (all supported) | Q12: Not Run | S12: Ref: GR-56
A13: PS-FEA-012 | B13: Feature | C13: Sticky Wilds FS | D13: Max win in feature | E13: Verify reaching max win cap during Sticky Wilds FS ends the feature immediately | F13: Forced outcome exceeding cap | G13: Cap TBC | H13: 1. Force 2. Play | I13: Feature ends at cap; summary shows cap amount; remaining spins forfeited per rules | K13: P0 | L13: Critical | M13: Boundary | N13: Yes | O13: QA / Staging (Game Client + RGS) | P13: Desktop Chrome (latest) | Q13: Not Run | S13: Ref: GR-29 | OBS-09
... A60: PS-FEA-059 | B60: Feature | C60: Feature Recovery | D60: Feature end screen refresh | E60: Verify refresh on FS summary screen does not credit twice | F60: Summary screen visible | G60: Total 25.00 | H60: 1. Refresh 2. Reload | I60: Balance credited once; game returns to base idle or summary shown once | K60: P0 | L60: Critical | M60: Recovery | N60: Yes | O60: QA / Staging (Game Client + RGS) | P60: Desktop + Mobile (all supported) | Q60: Not Run | S60: Ref: GR-12, GR-56

Sheet Edge & Boundary Cases
A1: Test Case ID | B1: Module | C1: Feature | D1: Sub-Feature | E1: Test Scenario | F1: Preconditions | G1: Test Data | H1: Detailed Test Steps | I1: Expected Result | J1: Actual Result | K1: Priority | L1: Severity | M1: Test Type | N1: Automation Candidate | O1: Environment | P1: Browser/Device | Q1: Status | R1: Defect ID | S1: Remarks
A2: PS-EDG-001 | B2: Edge/Boundary | C2: Bet | D2: Min bet exact balance | E2: Verify spin is accepted at minimum bet when balance equals exactly the minimum bet and balance becomes 0.00 on loss | F2: Balance = min bet | G2: Min bet (TBC, e.g. 0.20); balance 0.20 | H2: 1. Set min bet 2. Spin (forced loss) | I2: Spin accepted; debit 0.20 once; balance 0.00; Play disabled or insufficient funds on next attempt | K2: P0 | L2: Critical | M2: Boundary | N2: Yes | O2: QA / Staging (Game Client + RGS) | P2: Desktop + Mobile (all supported) | Q2: Not Run | S2: Ref: GR-28, GR-22 | OBS-09
A3: PS-EDG-002 | B3: Edge/Boundary | C3: Bet | D3: Max bet exact balance | E3: Verify spin at maximum bet with balance exactly equal to max bet | F3: Balance = max bet | G3: Max bet (TBC) | H3: 1. Set max bet 2. Spin | I3: Accepted; single debit; balance updated with any win | K3: P0 | L3: Critical | M3: Boundary | N3: Yes | O3: QA / Staging (Game Client + RGS) | P3: Desktop + Mobile (all supported) | Q3: Not Run | S3: Ref: GR-28 | OBS-09
A4: PS-EDG-003 | B4: Edge/Boundary | C4: Balance | D4: Below min bet | E4: Verify spin is blocked when balance is 0.01 below the selected bet | F4: Balance = bet - 0.01 | G4: Bet 1.00; balance 0.99 | H4: 1. Spin | I4: Spin rejected; insufficient funds message; no debit | K4: P0 | L4: Critical | M4: Negative | N4: Yes | O4: QA / Staging (Game Client + RGS) | P4: Desktop + Mobile (all supported) | Q4: Not Run | S4: Ref: GR-22
A5: PS-EDG-004 | B5: Edge/Boundary | C5: Balance | D5: Zero balance | E5: Verify game behaviour with zero balance on launch | F5: Wallet 0.00 | G5: 0.00 | H5: 1. Launch 2. Press Play | I5: Game loads; Play rejected with insufficient funds and deposit link if configured; no RGS bet | K5: P0 | L5: Critical | M5: Negative | N5: Yes | O5: QA / Staging (Game Client + RGS) | P5: Desktop + Mobile (all supported) | Q5: Not Run | S5: Ref: GR-46
A6: PS-EDG-005 | B6: Edge/Boundary | C6: Balance | D6: Balance below bet, lower bet allowed | E6: Verify player can lower bet to continue playing when balance below current bet | F6: Balance 0.50, bet 1.00 | G6: Min bet 0.20 | H6: 1. Lower bet to 0.20 2. Spin | I6: Spin accepted at 0.20 | K6: P1 | L6: High | M6: Boundary | N6: Yes | O6: QA / Staging (Game Client + RGS) | P6: Desktop + Mobile (all supported) | Q6: Not Run | S6: Ref: GR-20
A7: PS-EDG-006 | B7: Edge/Boundary | C7: Buy | D7: Exact buy balance | E7: Verify Buy accepted when balance equals exactly 100x bet | F7: Balance 100.00, bet 1.00 | H7: 1. Buy | I7: Accepted; balance 0.00 before feature wins | K7: P0 | L7: Critical | M7: Boundary | N7: Yes | O7: QA / Staging (Game Client + RGS) | P7: Desktop + Mobile (all supported) | Q7: Not Run | S7: Ref: GR-36
A8: PS-EDG-007 | B8: Edge/Boundary | C8: Buy | D8: Min bet buy | E8: Verify Buy at minimum bet costs 100 x min bet | F8: Min bet | H8: 1. Open Buy at min bet | I8: Cost = 100 x min bet | K8: P1 | L8: High | M8: Boundary | N8: Yes | O8: QA / Staging (Game Client + RGS) | P8: Desktop + Mobile (all supported) | Q8: Not Run | S8: Ref: GR-36, GR-28 | OBS-09
A9: PS-EDG-008 | B9: Edge/Boundary | C9: Buy | D9: Max bet buy | E9: Verify Buy at maximum bet and display of large cost | F9: Max bet; sufficient balance | H9: 1. Open Buy at max bet 2. Confirm | I9: Cost = 100 x max bet shown fully formatted; single debit | K9: P1 | L9: High | M9: Boundary | N9: Yes | O9: QA / Staging (Game Client + RGS) | P9: Desktop + Mobile (all supported) | Q9: Not Run | S9: Ref: GR-36, GR-28
A10: PS-EDG-009 | B10: Edge/Boundary | C10: Win | D10: Large win display | E10: Verify display of a large win (>= 10,000x bet) with full digits and separators | F10: Forced large FS win | G10: Bet max; win 10,000x bet | H10: 1. Force 2. Play | I10: Win and balance shown fully; no overflow or scientific notation; Big Win sequence plays | K10: P0 | L10: Critical | M10: Boundary | N10: Yes | O10: QA / Staging (Game Client + RGS) | P10: Desktop + Mobile (all supported) | Q10: Not Run | S10: Ref: GR-25
A11: PS-EDG-010 | B11: Edge/Boundary | C11: Win | D11: Max win exact | E11: Verify win equal to the cap exactly is paid in full without truncation message error | F11: Forced win = cap | G11: Cap TBC | H11: 1. Force | I11: Win credited = cap; max win message per spec | K11: P0 | L11: Critical | M11: Boundary | N11: Yes | O11: QA / Staging (Game Client + RGS) | P11: Desktop + Mobile (all supported) | Q11: Not Run | S11: Ref: GR-29 | OBS-09
A12: PS-EDG-011 | B12: Edge/Boundary | C12: Win | D12: Max win +0.01 | E12: Verify win of cap + 0.01 is truncated to cap | F12: Forced | G12: Cap + 0.01 | H12: 1. Force | I12: Credited amount = cap | K12: P0 | L12: Critical | M12: Boundary | N12: Yes | O12: QA / Staging (Game Client + RGS) | P12: Desktop + Mobile (all supported) | Q12: Not Run | S12: Ref: GR-29 | OBS-09
A13: PS-EDG-012 | B13: Edge/Boundary | C13: Win | D13: Cap reached on triggering spin | E13: Verify base spin hitting cap while also landing 3 BN | F13: Forced | G13: Base win >= cap with 3 BN | H13: 1. Force | I13: Requires Specification/Confirmation: Expected: cap credited, FS not played (round ends) | K13: P1 | L13: High | M13: Boundary | N13: Yes | O13: QA / Staging (Game Client + RGS) | P13: Desktop + Mobile (all supported) | Q13: Not Run | S13: Ref: GR-29 | OBS-09
A14: PS-EDG-013 | B14: Edge/Boundary | C14: Win | D14: Many simultaneous wins | E14: Verify a spin with wins on 5+ symbols and thousands of ways evaluates and presents correctly | F14: Forced | G14: 7 rows all reels, mixed symbols | H14: 1. Force 2. Spin | I14: Total equals server; presentation cycles all wins; no freeze | K14: P1 | L14: High | M14: Boundary | N14: Yes | O14: QA / Staging (Game Client + RGS) | P14: Desktop + Mobile (all supported) | Q14: Not Run | S14: Ref: GR-25, GR-01
A15: PS-EDG-014 | B15: Edge/Boundary | C15: Win | D15: Max ways all same symbol | E15: Verify 117,649 ways of AA 6oak with no wilds | F15: Forced | G15: All 42 positions AA, bet 1.00 => 117,649 x 7.50 = 882,367.50 | H15: 1. Force | I15: Win 882,367.50 before cap; cap applied if configured lower | K15: P1 | L15: High | M15: Boundary | N15: Yes | O15: QA / Staging (Game Client + RGS) | P15: Desktop + Mobile (all supported) | Q15: Not Run | S15: Ref: GR-01, M-05, GR-29
A16: PS-EDG-015 | B16: Edge/Boundary | C16: Wild | D16: Max multiplier product | E16: Verify extreme multiplier product in Sticky FS (e.g. 28 stickies x3) is computed without overflow | F16: Forced FS | G16: Reels 2-5 all sticky x3 (7 rows) => product per way 3^4 = 81 per way; ways 7^6 | H16: 1. Force | I16: Server computes exact value; cap applied; no overflow/NaN | K16: P0 | L16: Critical | M16: Boundary | N16: Yes | O16: QA / Staging (Game Client + RGS) | P16: Desktop + Mobile (all supported) | Q16: Not Run | S16: Ref: GR-13, GR-29
A17: PS-EDG-016 | B17: Edge/Boundary | C17: Bonus | D17: Exactly 3 BN at max rows | E17: Verify 3 BN trigger when reels are at 7 rows | F17: Forced | G17: 3 BN, rows all 7 | H17: 1. Force | I17: Trigger | K17: P2 | L17: Medium | M17: Boundary | N17: Yes | O17: QA / Staging (Game Client + RGS) | P17: Desktop + Mobile (all supported) | Q17: Not Run | S17: Ref: GR-14
A18: PS-EDG-017 | B18: Edge/Boundary | C18: Bonus | D18: BN with min rows | E18: Verify 6 BN trigger with all reels at 2 rows | F18: Forced | G18: 6 BN, rows all 2 | H18: 1. Force | I18: Trigger with 6 BN award | K18: P2 | L18: Medium | M18: Boundary | N18: Yes | O18: QA / Staging (Game Client + RGS) | P18: Desktop + Mobile (all supported) | Q18: Not Run | S18: Ref: GR-14, GR-17
A19: PS-EDG-018 | B19: Edge/Boundary | C19: Bonus | D19: Two BN on same reel | E19: Verify whether two Bonus symbols can appear on one reel | F19: Strip review / forced | G19: N/A | H19: 1. Review strips for adjacent BN 2. Try force | I19: Requires Specification/Confirmation: Max BN per reel not defined (OBS-16). Expected per math: max 1 per reel visible | K19: P2 | L19: Medium | M19: Boundary | N19: No | O19: QA / Staging (Game Client + RGS) | P19: Desktop + Mobile (all supported) | Q19: Not Run | S19: Ref: GR-14 | OBS-16
A20: PS-EDG-019 | B20: Edge/Boundary | C20: Spin | D20: Spam Play | E20: Verify spam clicking Play (10 clicks/sec for 3s) starts only sequential rounds | F20: Bet 1.00 | H20: 1. Click Play repeatedly | I20: No overlapping rounds; each round debited once; no duplicate RGS requests | K20: P0 | L20: Critical | M20: Negative | N20: Yes | O20: QA / Staging (Game Client + RGS) | P20: Desktop + Mobile (all supported) | Q20: Not Run | S20: Ref: GR-22
A21: PS-EDG-020 | B21: Edge/Boundary | C21: Spin | D21: Space + click | E21: Verify pressing space and clicking Play simultaneously starts one round | F21: Desktop | H21: 1. Press space and click Play at same time | I21: One round only | K21: P1 | L21: High | M21: Negative | N21: Yes | O21: QA / Staging (Game Client + RGS) | P21: Desktop Chrome (latest) | Q21: Not Run | S21: Ref: GR-44
A22: PS-EDG-021 | B22: Edge/Boundary | C22: Spin | D22: Click during win | E22: Verify clicking Play during win presentation skips presentation and starts next round only once | F22: Win presentation running | H22: 1. Click Play during presentation | I22: Presentation skipped or next round starts per spec; win already credited; no double credit | K22: P1 | L22: High | M22: Boundary | N22: Yes | O22: QA / Staging (Game Client + RGS) | P22: Desktop + Mobile (all supported) | Q22: Not Run | S22: Ref: GR-22
A23: PS-EDG-022 | B23: Edge/Boundary | C23: Spin | D23: Click during transition | E23: Verify inputs during FS intro/outro transitions are ignored | F23: FS transition | H23: 1. Click Play/Bet/Menu during transition | I23: No action; transition completes; no stray spin | K23: P1 | L23: High | M23: Negative | N23: Yes | O23: QA / Staging (Game Client + RGS) | P23: Desktop + Mobile (all supported) | Q23: Not Run | S23: Ref: GR-16
A24: PS-EDG-023 | B24: Edge/Boundary | C24: Spin | D24: Buy during spin | E24: Verify Buy button disabled while reels spin | F24: Spin in progress | H24: 1. Click Buy during spin | I24: No interface opens | K24: P1 | L24: High | M24: Negative | N24: Yes | O24: QA / Staging (Game Client + RGS) | P24: Desktop + Mobile (all supported) | Q24: Not Run | S24: Ref: GR-32
A25: PS-EDG-024 | B25: Edge/Boundary | C25: Auto Spin | D25: Spend limit boundary | E25: Verify Auto Spin stops exactly when spend limit equals cumulative stake | F25: Bet 1.00 | G25: Spend limit 3.00 | H25: 1. Set 10 spins, limit 3.00 2. Force losses | I25: Requires Specification/Confirmation: Expected: 3 rounds then stop (limit inclusive) - confirm inclusive/exclusive | K25: P1 | L25: High | M25: Boundary | N25: Yes | O25: QA / Staging (Game Client + RGS) | P25: Desktop + Mobile (all supported) | Q25: Not Run | S25: Ref: GR-40 | OBS-21
A26: PS-EDG-025 | B26: Edge/Boundary | C26: Auto Spin | D26: Min/max count | E26: Verify the smallest and largest auto spin count options | F26: Auto menu | G26: Options per config | H26: 1. Select min 2. Run 3. Select max 4. Stop after 5 | I26: Counts honoured | K26: P2 | L26: Medium | M26: Boundary | N26: Yes | O26: QA / Staging (Game Client + RGS) | P26: Desktop + Mobile (all supported) | Q26: Not Run | S26: Ref: GR-38
A27: PS-EDG-026 | B27: Edge/Boundary | C27: Auto Spin | D27: Feature on last auto spin | E27: Verify FS triggered on the last auto spin completes and Auto Spin ends after | F27: Auto 5, trigger on 5th | H27: 1. Run | I27: Feature completes; Auto ends; remaining 0 | K27: P1 | L27: High | M27: Boundary | N27: Yes | O27: QA / Staging (Game Client + RGS) | P27: Desktop + Mobile (all supported) | Q27: Not Run | S27: Ref: GR-43
A28: PS-EDG-027 | B28: Edge/Boundary | C28: Auto Spin | D28: Stop pressed during FS | E28: Verify Stop pressed during auto-triggered FS | F28: Auto + FS | H28: 1. Press Stop during FS | I28: FS continues to completion (cannot be abandoned); auto stops after | K28: P1 | L28: High | M28: Boundary | N28: Yes | O28: QA / Staging (Game Client + RGS) | P28: Desktop + Mobile (all supported) | Q28: Not Run | S28: Ref: GR-43
A29: PS-EDG-028 | B29: Edge/Boundary | C29: Free Spins | D29: Last spin refresh | E29: Verify refresh during the last Free Spin | F29: Last FS spinning | H29: 1. Refresh | I29: Last result shown once; summary; single credit | K29: P0 | L29: Critical | M29: Recovery | N29: Yes | O29: QA / Staging (Game Client + RGS) | P29: Desktop + Mobile (all supported) | Q29: Not Run | S29: Ref: GR-56
A30: PS-EDG-029 | B30: Edge/Boundary | C30: Free Spins | D30: Refresh immediately after trigger | E30: Verify refresh immediately after 3 BN land (before choice) | F30: Trigger | H30: 1. Refresh within 500ms | I30: Choice screen restored | K30: P0 | L30: Critical | M30: Recovery | N30: Yes | O30: QA / Staging (Game Client + RGS) | P30: Desktop + Mobile (all supported) | Q30: Not Run | S30: Ref: GR-56, GR-16
A31: PS-EDG-030 | B31: Edge/Boundary | C31: Session | D31: Expired session spin | E31: Verify spin with expired session token | F31: Session expired by operator | H31: 1. Press Play | I31: Error shown; no debit; prompt to reload | K31: P0 | L31: Critical | M31: Negative | N31: Yes | O31: QA / Staging (Game Client + RGS) | P31: Desktop + Mobile (all supported) | Q31: Not Run | S31: Ref: GR-56
A32: PS-EDG-031 | B32: Edge/Boundary | C32: Session | D32: Timeout during FS | E32: Verify session timeout during FS | F32: FS in progress; operator timeout short | H32: 1. Idle until timeout 2. Relaunch | I32: Feature resumes after re-auth | K32: P0 | L32: Critical | M32: Recovery | N32: Yes | O32: QA / Staging (Game Client + RGS) | P32: Desktop + Mobile (all supported) | Q32: Not Run | S32: Ref: GR-56
A33: PS-EDG-032 | B33: Edge/Boundary | C33: Network | D33: Delayed response | E33: Verify UI behaviour with 10s server latency on spin | F33: Throttle 10s | H33: 1. Spin | I33: Reels keep spinning/loader; no second request; result shown when received | K33: P1 | L33: High | M33: Boundary | N33: Yes | O33: QA / Staging (Game Client + RGS) | P33: Desktop + Mobile (all supported) | Q33: Not Run | S33: Ref: GR-22
A34: PS-EDG-033 | B34: Edge/Boundary | C34: Network | D34: Response after timeout | E34: Verify late response after client timeout is reconciled | F34: Client timeout < server latency | H34: 1. Spin with latency > timeout | I34: Client recovers state from server on reconnect; balance consistent | K34: P0 | L34: Critical | M34: Recovery | N34: Yes | O34: QA / Staging (Game Client + RGS) | P34: Desktop + Mobile (all supported) | Q34: Not Run | S34: Ref: GR-56
A35: PS-EDG-034 | B35: Edge/Boundary | C35: Browser | D35: Back button | E35: Verify browser back during spin | F35: Spin in progress | H35: 1. Press back | I35: Leaves game or prompt; round completes server-side; on return state consistent | K35: P1 | L35: High | M35: Recovery | N35: Yes | O35: QA / Staging (Game Client + RGS) | P35: Desktop + Mobile (all supported) | Q35: Not Run | S35: Ref: GR-56
A36: PS-EDG-035 | B36: Edge/Boundary | C36: Browser | D36: Forward/back during FS | E36: Verify back then forward during FS | F36: FS | H36: 1. Back 2. Forward | I36: FS restored | K36: P1 | L36: High | M36: Recovery | N36: Yes | O36: QA / Staging (Game Client + RGS) | P36: Desktop + Mobile (all supported) | Q36: Not Run | S36: Ref: GR-56
A37: PS-EDG-036 | B37: Edge/Boundary | C37: Browser | D37: Multiple tabs | E37: Verify same game opened in two tabs for one session | F37: Tab A and Tab B | H37: 1. Spin in A 2. Spin in B | I37: Either single-session enforced or balance consistent; no double play of same FS | K37: P0 | L37: Critical | M37: Negative | N37: Yes | O37: QA / Staging (Game Client + RGS) | P37: Desktop + Mobile (all supported) | Q37: Not Run | S37: Ref: GR-56
A38: PS-EDG-037 | B38: Edge/Boundary | C38: Currency | D38: Decimal boundary | E38: Verify currency with 0 decimals and with 3 decimals display | F38: Sessions in non-decimal currency if supported | H38: 1. Spin 2. Check fields | I38: Precision correct | K38: P2 | L38: Medium | M38: Boundary | N38: Yes | O38: QA / Staging (Game Client + RGS) | P38: Desktop + Mobile (all supported) | Q38: Not Run | S38: Ref: GR-19
... A41: PS-EDG-040 | B41: Edge/Boundary | C41: Max Ways | D41: 7 rows on all reels FS | E41: Verify FS spin with all reels at 7 rows and sticky wilds | F41: Forced | H41: 1. Force | I41: Correct evaluation; layout fits | K41: P2 | L41: Medium | M41: Boundary | N41: Yes | O41: QA / Staging (Game Client + RGS) | P41: Desktop + Mobile (all supported) | Q41: Not Run | S41: Ref: GR-02, GR-08
A42: PS-EDG-041 | B42: Edge/Boundary | C42: Bet | D42: Bet change right before spin | E42: Verify changing bet and immediately pressing Play uses the new bet | F42: Bet 1.00 | G42: Change to 2.00 then Play within 200ms | H42: 1. Change 2. Spin | I42: Debit 2.00; RGS bet 2.00 | K42: P1 | L42: High | M42: Boundary | N42: Yes | O42: QA / Staging (Game Client + RGS) | P42: Desktop + Mobile (all supported) | Q42: Not Run | S42: Ref: GR-20
A43: PS-EDG-042 | B43: Edge/Boundary | C43: Inactivity | D43: Persistent data 90 days | E43: Verify retention of persistent game data up to 90 days | F43: Time-shift env | G43: 90 days | H43: 1. Create data 2. Shift 89 days 3. Shift 91 days | I43: Requires Specification/Confirmation: Rules: 'may be retained up to 90 days'. Expected behaviour to confirm | K43: P3 | L43: Low | M43: Boundary | N43: No | O43: QA / Staging (Game Client + RGS) | P43: Desktop + Mobile (all supported) | Q43: Not Run | S43: Ref: GR-57

Sheet Regression Suite
A1: Test Case ID | B1: Module | C1: Feature | D1: Sub-Feature | E1: Test Scenario | F1: Preconditions | G1: Test Data | H1: Detailed Test Steps | I1: Expected Result | J1: Actual Result | K1: Priority | L1: Severity | M1: Test Type | N1: Automation Candidate | O1: Environment | P1: Browser/Device | Q1: Status | R1: Defect ID | S1: Remarks
A2: PS-REG-001 | B2: Regression (Functional) | C2: Game Launch | D2: Smoke | Initial load | E2: Verify the game launches from the operator lobby in real-money mode and lands on the base game with correct initial state | F2: Valid player session with funded wallet; game enabled for operator | G2: Balance: 500.00 EUR; default bet as configured | H2: 1. Log in to the operator lobby 2. Launch Pig Style 3. Wait for the loader to complete 4. Observe reels, bet field, balance field and win field | I2: Loader completes without error; 6 reels displayed; balance equals wallet balance (500.00); bet field shows configured default bet; win field shows 0.00 or blank; Play button enabled | K2: P0 | L2: Critical | M2: Regression | N2: Yes | O2: QA / Staging (Game Client + RGS) | P2: Desktop + Mobile (all supported) | Q2: Not Run | S2: Source: PS-FUN-001 (source priority P0) | Execute after: Code, UI, Configuration, CMS, Game engine
A3: PS-REG-002 | B3: Regression (Functional) | C3: Base Game | D3: Smoke | Reel layout | E3: Verify the base game shows 6 reels and each reel displays between 2 and 7 symbols per spin | F3: Base game loaded | G3: Observe 50 spins | H3: 1. Spin 50 times at any bet 2. For each spin, count visible symbol rows on every reel 3. Record min and max per reel | I3: Every reel shows a symbol count in the range 2..7 on every spin; no reel shows 1 or 8+ positions; reel heights vary independently per reel | K3: P0 | L3: Critical | M3: Regression | N3: Yes | O3: QA / Staging (Game Client + RGS) | P3: Desktop + Mobile (all supported) | Q3: Not Run | S3: Source: PS-FUN-005 (source priority P0) | Execute after: Code, UI, Configuration, CMS, Game engine
A4: PS-REG-003 | B4: Regression (Functional) | C4: Base Game | D4: Extended | Ways counter | E4: Verify the ways-to-win counter equals the product of the symbol counts on all 6 reels | F4: Base game loaded; ways counter visible | G4: Example rows [2,3,4,5,6,7] => 2x3x4x5x6x7 = 5,040 ways | H4: 1. Spin until a result is observed 2. Count rows on each reel 3. Multiply counts 4. Compare to on-screen ways counter | I4: Ways counter equals product of reel heights for every spin (e.g. 5,040 for [2,3,4,5,6,7]); counter updates when the reels stop | K4: P2 | L4: Critical | M4: Regression | N4: Yes | O4: QA / Staging (Game Client + RGS) | P4: Desktop + Mobile (all supported) | Q4: Not Run | S4: Source: PS-FUN-006 (source priority P0) | Execute after: Code, UI, Configuration, CMS, Game engine
A5: PS-REG-004 | B5: Regression (Functional) | C5: Spin | D5: Smoke | Start spin | E5: Verify pressing the Play button starts exactly one game round at the selected bet | F5: Balance >= selected bet | G5: Bet: 1.00; Balance: 100.00 | H5: 1. Note balance 2. Press Play once 3. Wait for round to complete | I5: One round starts; balance reduces by exactly 1.00 at spin start; one bet transaction in RGS; reels spin and stop; any win added after evaluation | K5: P0 | L5: Critical | M5: Regression | N5: Yes | O5: QA / Staging (Game Client + RGS) | P5: Desktop + Mobile (all supported) | Q5: Not Run | S5: Source: PS-FUN-009 (source priority P0) | Execute after: Code, UI, Configuration, CMS, Game engine
A6: PS-REG-005 | B6: Regression (Functional) | C6: Bet | D6: Extended | Limits | E6: Verify the increase control is disabled at maximum bet and decrease control disabled at minimum bet | F6: Bet panel open | G6: Min Bet / Max Bet: Requires Specification/Confirmation: values are {{text1}} in rules | H6: 1. Set bet to max; try increase 2. Set bet to min; try decrease | I6: Increase disabled/no effect at max; decrease disabled/no effect at min; bet never leaves configured range | K6: P2 | L6: Critical | M6: Regression | N6: Yes | O6: QA / Staging (Game Client + RGS) | P6: Desktop + Mobile (all supported) | Q6: Not Run | S6: Source: PS-FUN-016 (source priority P0) | Execute after: Code, UI, Configuration, CMS, Game engine
A7: PS-REG-006 | B7: Regression (Functional) | C7: Bet | D7: Extended | Bet lock | E7: Verify bet controls are disabled while reels are spinning and during win presentation | F7: Base game | G7: Bet: 1.00 | H7: 1. Press Play 2. While reels spin, attempt to open bet panel / change bet 3. During win presentation attempt to change bet | I7: Bet controls disabled or ignored during spin; bet of current round unchanged in RGS record | K7: P2 | L7: Critical | M7: Regression | N7: Yes | O7: QA / Staging (Game Client + RGS) | P7: Desktop + Mobile (all supported) | Q7: Not Run | S7: Source: PS-FUN-018 (source priority P0) | Execute after: Code, UI, Configuration, CMS, Game engine
A8: PS-REG-007 | B8: Regression (Functional) | C8: Bet | D8: Extended | Bet lock in Free Spins | E8: Verify bet cannot be changed during Free Spins | F8: Free Spins in progress (forced trigger) | G8: Trigger bet: 1.00 | H8: 1. Trigger Free Spins 2. During feature attempt to open bet panel | I8: Bet controls disabled for the whole feature; all Free Spins evaluated at 1.00 | K8: P2 | L8: Critical | M8: Regression | N8: Yes | O8: QA / Staging (Game Client + RGS) | P8: Desktop + Mobile (all supported) | Q8: Not Run | S8: Source: PS-FUN-019 (source priority P0) | Execute after: Code, UI, Configuration, CMS, Game engine
A9: PS-REG-008 | B9: Regression (Functional) | C9: Balance | D9: Smoke | Debit | E9: Verify the balance is debited by exactly the bet amount once per paid spin | F9: Funded balance | G9: Balance 100.00; Bet 0.20 (or min configured) | H9: 1. Note balance 2. Spin once with a losing result (forced) 3. Note balance | I9: Balance = 100.00 - 0.20 = 99.80; one debit transaction | K9: P0 | L9: Critical | M9: Regression | N9: Yes | O9: QA / Staging (Game Client + RGS) | P9: Desktop + Mobile (all supported) | Q9: Not Run | S9: Source: PS-FUN-020 (source priority P0) | Execute after: Code, UI, Configuration, CMS, Game engine
A10: PS-REG-009 | B10: Regression (Functional) | C10: Balance | D10: Smoke | Credit | E10: Verify a base game win is credited to the balance and shown in the win field | F10: Forced winning outcome | G10: Bet 1.00; outcome AA on reels 1-3 (1 way) => win 1.00 x 15/20 = 0.75 | H10: 1. Note balance B0 2. Spin with forced outcome 3. Read win field and balance | I10: Win field 0.75; final balance = B0 - 1.00 + 0.75; RGS win transaction amount 0.75 | K10: P0 | L10: Critical | M10: Regression | N10: Yes | O10: QA / Staging (Game Client + RGS) | P10: Desktop + Mobile (all supported) | Q10: Not Run | S10: Source: PS-FUN-021 (source priority P0) | Execute after: Code, UI, Configuration, CMS, Game engine
A11: PS-REG-010 | B11: Regression (Functional) | C11: Balance | D11: Core | Display sync | E11: Verify displayed balance matches the wallet balance after each round | F11: Wallet admin access | G11: 10 consecutive rounds | H11: 1. Play 10 rounds 2. After each round compare in-game balance with wallet backend balance | I11: Values match to the cent after every round | K11: P1 | L11: Critical | M11: Regression | N11: Yes | O11: QA / Staging (Game Client + RGS) | P11: Desktop + Mobile (all supported) | Q11: Not Run | S11: Source: PS-FUN-022 (source priority P0) | Execute after: Code, UI, Configuration, CMS, Game engine
A12: PS-REG-011 | B12: Regression (Functional) | C12: Paytable | D12: Extended | Symbol AA | E12: Verify paytable values for symbol AA for 3, 4, 5 and 6 of a kind at the current bet | F12: Game Info / paytable open | G12: Math pays (credits @ bet 20): 6=150, 5=60, 4=40, 3=15. At bet 1.00 => 6=7.50, 5=3.00, 4=2.00, 3=0.75 | H12: 1. Set bet 1.00 2. Open paytable 3. Read values for AA 4. Change bet to 2.00 and re-read | I12: At 1.00: 6x=7.50, 5x=3.00, 4x=2.00, 3x=0.75; at 2.00 all values double; no value shown for 2-of-a-kind (math has no 2oak pay, see OBS-03) | K12: P2 | L12: Critical | M12: Regression | N12: Yes | O12: QA / Staging (Game Client + RGS) | P12: Desktop + Mobile (all supported) | Q12: Not Run | S12: Source: PS-FUN-023 (source priority P0) | Execute after: Code, UI, Configuration, CMS, Game engine
A13: PS-REG-012 | B13: Regression (Functional) | C13: Paytable | D13: Extended | Bet scaling | E13: Verify all paytable values scale linearly when bet changes | F13: Paytable open | G13: Bets: min, 1.00, max | H13: 1. Open paytable at min bet and record all values 2. Repeat at 1.00 and at max | I13: Each value = bet x pay(credits)/20; ratios between bets exactly equal bet ratios; rounding per currency precision | K13: P2 | L13: Critical | M13: Regression | N13: Yes | O13: QA / Staging (Game Client + RGS) | P13: Desktop + Mobile (all supported) | Q13: Not Run | S13: Source: PS-FUN-034 (source priority P0) | Execute after: Code, UI, Configuration, CMS, Game engine
... A100: PS-REG-099 | B100: Regression (Edge/Boundary) | C100: Balance | D100: Core | Zero balance | E100: Verify game behaviour with zero balance on launch | F100: Wallet 0.00 | G100: 0.00 | H100: 1. Launch 2. Press Play | I100: Game loads; Play rejected with insufficient funds and deposit link if configured; no RGS bet | K100: P1 | L100: Critical | M100: Regression | N100: Yes | O100: QA / Staging (Game Client + RGS) | P100: Desktop + Mobile (all supported) | Q100: Not Run | S100: Source: PS-EDG-004 (source priority P0) | Execute after: Code, Wallet, Backend/API
A101: PS-REG-100 | B101: Regression (Edge/Boundary) | C101: Buy | D101: Extended | Exact buy balance | E101: Verify Buy accepted when balance equals exactly 100x bet | F101: Balance 100.00, bet 1.00 | H101: 1. Buy | I101: Accepted; balance 0.00 before feature wins | K101: P2 | L101: Critical | M101: Regression | N101: Yes | O101: QA / Staging (Game Client + RGS) | P101: Desktop + Mobile (all supported) | Q101: Not Run | S101: Source: PS-EDG-006 (source priority P0) | Execute after: Code, Wallet, Backend/API
A102: PS-REG-101 | B102: Regression (Edge/Boundary) | C102: Win | D102: Extended | Max win exact | E102: Verify win equal to the cap exactly is paid in full without truncation message error | F102: Forced win = cap | G102: Cap TBC | H102: 1. Force | I102: Win credited = cap; max win message per spec | K102: P2 | L102: Critical | M102: Regression | N102: Yes | O102: QA / Staging (Game Client + RGS) | P102: Desktop + Mobile (all supported) | Q102: Not Run | S102: Source: PS-EDG-010 (source priority P0) | Execute after: Code, Wallet, Backend/API
A103: PS-REG-102 | B103: Regression (Edge/Boundary) | C103: Win | D103: Extended | Max win +0.01 | E103: Verify win of cap + 0.01 is truncated to cap | F103: Forced | G103: Cap + 0.01 | H103: 1. Force | I103: Credited amount = cap | K103: P2 | L103: Critical | M103: Regression | N103: Yes | O103: QA / Staging (Game Client + RGS) | P103: Desktop + Mobile (all supported) | Q103: Not Run | S103: Source: PS-EDG-011 (source priority P0) | Execute after: Code, Wallet, Backend/API
A104: PS-REG-103 | B104: Regression (Edge/Boundary) | C104: Spin | D104: Core | Spam Play | E104: Verify spam clicking Play (10 clicks/sec for 3s) starts only sequential rounds | F104: Bet 1.00 | H104: 1. Click Play repeatedly | I104: No overlapping rounds; each round debited once; no duplicate RGS requests | K104: P1 | L104: Critical | M104: Regression | N104: Yes | O104: QA / Staging (Game Client + RGS) | P104: Desktop + Mobile (all supported) | Q104: Not Run | S104: Source: PS-EDG-019 (source priority P0) | Execute after: Code, Wallet, Backend/API
A105: PS-REG-104 | B105: Regression (UI/UX) | C105: Text | D105: Extended | Placeholders | E105: Verify no template placeholders like {{text1}} appear anywhere | F105: All screens | H105: 1. Search all text | I105: None present | K105: P2 | L105: Critical | M105: Regression | N105: Yes | O105: QA / Staging (Game Client + RGS) | P105: Desktop + Mobile (all supported) | Q105: Not Run | S105: Source: PS-UI-036 (source priority P0) | Execute after: UI, CMS
A106: PS-REG-105 | B106: Regression (Compatibility) | C106: Compatibility | D106: Extended | Windows 11 / Chrome (latest, latest-1) | E106: Verify full smoke flow on Windows 11 with Chrome (latest, latest-1): load, spin, win, bet change, FS (both types), Buy, Auto Spin, Info, Sound | F106: Device available; funded test account | G106: Bet 1.00 | H106: 1. Launch 2. Spin 10 rounds 3. Change bet 4. Force/trigger FS: Sticky 5. Force/trigger FS: Raining 6. Buy feature 7. Run 5 auto spins 8. Open Info 9. Toggle sound | I106: All steps work with no visual defects, errors or performance issues; balance consistent | K106: P2 | L106: High | M106: Regression | N106: Partial | O106: QA / Staging (Game Client + RGS) | P106: Windows 11 / Chrome (latest, latest-1) | Q106: Not Run | S106: Source: PS-CMP-001 (source priority P0) | Execute after: UI, Game engine
A107: PS-REG-106 | B107: Regression (Compatibility) | C107: Compatibility | D107: Extended | iOS 17/18 iPhone / Safari | E107: Verify full smoke flow on iOS 17/18 iPhone with Safari: load, spin, win, bet change, FS (both types), Buy, Auto Spin, Info, Sound | F107: Device available; funded test account | G107: Bet 1.00 | H107: 1. Launch 2. Spin 10 rounds 3. Change bet 4. Force/trigger FS: Sticky 5. Force/trigger FS: Raining 6. Buy feature 7. Run 5 auto spins 8. Open Info 9. Toggle sound | I107: All steps work with no visual defects, errors or performance issues; balance consistent | K107: P2 | L107: High | M107: Regression | N107: Partial | O107: QA / Staging (Game Client + RGS) | P107: iOS 17/18 iPhone / Safari | Q107: Not Run | S107: Source: PS-CMP-006 (source priority P0) | Execute after: UI, Game engine
A108: PS-REG-107 | B108: Regression (Compatibility) | C108: Compatibility | D108: Extended | Android 13/14 phone / Chrome | E108: Verify full smoke flow on Android 13/14 phone with Chrome: load, spin, win, bet change, FS (both types), Buy, Auto Spin, Info, Sound | F108: Device available; funded test account | G108: Bet 1.00 | H108: 1. Launch 2. Spin 10 rounds 3. Change bet 4. Force/trigger FS: Sticky 5. Force/trigger FS: Raining 6. Buy feature 7. Run 5 auto spins 8. Open Info 9. Toggle sound | I108: All steps work with no visual defects, errors or performance issues; balance consistent | K108: P2 | L108: High | M108: Regression | N108: Partial | O108: QA / Staging (Game Client + RGS) | P108: Android 13/14 phone / Chrome | Q108: Not Run | S108: Source: PS-CMP-009 (source priority P0) | Execute after: UI, Game engine
A109: PS-REG-108 | B109: Regression (Interruption) | C109: Interruption | D109: Core | Refresh | E109: Refresh: during base spin | F109: Spin in progress | G109: Bet 1.00 | H109: 1. Press Play 2. Refresh before reels stop 3. Reload | I109: One debit; result of interrupted round shown or in history; win credited once; no new round | K109: P1 | L109: Critical | M109: Regression | N109: Yes | O109: QA / Staging (Game Client + RGS) | P109: Desktop + Mobile (all supported) | Q109: Not Run | S109: Source: PS-INT-001 (source priority P0) | Execute after: Backend/API, Wallet, Game engine
A110: PS-REG-109 | B110: Regression (Interruption) | C110: Interruption | D110: Core | Refresh | E110: Refresh: during win presentation | F110: Win presenting | G110: Bet 1.00 | H110: 1. Refresh | I110: Win credited once; balance correct | K110: P1 | L110: Critical | M110: Regression | N110: Yes | O110: QA / Staging (Game Client + RGS) | P110: Desktop + Mobile (all supported) | Q110: Not Run | S110: Source: PS-INT-002 (source priority P0) | Execute after: Backend/API, Wallet, Game engine
A111: PS-REG-110 | B111: Regression (Interruption) | C111: Interruption | D111: Smoke | Refresh | E111: Refresh: during Free Spins | F111: FS spin 4/15 | G111: Bet 1.00 | H111: 1. Refresh | I111: Resume at correct spin; total win and wilds preserved | K111: P0 | L111: Critical | M111: Regression | N111: Yes | O111: QA / Staging (Game Client + RGS) | P111: Desktop + Mobile (all supported) | Q111: Not Run | S111: Source: PS-INT-003 (source priority P0) | Execute after: Backend/API, Wallet, Game engine
A112: PS-REG-111 | B112: Regression (Interruption) | C112: Interruption | D112: Core | Refresh | E112: Refresh: on FS choice screen | F112: Choice screen | G112: Bet 1.00 | H112: 1. Refresh | I112: Choice screen restored | K112: P1 | L112: Critical | M112: Regression | N112: Yes | O112: QA / Staging (Game Client + RGS) | P112: Desktop + Mobile (all supported) | Q112: Not Run | S112: Source: PS-INT-004 (source priority P0) | Execute after: Backend/API, Wallet, Game engine
A113: PS-REG-112 | B113: Regression (Interruption) | C113: Interruption | D113: Core | Refresh | E113: Refresh: immediately after Buy confirm | F113: Buy confirmed | G113: Bet 1.00 | H113: 1. Refresh | I113: Single debit; feature resumes | K113: P1 | L113: Critical | M113: Regression | N113: Yes | O113: QA / Staging (Game Client + RGS) | P113: Desktop + Mobile (all supported) | Q113: Not Run | S113: Source: PS-INT-005 (source priority P0) | Execute after: Backend/API, Wallet, Game engine
A114: PS-REG-113 | B114: Regression (Interruption) | C114: Interruption | D114: Core | Close/reopen | E114: Close/reopen: during base spin | F114: Spin | G114: Bet 1.00 | H114: 1. Close tab 2. Reopen | I114: Round completed server-side; balance and history correct | K114: P1 | L114: Critical | M114: Regression | N114: Yes | O114: QA / Staging (Game Client + RGS) | P114: Desktop + Mobile (all supported) | Q114: Not Run | S114: Source: PS-INT-006 (source priority P0) | Execute after: Backend/API, Wallet, Game engine
A115: PS-REG-114 | B115: Regression (Interruption) | C115: Interruption | D115: Core | Close/reopen | E115: Close/reopen: during FS | F115: FS | G115: Bet 1.00 | H115: 1. Close 2. Reopen | I115: FS resumes | K115: P1 | L115: Critical | M115: Regression | N115: Yes | O115: QA / Staging (Game Client + RGS) | P115: Desktop + Mobile (all supported) | Q115: Not Run | S115: Source: PS-INT-007 (source priority P0) | Execute after: Backend/API, Wallet, Game engine
A116: PS-REG-115 | B116: Regression (Interruption) | C116: Interruption | D116: Core | Network loss | E116: Network loss: before spin request | F116: Offline | G116: Bet 1.00 | H116: 1. Disable network 2. Press Play | I116: Error/reconnect message; no debit; no round | K116: P1 | L116: Critical | M116: Regression | N116: Yes | O116: QA / Staging (Game Client + RGS) | P116: Desktop + Mobile (all supported) | Q116: Not Run | S116: Source: PS-INT-008 (source priority P0) | Execute after: Backend/API, Wallet, Game engine
A117: PS-REG-116 | B117: Regression (Interruption) | C117: Interruption | D117: Core | Network loss | E117: Network loss: after request sent, before response | F117: Network drops after request | G117: Bet 1.00 | H117: 1. Spin 2. Drop network 3. Restore | I117: On reconnect state synced; one debit; result displayed; no duplicate | K117: P1 | L117: Critical | M117: Regression | N117: Yes | O117: QA / Staging (Game Client + RGS) | P117: Desktop + Mobile (all supported) | Q117: Not Run | S117: Source: PS-INT-009 (source priority P0) | Execute after: Backend/API, Wallet, Game engine
... A163: PS-REG-162 | B163: Regression (Error Handling) | C163: Error Handling | D163: Extended | Recovery after error | E163: Recovery after error | F163: After each error | G163: Bet 1.00 | H163: 1. Reload | I163: Correct balance and state; no duplicates | K163: P2 | L163: Critical | M163: Regression | N163: Yes | O163: QA / Staging (Game Client + RGS) | P163: Desktop + Mobile (all supported) | Q163: Not Run | S163: Source: PS-ERR-018 (source priority P0) | Execute after: Backend/API, Wallet, Code

Sheet UI-UX Testing
A1: Test Case ID | B1: Module | C1: Feature | D1: Sub-Feature | E1: Test Scenario | F1: Preconditions | G1: Test Data | H1: Detailed Test Steps | I1: Expected Result | J1: Actual Result | K1: Priority | L1: Severity | M1: Test Type | N1: Automation Candidate | O1: Environment | P1: Browser/Device | Q1: Status | R1: Defect ID | S1: Remarks
A2: PS-UI-001 | B2: UI/UX | C2: Loading | D2: Loader | E2: Verify loading screen shows progress and branding and completes without layout jump | F2: Fresh cache | H2: 1. Launch | I2: Progress bar advances to 100%; no flicker; base game appears | K2: P1 | L2: Medium | M2: UI | N2: Partial | O2: QA / Staging (Game Client + RGS) | P2: Desktop + Mobile (all supported) | Q2: Not Run | S2: Ref: GR-01
A3: PS-UI-002 | B3: UI/UX | C3: Layout | D3: Desktop 1920x1080 | E3: Verify base game layout at 1920x1080 | F3: Desktop | G3: 1920x1080 | H3: 1. Launch 2. Inspect all elements | I3: No overlap/cut-off; reels centred; controls readable | K3: P1 | L3: Medium | M3: UI | N3: Partial | O3: QA / Staging (Game Client + RGS) | P3: Desktop Chrome (latest) | Q3: Not Run | S3: Ref: GR-52
A4: PS-UI-003 | B4: UI/UX | C4: Layout | D4: Desktop 1366x768 | E4: Verify layout at 1366x768 | F4: Desktop | G4: 1366x768 | H4: 1. Launch | I4: Scales correctly | K4: P2 | L4: Medium | M4: UI | N4: Partial | O4: QA / Staging (Game Client + RGS) | P4: Desktop Chrome (latest) | Q4: Not Run | S4: Ref: GR-52
A5: PS-UI-004 | B5: UI/UX | C5: Layout | D5: Ultra-wide | E5: Verify layout at 2560x1080 | F5: Desktop | G5: 2560x1080 | H5: 1. Launch | I5: Letterboxing/background fill; no stretch | K5: P3 | L5: Low | M5: UI | N5: Partial | O5: QA / Staging (Game Client + RGS) | P5: Desktop Chrome (latest) | Q5: Not Run | S5: Ref: GR-52
A6: PS-UI-005 | B6: UI/UX | C6: Layout | D6: Portrait mobile | E6: Verify portrait layout on 390x844 | F6: Mobile | G6: iPhone 13/14 | H6: 1. Launch portrait | I6: Reels and controls fit; ways counter visible | K6: P1 | L6: Medium | M6: UI | N6: Partial | O6: QA / Staging (Game Client + RGS) | P6: Mobile (iOS Safari / Android Chrome) | Q6: Not Run | S6: Ref: GR-52
A7: PS-UI-006 | B7: UI/UX | C7: Layout | D7: Landscape mobile | E7: Verify landscape layout on mobile | F7: Mobile | H7: 1. Rotate to landscape | I7: Layout switches; nothing cut off | K7: P1 | L7: Medium | M7: UI | N7: Partial | O7: QA / Staging (Game Client + RGS) | P7: Mobile (iOS Safari / Android Chrome) | Q7: Not Run | S7: Ref: GR-52
A8: PS-UI-007 | B8: UI/UX | C8: Layout | D8: Tablet | E8: Verify layout on iPad portrait and landscape | F8: Tablet | G8: iPad 10th gen | H8: 1. Launch 2. Rotate | I8: Correct scaling | K8: P2 | L8: Medium | M8: UI | N8: Partial | O8: QA / Staging (Game Client + RGS) | P8: Tablet (iPad / Android tablet) | Q8: Not Run | S8: Ref: GR-52
A9: PS-UI-008 | B9: UI/UX | C9: Layout | D9: Window resize | E9: Verify live window resize during idle and during spin | F9: Desktop | H9: 1. Resize window repeatedly | I9: Re-layout without breaking; spin unaffected | K9: P2 | L9: Medium | M9: UI | N9: Partial | O9: QA / Staging (Game Client + RGS) | P9: Desktop Chrome (latest) | Q9: Not Run | S9: Ref: GR-52
A10: PS-UI-009 | B10: UI/UX | C10: Layout | D10: Reel height variation | E10: Verify reels of different heights (2..7) render with correctly sized symbols and aligned top/bottom | F10: Base | H10: 1. Observe 20 spins | I10: Symbols scale per reel height; no overlap with frame | K10: P1 | L10: High | M10: UI | N10: Partial | O10: QA / Staging (Game Client + RGS) | P10: Desktop + Mobile (all supported) | Q10: Not Run | S10: Ref: GR-02
A11: PS-UI-010 | B11: UI/UX | C11: Layout | D11: Ways counter | E11: Verify ways counter is visible and legible at all resolutions | F11: All | H11: 1. Check counter | I11: Readable; formatted with separators | K11: P2 | L11: Medium | M11: UI | N11: Partial | O11: QA / Staging (Game Client + RGS) | P11: Desktop + Mobile (all supported) | Q11: Not Run | S11: Ref: GR-01
A12: PS-UI-011 | B12: UI/UX | C12: Controls | D12: Button states idle | E12: Verify enabled state of Play, Bet, Buy, Turbo, Menu, Info, Sound in idle | F12: Base idle | H12: 1. Inspect | I12: All enabled | K12: P1 | L12: Medium | M12: UI | N12: Partial | O12: QA / Staging (Game Client + RGS) | P12: Desktop + Mobile (all supported) | Q12: Not Run | S12: Ref: GR-52
A13: PS-UI-012 | B13: UI/UX | C13: Controls | D13: Button states spinning | E13: Verify Bet, Buy, Menu disabled while spinning; Stop/Quick Stop enabled | F13: Spinning | H13: 1. Inspect | I13: States correct | K13: P1 | L13: High | M13: UI | N13: Partial | O13: QA / Staging (Game Client + RGS) | P13: Desktop + Mobile (all supported) | Q13: Not Run | S13: Ref: GR-52, GR-31 | OBS-19
A14: PS-UI-013 | B14: UI/UX | C14: Controls | D14: Button states FS | E14: Verify Bet and Buy disabled during FS and Auto Spin | F14: FS | H14: 1. Inspect | I14: Disabled; visual disabled styling | K14: P1 | L14: High | M14: UI | N14: Partial | O14: QA / Staging (Game Client + RGS) | P14: Desktop + Mobile (all supported) | Q14: Not Run | S14: Ref: GR-15
A15: PS-UI-014 | B15: UI/UX | C15: Controls | D15: Hover/press feedback | E15: Verify hover and pressed visuals on desktop | F15: Desktop | H15: 1. Hover each button | I15: Feedback present | K15: P3 | L15: Low | M15: UI | N15: Partial | O15: QA / Staging (Game Client + RGS) | P15: Desktop Chrome (latest) | Q15: Not Run | S15: Ref: GR-52
A16: PS-UI-015 | B16: UI/UX | C16: Controls | D16: Touch targets | E16: Verify all buttons are easily tappable (>= 44x44 pt) | F16: Mobile | H16: 1. Tap each control | I16: No mis-taps | K16: P2 | L16: Medium | M16: UI | N16: Partial | O16: QA / Staging (Game Client + RGS) | P16: Mobile (iOS Safari / Android Chrome) | Q16: Not Run | S16: Ref: GR-52
A17: PS-UI-016 | B17: UI/UX | C17: Controls | D17: Turbo icon states | E17: Verify Turbo enabled/disabled icons match rules table | F17: Base | H17: 1. Toggle Turbo | I17: Icons match documented images | K17: P3 | L17: Low | M17: UI | N17: Partial | O17: QA / Staging (Game Client + RGS) | P17: Desktop + Mobile (all supported) | Q17: Not Run | S17: Ref: GR-37, GR-52
A18: PS-UI-017 | B18: UI/UX | C18: Balance | D18: Balance field | E18: Verify balance field updates at spin start (debit) and after win | F18: Base | H18: 1. Spin with win | I18: Debit then credit visible; final value correct | K18: P1 | L18: High | M18: UI | N18: Partial | O18: QA / Staging (Game Client + RGS) | P18: Desktop + Mobile (all supported) | Q18: Not Run | S18: Ref: GR-19
A19: PS-UI-018 | B19: UI/UX | C19: Win | D19: Win field | E19: Verify win field shows current round total and resets at next spin | F19: Base | H19: 1. Spin win 2. Spin loss | I19: Shows win then resets | K19: P1 | L19: High | M19: UI | N19: Partial | O19: QA / Staging (Game Client + RGS) | P19: Desktop + Mobile (all supported) | Q19: Not Run | S19: Ref: GR-25
A20: PS-UI-019 | B20: UI/UX | C20: Win | D20: Win ticker | E20: Verify win count-up ends exactly on the final win value | F20: Win | G20: Win 12.35 | H20: 1. Observe | I20: Ticker ends 12.35, no overshoot | K20: P1 | L20: High | M20: UI | N20: Partial | O20: QA / Staging (Game Client + RGS) | P20: Desktop + Mobile (all supported) | Q20: Not Run | S20: Ref: GR-25
A21: PS-UI-020 | B21: UI/UX | C21: Win | D21: Big win tiers | E21: Verify Big/Mega/Epic win presentation thresholds | F21: Forced wins at thresholds | G21: Thresholds TBC | H21: 1. Force wins just below and at each threshold | I21: Requires Specification/Confirmation: Thresholds not in rules. Expected: tier shown per art/spec | K21: P2 | L21: Medium | M21: UI | N21: Partial | O21: QA / Staging (Game Client + RGS) | P21: Desktop + Mobile (all supported) | Q21: Not Run | S21: Ref: GR-25 | OBS-22
A22: PS-UI-021 | B22: UI/UX | C22: Win | D22: Win highlight | E22: Verify winning positions are highlighted for every winning way | F22: Forced multi-way win | H22: 1. Observe | I22: All winning positions highlighted; non-winning dimmed | K22: P2 | L22: Medium | M22: UI | N22: Partial | O22: QA / Staging (Game Client + RGS) | P22: Desktop + Mobile (all supported) | Q22: Not Run | S22: Ref: GR-25
A23: PS-UI-022 | B23: UI/UX | C23: FS UI | D23: Counter | E23: Verify FS counter and total win meter visible throughout FS | F23: FS | H23: 1. Observe | I23: Visible and legible on all devices | K23: P1 | L23: High | M23: UI | N23: Partial | O23: QA / Staging (Game Client + RGS) | P23: Desktop + Mobile (all supported) | Q23: Not Run | S23: Ref: GR-12
A24: PS-UI-023 | B24: UI/UX | C24: FS UI | D24: Choice screen | E24: Verify FS choice screen art, text and spin numbers | F24: Choice screen | H24: 1. Inspect | I24: Text correct, no truncation | K24: P1 | L24: High | M24: UI | N24: Partial | O24: QA / Staging (Game Client + RGS) | P24: Desktop + Mobile (all supported) | Q24: Not Run | S24: Ref: GR-16
A25: PS-UI-024 | B25: UI/UX | C25: FS UI | D25: Sticky multiplier labels | E25: Verify multiplier labels on sticky wilds remain readable at small reel heights (7 rows) | F25: Sticky FS | H25: 1. Observe | I25: Readable | K25: P2 | L25: Medium | M25: UI | N25: Partial | O25: QA / Staging (Game Client + RGS) | P25: Desktop + Mobile (all supported) | Q25: Not Run | S25: Ref: GR-07
A26: PS-UI-025 | B26: UI/UX | C26: FS UI | D26: Raining animation | E26: Verify raining wild drop animation lands exactly on final positions | F26: Raining FS | H26: 1. Observe | I26: Wilds land on positions matching server | K26: P2 | L26: Medium | M26: UI | N26: Partial | O26: QA / Staging (Game Client + RGS) | P26: Desktop + Mobile (all supported) | Q26: Not Run | S26: Ref: GR-10
A27: PS-UI-026 | B27: UI/UX | C27: FS UI | D27: Summary popup | E27: Verify FS end summary shows total win and dismiss control | F27: FS end | H27: 1. Observe 2. Dismiss | I27: Correct value; dismiss works | K27: P1 | L27: High | M27: UI | N27: Partial | O27: QA / Staging (Game Client + RGS) | P27: Desktop + Mobile (all supported) | Q27: Not Run | S27: Ref: GR-12
A28: PS-UI-027 | B28: UI/UX | C28: Popups | D28: Insufficient funds | E28: Verify insufficient funds popup text and actions | F28: Low balance | H28: 1. Trigger | I28: Clear message; OK/Deposit | K28: P1 | L28: High | M28: UI | N28: Partial | O28: QA / Staging (Game Client + RGS) | P28: Desktop + Mobile (all supported) | Q28: Not Run | S28: Ref: GR-46
A29: PS-UI-028 | B29: UI/UX | C29: Popups | D29: Max win | E29: Verify max win reached popup | F29: Forced cap | H29: 1. Trigger | I29: Message shows cap amount | K29: P1 | L29: High | M29: UI | N29: Partial | O29: QA / Staging (Game Client + RGS) | P29: Desktop + Mobile (all supported) | Q29: Not Run | S29: Ref: GR-29 | OBS-09
A30: PS-UI-029 | B30: UI/UX | C30: Popups | D30: Z-index | E30: Verify popups render above reels and controls | F30: Any popup | H30: 1. Open popups | I30: No element above popup; background blocked | K30: P2 | L30: Medium | M30: UI | N30: Partial | O30: QA / Staging (Game Client + RGS) | P30: Desktop + Mobile (all supported) | Q30: Not Run | S30: Ref: GR-52
A31: PS-UI-030 | B31: UI/UX | C31: Buy UI | D31: Buy interface | E31: Verify Buy interface layout, cost text and buttons | F31: Buy open | H31: 1. Inspect at each resolution | I31: Readable; cost correct | K31: P1 | L31: High | M31: UI | N31: Partial | O31: QA / Staging (Game Client + RGS) | P31: Desktop + Mobile (all supported) | Q31: Not Run | S31: Ref: GR-32
A32: PS-UI-031 | B32: UI/UX | C32: Auto UI | D32: Auto panel | E32: Verify Auto Spin panel counters layout | F32: Auto running | H32: 1. Observe | I32: Total/remaining/total win visible | K32: P2 | L32: Medium | M32: UI | N32: Partial | O32: QA / Staging (Game Client + RGS) | P32: Desktop + Mobile (all supported) | Q32: Not Run | S32: Ref: GR-41
A33: PS-UI-032 | B33: UI/UX | C33: Paytable UI | D33: Paytable pages | E33: Verify paytable shows all 11 paying symbols, Wild, Bonus with values | F33: Info | H33: 1. Open paytable | I33: All symbols present with correct art | K33: P1 | L33: High | M33: UI | N33: Partial | O33: QA / Staging (Game Client + RGS) | P33: Desktop + Mobile (all supported) | Q33: Not Run | S33: Ref: GR-48, GR-50 | OBS-15
... A37: PS-UI-036 | B37: UI/UX | C37: Text | D37: Placeholders | E37: Verify no template placeholders like {{text1}} appear anywhere | F37: All screens | H37: 1. Search all text | I37: None present | K37: P0 | L37: Critical | M37: UI | N37: Yes | O37: QA / Staging (Game Client + RGS) | P37: Desktop + Mobile (all supported) | Q37: Not Run | S37: Ref: GR-28, GR-54 | OBS-09
A38: PS-UI-037 | B38: UI/UX | C38: Currency | D38: Formatting | E38: Verify thousands and decimal separators per locale | F38: Locales EN, RO | G38: 1234.5 | H38: 1. Check fields | I38: EN 1,234.50; RO 1.234,50 or per operator | K38: P1 | L38: High | M38: UI | N38: Partial | O38: QA / Staging (Game Client + RGS) | P38: Desktop + Mobile (all supported) | Q38: Not Run | S38: Ref: GR-19
A39: PS-UI-038 | B39: UI/UX | C39: Animation | D39: Spin animation | E39: Verify reel spin/stop animation smooth at 60fps target | F39: Desktop/mobile | H39: 1. Observe | I39: No stutter > 100ms | K39: P3 | L39: Low | M39: UI | N39: Partial | O39: QA / Staging (Game Client + RGS) | P39: Desktop + Mobile (all supported) | Q39: Not Run | S39: Ref: GR-22
A40: PS-UI-039 | B40: UI/UX | C40: Animation | D40: Skip | E40: Verify win animations can be skipped by tap/click | F40: Win | H40: 1. Tap during animation | I40: Skips to final state; values correct | K40: P2 | L40: Medium | M40: UI | N40: Partial | O40: QA / Staging (Game Client + RGS) | P40: Desktop + Mobile (all supported) | Q40: Not Run | S40: Ref: GR-25
A41: PS-UI-040 | B41: UI/UX | C41: Animation | D41: Turbo animation | E41: Verify Turbo shortens win animations | F41: Turbo | H41: 1. Compare durations | I41: Shorter | K41: P2 | L41: Medium | M41: UI | N41: Partial | O41: QA / Staging (Game Client + RGS) | P41: Desktop + Mobile (all supported) | Q41: Not Run | S41: Ref: GR-37
A42: PS-UI-041 | B42: UI/UX | C42: Audio | D42: Background music | E42: Verify base game music loops seamlessly | F42: Sound on | H42: 1. Listen 3 min | I42: No gap/click | K42: P3 | L42: Low | M42: UI | N42: No | O42: QA / Staging (Game Client + RGS) | P42: Desktop + Mobile (all supported) | Q42: Not Run | S42: Ref: GR-49
A43: PS-UI-042 | B43: UI/UX | C43: Audio | D43: Win sounds | E43: Verify win sound plays per win and scales with tier | F43: Wins | H43: 1. Force wins | I43: Correct sounds | K43: P3 | L43: Low | M43: UI | N43: No | O43: QA / Staging (Game Client + RGS) | P43: Desktop + Mobile (all supported) | Q43: Not Run | S43: Ref: GR-49
A44: PS-UI-043 | B44: UI/UX | C44: Audio | D44: FS music | E44: Verify FS music differs per feature and returns to base music | F44: FS | H44: 1. Enter/exit FS | I44: Correct switch | K44: P3 | L44: Low | M44: UI | N44: No | O44: QA / Staging (Game Client + RGS) | P44: Desktop + Mobile (all supported) | Q44: Not Run | S44: Ref: GR-49
A45: PS-UI-044 | B45: UI/UX | C45: Audio | D45: Mute persistence | E45: Verify mute persists across refresh | F45: Muted | H45: 1. Refresh | I45: Still muted | K45: P2 | L45: Medium | M45: UI | N45: Partial | O45: QA / Staging (Game Client + RGS) | P45: Desktop + Mobile (all supported) | Q45: Not Run | S45: Ref: GR-49
A46: PS-UI-045 | B46: UI/UX | C46: Audio | D46: Background tab | E46: Verify audio pauses when tab/app goes to background | F46: Sound on | H46: 1. Switch tab/app | I46: Audio pauses and resumes | K46: P2 | L46: Medium | M46: UI | N46: Partial | O46: QA / Staging (Game Client + RGS) | P46: Desktop + Mobile (all supported) | Q46: Not Run | S46: Ref: GR-49
A47: PS-UI-046 | B47: UI/UX | C47: Audio | D47: Sync | E47: Verify reel stop sounds sync with reel stops (incl. Quick Stop) | F47: Sound on | H47: 1. Spin, quick stop | I47: In sync | K47: P3 | L47: Low | M47: UI | N47: No | O47: QA / Staging (Game Client + RGS) | P47: Desktop + Mobile (all supported) | Q47: Not Run | S47: Ref: GR-31, GR-49
A48: PS-UI-047 | B48: UI/UX | C48: Audio | D48: Autoplay policy | E48: Verify game handles browser autoplay restriction (audio starts after first interaction) | F48: Fresh load | H48: 1. Load 2. Click | I48: No error; audio starts after interaction | K48: P2 | L48: Medium | M48: UI | N48: Partial | O48: QA / Staging (Game Client + RGS) | P48: Desktop + Mobile (all supported) | Q48: Not Run | S48: Ref: GR-49

Sheet Compatibility Testing
A1: Test Case ID | B1: Module | C1: Feature | D1: Sub-Feature | E1: Test Scenario | F1: Preconditions | G1: Test Data | H1: Detailed Test Steps | I1: Expected Result | J1: Actual Result | K1: Priority | L1: Severity | M1: Test Type | N1: Automation Candidate | O1: Environment | P1: Browser/Device | Q1: Status | R1: Defect ID | S1: Remarks
A2: PS-CMP-001 | B2: Compatibility | C2: Compatibility | D2: Windows 11 / Chrome (latest, latest-1) | E2: Verify full smoke flow on Windows 11 with Chrome (latest, latest-1): load, spin, win, bet change, FS (both types), Buy, Auto Spin, Info, Sound | F2: Device available; funded test account | G2: Bet 1.00 | H2: 1. Launch 2. Spin 10 rounds 3. Change bet 4. Force/trigger FS: Sticky 5. Force/trigger FS: Raining 6. Buy feature 7. Run 5 auto spins 8. Open Info 9. Toggle sound | I2: All steps work with no visual defects, errors or performance issues; balance consistent | K2: P0 | L2: High | M2: Compatibility | N2: Partial | O2: QA / Staging (Game Client + RGS) | P2: Windows 11 / Chrome (latest, latest-1) | Q2: Not Run | S2: Ref: GR-01, GR-22, GR-16, GR-32
A3: PS-CMP-002 | B3: Compatibility | C3: Compatibility | D3: Windows 11 / Firefox (latest) | E3: Verify full smoke flow on Windows 11 with Firefox (latest): load, spin, win, bet change, FS (both types), Buy, Auto Spin, Info, Sound | F3: Device available; funded test account | G3: Bet 1.00 | H3: 1. Launch 2. Spin 10 rounds 3. Change bet 4. Force/trigger FS: Sticky 5. Force/trigger FS: Raining 6. Buy feature 7. Run 5 auto spins 8. Open Info 9. Toggle sound | I3: All steps work with no visual defects, errors or performance issues; balance consistent | K3: P1 | L3: High | M3: Compatibility | N3: Partial | O3: QA / Staging (Game Client + RGS) | P3: Windows 11 / Firefox (latest) | Q3: Not Run | S3: Ref: GR-01, GR-22, GR-16, GR-32
A4: PS-CMP-003 | B4: Compatibility | C4: Compatibility | D4: Windows 11 / Edge (latest) | E4: Verify full smoke flow on Windows 11 with Edge (latest): load, spin, win, bet change, FS (both types), Buy, Auto Spin, Info, Sound | F4: Device available; funded test account | G4: Bet 1.00 | H4: 1. Launch 2. Spin 10 rounds 3. Change bet 4. Force/trigger FS: Sticky 5. Force/trigger FS: Raining 6. Buy feature 7. Run 5 auto spins 8. Open Info 9. Toggle sound | I4: All steps work with no visual defects, errors or performance issues; balance consistent | K4: P1 | L4: High | M4: Compatibility | N4: Partial | O4: QA / Staging (Game Client + RGS) | P4: Windows 11 / Edge (latest) | Q4: Not Run | S4: Ref: GR-01, GR-22, GR-16, GR-32
A5: PS-CMP-004 | B5: Compatibility | C5: Compatibility | D5: macOS (latest) / Safari (latest) | E5: Verify full smoke flow on macOS (latest) with Safari (latest): load, spin, win, bet change, FS (both types), Buy, Auto Spin, Info, Sound | F5: Device available; funded test account | G5: Bet 1.00 | H5: 1. Launch 2. Spin 10 rounds 3. Change bet 4. Force/trigger FS: Sticky 5. Force/trigger FS: Raining 6. Buy feature 7. Run 5 auto spins 8. Open Info 9. Toggle sound | I5: All steps work with no visual defects, errors or performance issues; balance consistent | K5: P1 | L5: High | M5: Compatibility | N5: Partial | O5: QA / Staging (Game Client + RGS) | P5: macOS (latest) / Safari (latest) | Q5: Not Run | S5: Ref: GR-01, GR-22, GR-16, GR-32
A6: PS-CMP-005 | B6: Compatibility | C6: Compatibility | D6: macOS (latest) / Chrome (latest) | E6: Verify full smoke flow on macOS (latest) with Chrome (latest): load, spin, win, bet change, FS (both types), Buy, Auto Spin, Info, Sound | F6: Device available; funded test account | G6: Bet 1.00 | H6: 1. Launch 2. Spin 10 rounds 3. Change bet 4. Force/trigger FS: Sticky 5. Force/trigger FS: Raining 6. Buy feature 7. Run 5 auto spins 8. Open Info 9. Toggle sound | I6: All steps work with no visual defects, errors or performance issues; balance consistent | K6: P1 | L6: High | M6: Compatibility | N6: Partial | O6: QA / Staging (Game Client + RGS) | P6: macOS (latest) / Chrome (latest) | Q6: Not Run | S6: Ref: GR-01, GR-22, GR-16, GR-32
A7: PS-CMP-006 | B7: Compatibility | C7: Compatibility | D7: iOS 17/18 iPhone / Safari | E7: Verify full smoke flow on iOS 17/18 iPhone with Safari: load, spin, win, bet change, FS (both types), Buy, Auto Spin, Info, Sound | F7: Device available; funded test account | G7: Bet 1.00 | H7: 1. Launch 2. Spin 10 rounds 3. Change bet 4. Force/trigger FS: Sticky 5. Force/trigger FS: Raining 6. Buy feature 7. Run 5 auto spins 8. Open Info 9. Toggle sound | I7: All steps work with no visual defects, errors or performance issues; balance consistent | K7: P0 | L7: High | M7: Compatibility | N7: Partial | O7: QA / Staging (Game Client + RGS) | P7: iOS 17/18 iPhone / Safari | Q7: Not Run | S7: Ref: GR-01, GR-22, GR-16, GR-32
A8: PS-CMP-007 | B8: Compatibility | C8: Compatibility | D8: iOS 17/18 iPhone / Chrome | E8: Verify full smoke flow on iOS 17/18 iPhone with Chrome: load, spin, win, bet change, FS (both types), Buy, Auto Spin, Info, Sound | F8: Device available; funded test account | G8: Bet 1.00 | H8: 1. Launch 2. Spin 10 rounds 3. Change bet 4. Force/trigger FS: Sticky 5. Force/trigger FS: Raining 6. Buy feature 7. Run 5 auto spins 8. Open Info 9. Toggle sound | I8: All steps work with no visual defects, errors or performance issues; balance consistent | K8: P2 | L8: Medium | M8: Compatibility | N8: Partial | O8: QA / Staging (Game Client + RGS) | P8: iOS 17/18 iPhone / Chrome | Q8: Not Run | S8: Ref: GR-01, GR-22, GR-16, GR-32
A9: PS-CMP-008 | B9: Compatibility | C9: Compatibility | D9: iPadOS / Safari | E9: Verify full smoke flow on iPadOS with Safari: load, spin, win, bet change, FS (both types), Buy, Auto Spin, Info, Sound | F9: Device available; funded test account | G9: Bet 1.00 | H9: 1. Launch 2. Spin 10 rounds 3. Change bet 4. Force/trigger FS: Sticky 5. Force/trigger FS: Raining 6. Buy feature 7. Run 5 auto spins 8. Open Info 9. Toggle sound | I9: All steps work with no visual defects, errors or performance issues; balance consistent | K9: P1 | L9: High | M9: Compatibility | N9: Partial | O9: QA / Staging (Game Client + RGS) | P9: iPadOS / Safari | Q9: Not Run | S9: Ref: GR-01, GR-22, GR-16, GR-32
A10: PS-CMP-009 | B10: Compatibility | C10: Compatibility | D10: Android 13/14 phone / Chrome | E10: Verify full smoke flow on Android 13/14 phone with Chrome: load, spin, win, bet change, FS (both types), Buy, Auto Spin, Info, Sound | F10: Device available; funded test account | G10: Bet 1.00 | H10: 1. Launch 2. Spin 10 rounds 3. Change bet 4. Force/trigger FS: Sticky 5. Force/trigger FS: Raining 6. Buy feature 7. Run 5 auto spins 8. Open Info 9. Toggle sound | I10: All steps work with no visual defects, errors or performance issues; balance consistent | K10: P0 | L10: High | M10: Compatibility | N10: Partial | O10: QA / Staging (Game Client + RGS) | P10: Android 13/14 phone / Chrome | Q10: Not Run | S10: Ref: GR-01, GR-22, GR-16, GR-32
A11: PS-CMP-010 | B11: Compatibility | C11: Compatibility | D11: Android 13/14 phone / Samsung Internet | E11: Verify full smoke flow on Android 13/14 phone with Samsung Internet: load, spin, win, bet change, FS (both types), Buy, Auto Spin, Info, Sound | F11: Device available; funded test account | G11: Bet 1.00 | H11: 1. Launch 2. Spin 10 rounds 3. Change bet 4. Force/trigger FS: Sticky 5. Force/trigger FS: Raining 6. Buy feature 7. Run 5 auto spins 8. Open Info 9. Toggle sound | I11: All steps work with no visual defects, errors or performance issues; balance consistent | K11: P1 | L11: High | M11: Compatibility | N11: Partial | O11: QA / Staging (Game Client + RGS) | P11: Android 13/14 phone / Samsung Internet | Q11: Not Run | S11: Ref: GR-01, GR-22, GR-16, GR-32
A12: PS-CMP-011 | B12: Compatibility | C12: Compatibility | D12: Android tablet / Chrome | E12: Verify full smoke flow on Android tablet with Chrome: load, spin, win, bet change, FS (both types), Buy, Auto Spin, Info, Sound | F12: Device available; funded test account | G12: Bet 1.00 | H12: 1. Launch 2. Spin 10 rounds 3. Change bet 4. Force/trigger FS: Sticky 5. Force/trigger FS: Raining 6. Buy feature 7. Run 5 auto spins 8. Open Info 9. Toggle sound | I12: All steps work with no visual defects, errors or performance issues; balance consistent | K12: P2 | L12: Medium | M12: Compatibility | N12: Partial | O12: QA / Staging (Game Client + RGS) | P12: Android tablet / Chrome | Q12: Not Run | S12: Ref: GR-01, GR-22, GR-16, GR-32
A13: PS-CMP-012 | B13: Compatibility | C13: Compatibility | D13: iOS (oldest supported) / Safari | E13: Verify full smoke flow on iOS (oldest supported) with Safari: load, spin, win, bet change, FS (both types), Buy, Auto Spin, Info, Sound | F13: Device available; funded test account | G13: Bet 1.00 | H13: 1. Launch 2. Spin 10 rounds 3. Change bet 4. Force/trigger FS: Sticky 5. Force/trigger FS: Raining 6. Buy feature 7. Run 5 auto spins 8. Open Info 9. Toggle sound | I13: All steps work with no visual defects, errors or performance issues; balance consistent | K13: P2 | L13: Medium | M13: Compatibility | N13: Partial | O13: QA / Staging (Game Client + RGS) | P13: iOS (oldest supported) / Safari | Q13: Not Run | S13: Ref: GR-01, GR-22, GR-16, GR-32
... A22: PS-CMP-021 | B22: Compatibility | C22: Compatibility | D22: In-app webview (operator app) | E22: Verify in-app webview (operator app) | F22: Relevant device | G22: Operator native wrapper | H22: 1. Set condition 2. Play 5 rounds | I22: Game remains usable; no layout break; outcome unaffected | K22: P1 | L22: Medium | M22: Compatibility | N22: No | O22: QA / Staging (Game Client + RGS) | P22: Mobile / Tablet | Q22: Not Run | S22: Ref: GR-52

Sheet Interruption & Recovery
A1: Test Case ID | B1: Module | C1: Feature | D1: Sub-Feature | E1: Test Scenario | F1: Preconditions | G1: Test Data | H1: Detailed Test Steps | I1: Expected Result | J1: Actual Result | K1: Priority | L1: Severity | M1: Test Type | N1: Automation Candidate | O1: Environment | P1: Browser/Device | Q1: Status | R1: Defect ID | S1: Remarks
A2: PS-INT-001 | B2: Interruption | C2: Interruption | D2: Refresh | E2: Refresh: during base spin | F2: Spin in progress | G2: Bet 1.00 | H2: 1. Press Play 2. Refresh before reels stop 3. Reload | I2: One debit; result of interrupted round shown or in history; win credited once; no new round | K2: P0 | L2: Critical | M2: Recovery | N2: Yes | O2: QA / Staging (Game Client + RGS) | P2: Desktop + Mobile (all supported) | Q2: Not Run | S2: Ref: GR-56
A3: PS-INT-002 | B3: Interruption | C3: Interruption | D3: Refresh | E3: Refresh: during win presentation | F3: Win presenting | G3: Bet 1.00 | H3: 1. Refresh | I3: Win credited once; balance correct | K3: P0 | L3: Critical | M3: Recovery | N3: Yes | O3: QA / Staging (Game Client + RGS) | P3: Desktop + Mobile (all supported) | Q3: Not Run | S3: Ref: GR-56
A4: PS-INT-003 | B4: Interruption | C4: Interruption | D4: Refresh | E4: Refresh: during Free Spins | F4: FS spin 4/15 | G4: Bet 1.00 | H4: 1. Refresh | I4: Resume at correct spin; total win and wilds preserved | K4: P0 | L4: Critical | M4: Recovery | N4: Yes | O4: QA / Staging (Game Client + RGS) | P4: Desktop + Mobile (all supported) | Q4: Not Run | S4: Ref: GR-56
A5: PS-INT-004 | B5: Interruption | C5: Interruption | D5: Refresh | E5: Refresh: on FS choice screen | F5: Choice screen | G5: Bet 1.00 | H5: 1. Refresh | I5: Choice screen restored | K5: P0 | L5: Critical | M5: Recovery | N5: Yes | O5: QA / Staging (Game Client + RGS) | P5: Desktop + Mobile (all supported) | Q5: Not Run | S5: Ref: GR-56
A6: PS-INT-005 | B6: Interruption | C6: Interruption | D6: Refresh | E6: Refresh: immediately after Buy confirm | F6: Buy confirmed | G6: Bet 1.00 | H6: 1. Refresh | I6: Single debit; feature resumes | K6: P0 | L6: Critical | M6: Recovery | N6: Yes | O6: QA / Staging (Game Client + RGS) | P6: Desktop + Mobile (all supported) | Q6: Not Run | S6: Ref: GR-56
A7: PS-INT-006 | B7: Interruption | C7: Interruption | D7: Close/reopen | E7: Close/reopen: during base spin | F7: Spin | G7: Bet 1.00 | H7: 1. Close tab 2. Reopen | I7: Round completed server-side; balance and history correct | K7: P0 | L7: Critical | M7: Recovery | N7: Yes | O7: QA / Staging (Game Client + RGS) | P7: Desktop + Mobile (all supported) | Q7: Not Run | S7: Ref: GR-56
A8: PS-INT-007 | B8: Interruption | C8: Interruption | D8: Close/reopen | E8: Close/reopen: during FS | F8: FS | G8: Bet 1.00 | H8: 1. Close 2. Reopen | I8: FS resumes | K8: P0 | L8: Critical | M8: Recovery | N8: Yes | O8: QA / Staging (Game Client + RGS) | P8: Desktop + Mobile (all supported) | Q8: Not Run | S8: Ref: GR-56
A9: PS-INT-008 | B9: Interruption | C9: Interruption | D9: Network loss | E9: Network loss: before spin request | F9: Offline | G9: Bet 1.00 | H9: 1. Disable network 2. Press Play | I9: Error/reconnect message; no debit; no round | K9: P0 | L9: Critical | M9: Recovery | N9: Yes | O9: QA / Staging (Game Client + RGS) | P9: Desktop + Mobile (all supported) | Q9: Not Run | S9: Ref: GR-56
A10: PS-INT-009 | B10: Interruption | C10: Interruption | D10: Network loss | E10: Network loss: after request sent, before response | F10: Network drops after request | G10: Bet 1.00 | H10: 1. Spin 2. Drop network 3. Restore | I10: On reconnect state synced; one debit; result displayed; no duplicate | K10: P0 | L10: Critical | M10: Recovery | N10: Yes | O10: QA / Staging (Game Client + RGS) | P10: Desktop + Mobile (all supported) | Q10: Not Run | S10: Ref: GR-56
A11: PS-INT-010 | B11: Interruption | C11: Interruption | D11: Network loss | E11: Network loss: during FS | F11: FS | G11: Bet 1.00 | H11: 1. Drop 60s 2. Restore | I11: FS continues from last server state | K11: P0 | L11: Critical | M11: Recovery | N11: Yes | O11: QA / Staging (Game Client + RGS) | P11: Desktop + Mobile (all supported) | Q11: Not Run | S11: Ref: GR-56
A12: PS-INT-011 | B12: Interruption | C12: Interruption | D12: Network loss | E12: Network loss: long outage (10 min) | F12: Base | G12: Bet 1.00 | H12: 1. Drop 10 min 2. Restore | I12: Session handling per operator; state recoverable after relaunch | K12: P1 | L12: High | M12: Recovery | N12: Yes | O12: QA / Staging (Game Client + RGS) | P12: Desktop + Mobile (all supported) | Q12: Not Run | S12: Ref: GR-56
A13: PS-INT-012 | B13: Interruption | C13: Interruption | D13: App background | E13: App background: iOS during spin | F13: Spin | G13: Bet 1.00 | H13: 1. Home button 2. Return after 30s | I13: Spin completes; state consistent | K13: P0 | L13: Critical | M13: Recovery | N13: Yes | O13: QA / Staging (Game Client + RGS) | P13: Mobile (iOS Safari / Android Chrome) | Q13: Not Run | S13: Ref: GR-56
... A31: PS-INT-030 | B31: Interruption | C31: Interruption | D31: Suspended state | E31: Suspended state: resume point | F31: Interrupted at FS spin N | G31: Bet 1.00 | H31: 1. Relaunch | I31: Resumes from last successfully recorded action (spin N+1 or result of N) | K31: P0 | L31: Critical | M31: Recovery | N31: Yes | O31: QA / Staging (Game Client + RGS) | P31: Desktop + Mobile (all supported) | Q31: Not Run | S31: Ref: GR-56

Sheet STR - Transaction Testing
A1: Test Case ID | B1: Module | C1: Feature | D1: Sub-Feature | E1: Test Scenario | F1: Preconditions | G1: Test Data | H1: Detailed Test Steps | I1: Expected Result | J1: Actual Result | K1: Priority | L1: Severity | M1: Test Type | N1: Automation Candidate | O1: Environment | P1: Browser/Device | Q1: Status | R1: Defect ID | S1: Remarks
A2: PS-STR-001 | B2: Transactions | C2: Transactions | D2: Bet transaction | E2: Bet transaction: single debit | F2: Funded | G2: Bet 1.00; RGS/wallet log access | H2: 1. Spin 2. Inspect wallet calls | I2: One debit with unique transaction ID and round ID; amount = bet | K2: P0 | L2: Critical | M2: Integration | N2: Yes | O2: QA / Staging (Game Client + RGS) | P2: N/A (RGS / Simulation) | Q2: Not Run | S2: Ref: GR-22
A3: PS-STR-002 | B3: Transactions | C3: Transactions | D3: Win transaction | E3: Win transaction: amount | F3: Forced win 0.75 | G3: Bet 1.00; RGS/wallet log access | H3: 1. Spin 2. Inspect credit | I3: Credit 0.75 referencing same round ID | K3: P0 | L3: Critical | M3: Integration | N3: Yes | O3: QA / Staging (Game Client + RGS) | P3: N/A (RGS / Simulation) | Q3: Not Run | S3: Ref: GR-25
A4: PS-STR-003 | B4: Transactions | C4: Transactions | D4: Zero win | E4: Zero win: closing call | F4: Forced loss | G4: Bet 1.00; RGS/wallet log access | H4: 1. Spin | I4: Round closed per wallet protocol (0 credit or end-round call) | K4: P0 | L4: Critical | M4: Integration | N4: Yes | O4: QA / Staging (Game Client + RGS) | P4: N/A (RGS / Simulation) | Q4: Not Run | S4: Ref: GR-22
A5: PS-STR-004 | B5: Transactions | C5: Transactions | D5: Buy transaction | E5: Buy transaction | F5: Buy at 1.00 | G5: Bet 1.00; RGS/wallet log access | H5: 1. Buy 2. Inspect | I5: Debit 100.00 flagged as feature purchase; one round | K5: P0 | L5: Critical | M5: Integration | N5: Yes | O5: QA / Staging (Game Client + RGS) | P5: N/A (RGS / Simulation) | Q5: Not Run | S5: Ref: GR-36
A6: PS-STR-005 | B6: Transactions | C6: Transactions | D6: FS transactions | E6: FS transactions | F6: FS trigger | G6: Bet 1.00; RGS/wallet log access | H6: 1. Play FS 2. Inspect | I6: Requires Specification/Confirmation: Expected: no debits in FS; credits per spin or single credit at end per wallet spec (rules imply single at end, OBS-08) | K6: P0 | L6: Critical | M6: Integration | N6: Yes | O6: QA / Staging (Game Client + RGS) | P6: N/A (RGS / Simulation) | Q6: Not Run | S6: Ref: GR-12, GR-15 | OBS-08
A7: PS-STR-006 | B7: Transactions | C7: Transactions | D7: Round lifecycle | E7: Round lifecycle: FS in one round | F7: FS | G7: Bet 1.00; RGS/wallet log access | H7: 1. Inspect round IDs | I7: Trigger spin and FS belong to the same game round/round chain; round closed only after FS end | K7: P0 | L7: Critical | M7: Integration | N7: Yes | O7: QA / Staging (Game Client + RGS) | P7: N/A (RGS / Simulation) | Q7: Not Run | S7: Ref: GR-12
A8: PS-STR-007 | B8: Transactions | C8: Transactions | D8: Idempotency | E8: Idempotency: duplicate spin request | F8: Replay identical spin request with same request ID | G8: Bet 1.00; RGS/wallet log access | H8: 1. Send twice | I8: Second request rejected or returns original response; no second debit | K8: P0 | L8: Critical | M8: Integration | N8: Yes | O8: QA / Staging (Game Client + RGS) | P8: N/A (RGS / Simulation) | Q8: Not Run | S8: Ref: GR-22
A9: PS-STR-008 | B9: Transactions | C9: Transactions | D9: Idempotency | E9: Idempotency: duplicate credit | F9: Retry credit | G9: Bet 1.00; RGS/wallet log access | H9: 1. Force retry | I9: Wallet de-duplicates by transaction ID | K9: P0 | L9: Critical | M9: Integration | N9: Yes | O9: QA / Staging (Game Client + RGS) | P9: N/A (RGS / Simulation) | Q9: Not Run | S9: Ref: GR-22
A10: PS-STR-009 | B10: Transactions | C10: Transactions | D10: Replay | E10: Replay: old round request | F10: Resend request of completed round | G10: Bet 1.00; RGS/wallet log access | H10: 1. Replay | I10: Rejected; no state change | K10: P0 | L10: Critical | M10: Integration | N10: Yes | O10: QA / Staging (Game Client + RGS) | P10: N/A (RGS / Simulation) | Q10: Not Run | S10: Ref: GR-22
A11: PS-STR-010 | B11: Transactions | C11: Transactions | D11: Sequence | E11: Sequence: out-of-order requests | F11: FS spin request before choice | G11: Bet 1.00; RGS/wallet log access | H11: 1. Send FS spin without choice | I11: Rejected with invalid state error | K11: P0 | L11: Critical | M11: Integration | N11: Yes | O11: QA / Staging (Game Client + RGS) | P11: N/A (RGS / Simulation) | Q11: Not Run | S11: Ref: GR-16
A12: PS-STR-011 | B12: Transactions | C12: Transactions | D12: Sequence | E12: Sequence: spin during FS | F12: Base spin request while FS pending | G12: Bet 1.00; RGS/wallet log access | H12: 1. Send base spin | I12: Rejected; FS state preserved | K12: P0 | L12: Critical | M12: Integration | N12: Yes | O12: QA / Staging (Game Client + RGS) | P12: N/A (RGS / Simulation) | Q12: Not Run | S12: Ref: GR-15
A13: PS-STR-012 | B13: Transactions | C13: Transactions | D13: Tampered bet value | E13: Tampered bet value | F13: Bet not in ladder (e.g. 1.37) | G13: Bet 1.00; RGS/wallet log access | H13: 1. Send spin with bet 1.37 | I13: Rejected invalid bet; no debit | K13: P0 | L13: Critical | M13: Integration | N13: Yes | O13: QA / Staging (Game Client + RGS) | P13: N/A (RGS / Simulation) | Q13: Not Run | S13: Ref: GR-20, GR-28
... A28: PS-STR-027 | B28: Transactions | C28: Transactions | D28: Responsible gaming | E28: Responsible gaming: session/loss limit | F28: Operator limit reached | G28: Bet 1.00; RGS/wallet log access | H28: 1. Spin | I28: Spin blocked with operator message; FS in progress handled per operator rules | K28: P1 | L28: High | M28: Integration | N28: Partial | O28: QA / Staging (Game Client + RGS) | P28: N/A (RGS / Simulation) | Q28: Not Run | S28: Ref: GR-22

Sheet Error Handling
A1: Test Case ID | B1: Module | C1: Feature | D1: Sub-Feature | E1: Test Scenario | F1: Preconditions | G1: Test Data | H1: Detailed Test Steps | I1: Expected Result | J1: Actual Result | K1: Priority | L1: Severity | M1: Test Type | N1: Automation Candidate | O1: Environment | P1: Browser/Device | Q1: Status | R1: Defect ID | S1: Remarks
A2: PS-ERR-001 | B2: Error Handling | C2: Error Handling | D2: Insufficient balance | E2: Insufficient balance: spin | F2: Balance < bet | G2: Bet 1.00 | H2: 1. Spin | I2: Message with code; no debit; Play re-enabled after bet lowered | K2: P0 | L2: Critical | M2: Negative | N2: Yes | O2: QA / Staging (Game Client + RGS) | P2: Desktop + Mobile (all supported) | Q2: Not Run | S2: Ref: GR-22
A3: PS-ERR-002 | B3: Error Handling | C3: Error Handling | D3: Insufficient balance | E3: Insufficient balance: Buy | F3: Balance < 100x bet | G3: Bet 1.00 | H3: 1. Buy | I3: Message; no debit | K3: P0 | L3: Critical | M3: Negative | N3: Yes | O3: QA / Staging (Game Client + RGS) | P3: Desktop + Mobile (all supported) | Q3: Not Run | S3: Ref: GR-36
A4: PS-ERR-003 | B4: Error Handling | C4: Error Handling | D4: Session error | E4: Session error: expired | F4: Expired | G4: Bet 1.00 | H4: 1. Spin | I4: Session expired message; reload/relaunch prompt | K4: P0 | L4: Critical | M4: Negative | N4: Yes | O4: QA / Staging (Game Client + RGS) | P4: Desktop + Mobile (all supported) | Q4: Not Run | S4: Ref: GR-56
A5: PS-ERR-004 | B5: Error Handling | C5: Error Handling | D5: Session error | E5: Session error: concurrent login | F5: Login elsewhere | G5: Bet 1.00 | H5: 1. Spin | I5: Session invalid message | K5: P1 | L5: High | M5: Negative | N5: Yes | O5: QA / Staging (Game Client + RGS) | P5: Desktop + Mobile (all supported) | Q5: Not Run | S5: Ref: GR-56
A6: PS-ERR-005 | B6: Error Handling | C6: Error Handling | D6: Network error | E6: Network error: offline | F6: Offline | G6: Bet 1.00 | H6: 1. Spin | I6: Connection lost message; retry; no debit | K6: P1 | L6: High | M6: Negative | N6: Yes | O6: QA / Staging (Game Client + RGS) | P6: Desktop + Mobile (all supported) | Q6: Not Run | S6: Ref: GR-56
A7: PS-ERR-006 | B7: Error Handling | C7: Error Handling | D7: Server error | E7: Server error: 500 | F7: Mock | G7: Bet 1.00 | H7: 1. Spin | I7: Generic error with code; recoverable | K7: P0 | L7: Critical | M7: Negative | N7: Yes | O7: QA / Staging (Game Client + RGS) | P7: Desktop + Mobile (all supported) | Q7: Not Run | S7: Ref: GR-56
A8: PS-ERR-007 | B8: Error Handling | C8: Error Handling | D8: Server error | E8: Server error: 503 maintenance | F8: Mock | G8: Bet 1.00 | H8: 1. Launch | I8: Maintenance message | K8: P1 | L8: High | M8: Negative | N8: Yes | O8: QA / Staging (Game Client + RGS) | P8: Desktop + Mobile (all supported) | Q8: Not Run | S8: Ref: GR-56
A9: PS-ERR-008 | B9: Error Handling | C9: Error Handling | D9: Invalid game state | E9: Invalid game state: FS spin with no FS | F9: Mock | G9: Bet 1.00 | H9: 1. Send | I9: Error; game resyncs | K9: P1 | L9: High | M9: Negative | N9: Yes | O9: QA / Staging (Game Client + RGS) | P9: Desktop + Mobile (all supported) | Q9: Not Run | S9: Ref: GR-56
A10: PS-ERR-009 | B10: Error Handling | C10: Error Handling | D10: Invalid bet | E10: Invalid bet | F10: Mock bet not allowed | G10: Bet 1.00 | H10: 1. Spin | I10: Invalid bet message; bet resets to valid | K10: P1 | L10: High | M10: Negative | N10: Yes | O10: QA / Staging (Game Client + RGS) | P10: Desktop + Mobile (all supported) | Q10: Not Run | S10: Ref: GR-56
A11: PS-ERR-010 | B11: Error Handling | C11: Error Handling | D11: Invalid feature state | E11: Invalid feature state: choice twice | F11: Mock | G11: Bet 1.00 | H11: 1. Send choice twice | I11: Second rejected silently or with error; one feature | K11: P1 | L11: High | M11: Negative | N11: Yes | O11: QA / Staging (Game Client + RGS) | P11: Desktop + Mobile (all supported) | Q11: Not Run | S11: Ref: GR-56
A12: PS-ERR-011 | B12: Error Handling | C12: Error Handling | D12: Timeout | E12: Timeout: spin | F12: Delay | G12: Bet 1.00 | H12: 1. Spin | I12: Timeout message; recovery | K12: P0 | L12: Critical | M12: Negative | N12: Yes | O12: QA / Staging (Game Client + RGS) | P12: Desktop + Mobile (all supported) | Q12: Not Run | S12: Ref: GR-56
A13: PS-ERR-012 | B13: Error Handling | C13: Error Handling | D13: Failed spin | E13: Failed spin: RNG/engine error | F13: Mock engine error | G13: Bet 1.00 | H13: 1. Spin | I13: No debit or rollback; error message | K13: P0 | L13: Critical | M13: Negative | N13: Yes | O13: QA / Staging (Game Client + RGS) | P13: Desktop + Mobile (all supported) | Q13: Not Run | S13: Ref: GR-56
... A21: PS-ERR-020 | B21: Error Handling | C21: Error Handling | D21: Malfunction handling | E21: Malfunction handling | F21: Simulated malfunction | G21: Bet 1.00 | H21: 1. Trigger | I21: Round voided per rules; bet refunded per operator; logged | K21: P1 | L21: High | M21: Negative | N21: Yes | O21: QA / Staging (Game Client + RGS) | P21: Desktop + Mobile (all supported) | Q21: Not Run | S21: Ref: GR-53

Sheet Traceability Matrix
A1: Traceability Matrix: Requirement -> Feature -> Test Case
A3: Req ID | B3: Source | C3: Section / Cell Ref | D3: Requirement | E3: Feature | F3: Linked Test Case IDs | G3: TC Count | H3: Coverage | I3: Linked Observations
A4: GR-01 | B4: Game Rules | C4: Intro | D4: Megaways slot, 6 reels, up to 117,649 ways | E4: Reels / Ways | F4: PS-FUN-001, PS-FUN-005, PS-FUN-006, PS-FUN-007, PS-FUN-008, PS-FUN-040, PS-MTH-016, PS-EDG-013, PS-EDG-014, PS-UI-001, PS-UI-010, PS-CMP-001, PS-CMP-002, PS-CMP-003, PS-CMP-004, PS-CMP-005, PS-CMP-006, PS-CMP-007, PS-CMP-008, PS-CMP-009, PS-CMP-010, PS-CMP-011, PS-CMP-012, PS-CMP-013 | G4: =COUNTIF('Functional Testing'!$S:$S,"*"&$A4&"*")+COUNTIF('Math Validation'!$S:$S,"*"&$A4&"*")+COUNTIF('Feature Testing'!$S:$S,"*"&$A4&"*")+COUNTIF('Edge & Boundary Cases'!$S:$S,"*"&$A4&"*")+COUNTIF('UI-UX Testing'!$S:$S,"*"&$A4&"*")+COUNTIF('Compatibility Testing'!$S:$S,"*"&$A4&"*")+COUNTIF('Interruption & Recovery'!$S:$S,"*"&$A4&"*")+COUNTIF('STR - Transaction Testing'!$S:$S,"*"&$A4&"*")+COUNTIF('Error Handling'!$S:$S,"*"&$A4&"*") -> 24 | H4: =IF(G4=0,"NOT COVERED",IF(G4<2,"Partial","Covered")) -> Covered | I4: OBS-04
A5: GR-02 | B5: Game Rules | C5: Intro | D5: Each reel shows up to 7 symbols; ways depend on symbols per reel | E5: Reels / Ways | F5: PS-FUN-005, PS-FUN-006, PS-MTH-015, PS-EDG-040, PS-UI-009 | G5: =COUNTIF('Functional Testing'!$S:$S,"*"&$A5&"*")+COUNTIF('Math Validation'!$S:$S,"*"&$A5&"*")+COUNTIF('Feature Testing'!$S:$S,"*"&$A5&"*")+COUNTIF('Edge & Boundary Cases'!$S:$S,"*"&$A5&"*")+COUNTIF('UI-UX Testing'!$S:$S,"*"&$A5&"*")+COUNTIF('Compatibility Testing'!$S:$S,"*"&$A5&"*")+COUNTIF('Interruption & Recovery'!$S:$S,"*"&$A5&"*")+COUNTIF('STR - Transaction Testing'!$S:$S,"*"&$A5&"*")+COUNTIF('Error Handling'!$S:$S,"*"&$A5&"*") -> 5 | H5: =IF(G5=0,"NOT COVERED",IF(G5<2,"Partial","Covered")) -> Covered
A6: GR-03 | B6: Game Rules | C6: Intro | D6: Wins pay for matching symbols on adjacent reels from leftmost reel | E6: Win Evaluation | F6: PS-FUN-038, PS-FUN-039, PS-FUN-040 | G6: =COUNTIF('Functional Testing'!$S:$S,"*"&$A6&"*")+COUNTIF('Math Validation'!$S:$S,"*"&$A6&"*")+COUNTIF('Feature Testing'!$S:$S,"*"&$A6&"*")+COUNTIF('Edge & Boundary Cases'!$S:$S,"*"&$A6&"*")+COUNTIF('UI-UX Testing'!$S:$S,"*"&$A6&"*")+COUNTIF('Compatibility Testing'!$S:$S,"*"&$A6&"*")+COUNTIF('Interruption & Recovery'!$S:$S,"*"&$A6&"*")+COUNTIF('STR - Transaction Testing'!$S:$S,"*"&$A6&"*")+COUNTIF('Error Handling'!$S:$S,"*"&$A6&"*") -> 3 | H6: =IF(G6=0,"NOT COVERED",IF(G6<2,"Partial","Covered")) -> Covered
A7: GR-04 | B7: Game Rules | C7: Intro | D7: Paytable payouts based on current bet | E7: Paytable | F7: PS-FUN-021, PS-FUN-034, PS-MTH-017, PS-MTH-018, PS-MTH-019, PS-MTH-020, PS-MTH-021, PS-MTH-022, PS-MTH-023, PS-MTH-024, PS-MTH-025 | G7: =COUNTIF('Functional Testing'!$S:$S,"*"&$A7&"*")+COUNTIF('Math Validation'!$S:$S,"*"&$A7&"*")+COUNTIF('Feature Testing'!$S:$S,"*"&$A7&"*")+COUNTIF('Edge & Boundary Cases'!$S:$S,"*"&$A7&"*")+COUNTIF('UI-UX Testing'!$S:$S,"*"&$A7&"*")+COUNTIF('Compatibility Testing'!$S:$S,"*"&$A7&"*")+COUNTIF('Interruption & Recovery'!$S:$S,"*"&$A7&"*")+COUNTIF('STR - Transaction Testing'!$S:$S,"*"&$A7&"*")+COUNTIF('Error Handling'!$S:$S,"*"&$A7&"*") -> 11 | H7: =IF(G7=0,"NOT COVERED",IF(G7<2,"Partial","Covered")) -> Covered
A8: GR-05 | B8: Game Rules | C8: Sticky Wilds FS | D8: 3/4/5/6 Bonus award 7/12/15/20 Free Spins | E8: Sticky Wilds FS | F8: PS-FUN-054, PS-MTH-038, PS-MTH-039, PS-MTH-040, PS-MTH-041, PS-FEA-001, PS-FEA-002, PS-FEA-003, PS-FEA-004, PS-FEA-005, PS-FEA-041, PS-FEA-045 | G8: =COUNTIF('Functional Testing'!$S:$S,"*"&$A8&"*")+COUNTIF('Math Validation'!$S:$S,"*"&$A8&"*")+COUNTIF('Feature Testing'!$S:$S,"*"&$A8&"*")+COUNTIF('Edge & Boundary Cases'!$S:$S,"*"&$A8&"*")+COUNTIF('UI-UX Testing'!$S:$S,"*"&$A8&"*")+COUNTIF('Compatibility Testing'!$S:$S,"*"&$A8&"*")+COUNTIF('Interruption & Recovery'!$S:$S,"*"&$A8&"*")+COUNTIF('STR - Transaction Testing'!$S:$S,"*"&$A8&"*")+COUNTIF('Error Handling'!$S:$S,"*"&$A8&"*") -> 12 | H8: =IF(G8=0,"NOT COVERED",IF(G8<2,"Partial","Covered")) -> Covered
A9: GR-06 | B9: Game Rules | C9: Sticky Wilds FS | D9: Up to 7 Sticky Wilds can land on each reel | E9: Sticky Wilds FS | F9: PS-MTH-050, PS-FEA-028, PS-FEA-031, PS-FEA-032 | G9: =COUNTIF('Functional Testing'!$S:$S,"*"&$A9&"*")+COUNTIF('Math Validation'!$S:$S,"*"&$A9&"*")+COUNTIF('Feature Testing'!$S:$S,"*"&$A9&"*")+COUNTIF('Edge & Boundary Cases'!$S:$S,"*"&$A9&"*")+COUNTIF('UI-UX Testing'!$S:$S,"*"&$A9&"*")+COUNTIF('Compatibility Testing'!$S:$S,"*"&$A9&"*")+COUNTIF('Interruption & Recovery'!$S:$S,"*"&$A9&"*")+COUNTIF('STR - Transaction Testing'!$S:$S,"*"&$A9&"*")+COUNTIF('Error Handling'!$S:$S,"*"&$A9&"*") -> 4 | H9: =IF(G9=0,"NOT COVERED",IF(G9<2,"Partial","Covered")) -> Covered | I9: OBS-06
A10: GR-07 | B10: Game Rules | C10: Sticky Wilds FS | D10: Each Wild assigned random multiplier x2 or x3 | E10: Sticky Wilds FS | F10: PS-MTH-034, PS-FEA-026, PS-FEA-027, PS-UI-024, PS-UI-034 | G10: =COUNTIF('Functional Testing'!$S:$S,"*"&$A10&"*")+COUNTIF('Math Validation'!$S:$S,"*"&$A10&"*")+COUNTIF('Feature Testing'!$S:$S,"*"&$A10&"*")+COUNTIF('Edge & Boundary Cases'!$S:$S,"*"&$A10&"*")+COUNTIF('UI-UX Testing'!$S:$S,"*"&$A10&"*")+COUNTIF('Compatibility Testing'!$S:$S,"*"&$A10&"*")+COUNTIF('Interruption & Recovery'!$S:$S,"*"&$A10&"*")+COUNTIF('STR - Transaction Testing'!$S:$S,"*"&$A10&"*")+COUNTIF('Error Handling'!$S:$S,"*"&$A10&"*") -> 5 | H10: =IF(G10=0,"NOT COVERED",IF(G10<2,"Partial","Covered")) -> Covered | I10: OBS-01, OBS-20
A11: GR-08 | B11: Game Rules | C11: Sticky Wilds FS | D11: Sticky Wilds remain until feature end and resize as reels expand | E11: Sticky Wilds FS | F11: PS-MTH-051, PS-FEA-025, PS-FEA-026, PS-FEA-029, PS-FEA-030, PS-FEA-033, PS-EDG-040, PS-INT-024 | G11: =COUNTIF('Functional Testing'!$S:$S,"*"&$A11&"*")+COUNTIF('Math Validation'!$S:$S,"*"&$A11&"*")+COUNTIF('Feature Testing'!$S:$S,"*"&$A11&"*")+COUNTIF('Edge & Boundary Cases'!$S:$S,"*"&$A11&"*")+COUNTIF('UI-UX Testing'!$S:$S,"*"&$A11&"*")+COUNTIF('Compatibility Testing'!$S:$S,"*"&$A11&"*")+COUNTIF('Interruption & Recovery'!$S:$S,"*"&$A11&"*")+COUNTIF('STR - Transaction Testing'!$S:$S,"*"&$A11&"*")+COUNTIF('Error Handling'!$S:$S,"*"&$A11&"*") -> 8 | H11: =IF(G11=0,"NOT COVERED",IF(G11<2,"Partial","Covered")) -> Covered | I11: OBS-07
A12: GR-09 | B12: Game Rules | C12: Raining Wilds FS | D12: 3/4/5/6 Bonus award 15/18/25/30 Free Spins | E12: Raining Wilds FS | F12: PS-FUN-054, PS-MTH-042, PS-MTH-043, PS-MTH-044, PS-MTH-045, PS-FEA-013, PS-FEA-014, PS-FEA-015, PS-FEA-016, PS-FEA-017, PS-FEA-042, PS-FEA-045 | G12: =COUNTIF('Functional Testing'!$S:$S,"*"&$A12&"*")+COUNTIF('Math Validation'!$S:$S,"*"&$A12&"*")+COUNTIF('Feature Testing'!$S:$S,"*"&$A12&"*")+COUNTIF('Edge & Boundary Cases'!$S:$S,"*"&$A12&"*")+COUNTIF('UI-UX Testing'!$S:$S,"*"&$A12&"*")+COUNTIF('Compatibility Testing'!$S:$S,"*"&$A12&"*")+COUNTIF('Interruption & Recovery'!$S:$S,"*"&$A12&"*")+COUNTIF('STR - Transaction Testing'!$S:$S,"*"&$A12&"*")+COUNTIF('Error Handling'!$S:$S,"*"&$A12&"*") -> 12 | H12: =IF(G12=0,"NOT COVERED",IF(G12<2,"Partial","Covered")) -> Covered
A13: GR-10 | B13: Game Rules | C13: Raining Wilds FS | D13: Up to 6 Wilds of any size in random positions per Free Spin | E13: Raining Wilds FS | F13: PS-MTH-048, PS-MTH-049, PS-FEA-035, PS-FEA-036, PS-FEA-038, PS-FEA-039, PS-FEA-040, PS-UI-025 | G13: =COUNTIF('Functional Testing'!$S:$S,"*"&$A13&"*")+COUNTIF('Math Validation'!$S:$S,"*"&$A13&"*")+COUNTIF('Feature Testing'!$S:$S,"*"&$A13&"*")+COUNTIF('Edge & Boundary Cases'!$S:$S,"*"&$A13&"*")+COUNTIF('UI-UX Testing'!$S:$S,"*"&$A13&"*")+COUNTIF('Compatibility Testing'!$S:$S,"*"&$A13&"*")+COUNTIF('Interruption & Recovery'!$S:$S,"*"&$A13&"*")+COUNTIF('STR - Transaction Testing'!$S:$S,"*"&$A13&"*")+COUNTIF('Error Handling'!$S:$S,"*"&$A13&"*") -> 8 | H13: =IF(G13=0,"NOT COVERED",IF(G13<2,"Partial","Covered")) -> Covered | I13: OBS-05
A14: GR-11 | B14: Game Rules | C14: Raining Wilds FS | D14: Each Wild carries multiplier x2 or x3 | E14: Raining Wilds FS | F14: PS-MTH-033, PS-FEA-037 | G14: =COUNTIF('Functional Testing'!$S:$S,"*"&$A14&"*")+COUNTIF('Math Validation'!$S:$S,"*"&$A14&"*")+COUNTIF('Feature Testing'!$S:$S,"*"&$A14&"*")+COUNTIF('Edge & Boundary Cases'!$S:$S,"*"&$A14&"*")+COUNTIF('UI-UX Testing'!$S:$S,"*"&$A14&"*")+COUNTIF('Compatibility Testing'!$S:$S,"*"&$A14&"*")+COUNTIF('Interruption & Recovery'!$S:$S,"*"&$A14&"*")+COUNTIF('STR - Transaction Testing'!$S:$S,"*"&$A14&"*")+COUNTIF('Error Handling'!$S:$S,"*"&$A14&"*") -> 2 | H14: =IF(G14=0,"NOT COVERED",IF(G14<2,"Partial","Covered")) -> Covered | I14: OBS-01
A15: GR-12 | B15: Game Rules | C15: Raining Wilds FS | D15: All Free Spins winnings awarded when feature ends | E15: Free Spins | F15: PS-FEA-003, PS-FEA-008, PS-FEA-009, PS-FEA-015, PS-FEA-020, PS-FEA-021, PS-FEA-059, PS-UI-022, PS-UI-026, PS-STR-005, PS-STR-006 | G15: =COUNTIF('Functional Testing'!$S:$S,"*"&$A15&"*")+COUNTIF('Math Validation'!$S:$S,"*"&$A15&"*")+COUNTIF('Feature Testing'!$S:$S,"*"&$A15&"*")+COUNTIF('Edge & Boundary Cases'!$S:$S,"*"&$A15&"*")+COUNTIF('UI-UX Testing'!$S:$S,"*"&$A15&"*")+COUNTIF('Compatibility Testing'!$S:$S,"*"&$A15&"*")+COUNTIF('Interruption & Recovery'!$S:$S,"*"&$A15&"*")+COUNTIF('STR - Transaction Testing'!$S:$S,"*"&$A15&"*")+COUNTIF('Error Handling'!$S:$S,"*"&$A15&"*") -> 11 | H15: =IF(G15=0,"NOT COVERED",IF(G15<2,"Partial","Covered")) -> Covered | I15: OBS-08
A16: GR-13 | B16: Game Rules | C16: Wild formula | D16: Win = (Bet x Symbol Multiplier / 20) x Product of Wild Multipliers | E16: Wild Multiplier | F16: PS-FUN-048, PS-MTH-027, PS-MTH-028, PS-MTH-029, PS-MTH-030, PS-MTH-031, PS-MTH-036, PS-MTH-037, PS-MTH-057, PS-FEA-034, PS-EDG-015 | G16: =COUNTIF('Functional Testing'!$S:$S,"*"&$A16&"*")+COUNTIF('Math Validation'!$S:$S,"*"&$A16&"*")+COUNTIF('Feature Testing'!$S:$S,"*"&$A16&"*")+COUNTIF('Edge & Boundary Cases'!$S:$S,"*"&$A16&"*")+COUNTIF('UI-UX Testing'!$S:$S,"*"&$A16&"*")+COUNTIF('Compatibility Testing'!$S:$S,"*"&$A16&"*")+COUNTIF('Interruption & Recovery'!$S:$S,"*"&$A16&"*")+COUNTIF('STR - Transaction Testing'!$S:$S,"*"&$A16&"*")+COUNTIF('Error Handling'!$S:$S,"*"&$A16&"*") -> 11 | H16: =IF(G16=0,"NOT COVERED",IF(G16<2,"Partial","Covered")) -> Covered | I16: OBS-17
A17: GR-14 | B17: Game Rules | C17: Free Spins | D17: 3+ Bonus anywhere trigger Free Spins | E17: Free Spins Trigger | F17: PS-FUN-047, PS-FUN-050, PS-FUN-051, PS-MTH-011, PS-FEA-047, PS-EDG-016, PS-EDG-017, PS-EDG-018 | G17: =COUNTIF('Functional Testing'!$S:$S,"*"&$A17&"*")+COUNTIF('Math Validation'!$S:$S,"*"&$A17&"*")+COUNTIF('Feature Testing'!$S:$S,"*"&$A17&"*")+COUNTIF('Edge & Boundary Cases'!$S:$S,"*"&$A17&"*")+COUNTIF('UI-UX Testing'!$S:$S,"*"&$A17&"*")+COUNTIF('Compatibility Testing'!$S:$S,"*"&$A17&"*")+COUNTIF('Interruption & Recovery'!$S:$S,"*"&$A17&"*")+COUNTIF('STR - Transaction Testing'!$S:$S,"*"&$A17&"*")+COUNTIF('Error Handling'!$S:$S,"*"&$A17&"*") -> 8 | H17: =IF(G17=0,"NOT COVERED",IF(G17<2,"Partial","Covered")) -> Covered | I17: OBS-16
A18: GR-15 | B18: Game Rules | C18: Free Spins | D18: Free Spins played at triggering bet | E18: Free Spins | F18: PS-FUN-019, PS-FUN-056, PS-FEA-007, PS-FEA-019, PS-UI-013, PS-STR-005, PS-STR-011, PS-STR-016 | G18: =COUNTIF('Functional Testing'!$S:$S,"*"&$A18&"*")+COUNTIF('Math Validation'!$S:$S,"*"&$A18&"*")+COUNTIF('Feature Testing'!$S:$S,"*"&$A18&"*")+COUNTIF('Edge & Boundary Cases'!$S:$S,"*"&$A18&"*")+COUNTIF('UI-UX Testing'!$S:$S,"*"&$A18&"*")+COUNTIF('Compatibility Testing'!$S:$S,"*"&$A18&"*")+COUNTIF('Interruption & Recovery'!$S:$S,"*"&$A18&"*")+COUNTIF('STR - Transaction Testing'!$S:$S,"*"&$A18&"*")+COUNTIF('Error Handling'!$S:$S,"*"&$A18&"*") -> 8 | H18: =IF(G18=0,"NOT COVERED",IF(G18<2,"Partial","Covered")) -> Covered
A19: GR-16 | B19: Game Rules | C19: Free Spins | D19: Player chooses Sticky Wilds or Raining Wilds | E19: FS Selection | F19: PS-FUN-050, PS-FUN-054, PS-FUN-055, PS-FUN-077, PS-MTH-004, PS-FEA-041, PS-FEA-042, PS-FEA-043, PS-FEA-044, PS-EDG-022, PS-EDG-029, PS-UI-023, PS-CMP-001, PS-CMP-002, PS-CMP-003, PS-CMP-004, PS-CMP-005, PS-CMP-006, PS-CMP-007, PS-CMP-008, PS-CMP-009, PS-CMP-010, PS-CMP-011, PS-CMP-012, PS-CMP-013, PS-STR-010, PS-STR-015 | G19: =COUNTIF('Functional Testing'!$S:$S,"*"&$A19&"*")+COUNTIF('Math Validation'!$S:$S,"*"&$A19&"*")+COUNTIF('Feature Testing'!$S:$S,"*"&$A19&"*")+COUNTIF('Edge & Boundary Cases'!$S:$S,"*"&$A19&"*")+COUNTIF('UI-UX Testing'!$S:$S,"*"&$A19&"*")+COUNTIF('Compatibility Testing'!$S:$S,"*"&$A19&"*")+COUNTIF('Interruption & Recovery'!$S:$S,"*"&$A19&"*")+COUNTIF('STR - Transaction Testing'!$S:$S,"*"&$A19&"*")+COUNTIF('Error Handling'!$S:$S,"*"&$A19&"*") -> 27 | H19: =IF(G19=0,"NOT COVERED",IF(G19<2,"Partial","Covered")) -> Covered | I19: OBS-14, OBS-24
A20: GR-17 | B20: Game Rules | C20: Free Spins | D20: FS count depends on Bonus count and type | E20: FS Award | F20: PS-FUN-054, PS-MTH-038, PS-MTH-039, PS-MTH-040, PS-MTH-041, PS-MTH-042, PS-MTH-043, PS-MTH-044, PS-MTH-045, PS-FEA-001, PS-FEA-002, PS-FEA-003, PS-FEA-004, PS-FEA-005, PS-FEA-013, PS-FEA-014, PS-FEA-015, PS-FEA-016, PS-FEA-017, PS-FEA-045, PS-EDG-017 | G20: =COUNTIF('Functional Testing'!$S:$S,"*"&$A20&"*")+COUNTIF('Math Validation'!$S:$S,"*"&$A20&"*")+COUNTIF('Feature Testing'!$S:$S,"*"&$A20&"*")+COUNTIF('Edge & Boundary Cases'!$S:$S,"*"&$A20&"*")+COUNTIF('UI-UX Testing'!$S:$S,"*"&$A20&"*")+COUNTIF('Compatibility Testing'!$S:$S,"*"&$A20&"*")+COUNTIF('Interruption & Recovery'!$S:$S,"*"&$A20&"*")+COUNTIF('STR - Transaction Testing'!$S:$S,"*"&$A20&"*")+COUNTIF('Error Handling'!$S:$S,"*"&$A20&"*") -> 21 | H20: =IF(G20=0,"NOT COVERED",IF(G20<2,"Partial","Covered")) -> Covered
A21: GR-18 | B21: Game Rules | C21: Free Spins | D21: Free Spins cannot be retriggered | E21: Free Spins | F21: PS-MTH-062, PS-FEA-006, PS-FEA-018 | G21: =COUNTIF('Functional Testing'!$S:$S,"*"&$A21&"*")+COUNTIF('Math Validation'!$S:$S,"*"&$A21&"*")+COUNTIF('Feature Testing'!$S:$S,"*"&$A21&"*")+COUNTIF('Edge & Boundary Cases'!$S:$S,"*"&$A21&"*")+COUNTIF('UI-UX Testing'!$S:$S,"*"&$A21&"*")+COUNTIF('Compatibility Testing'!$S:$S,"*"&$A21&"*")+COUNTIF('Interruption & Recovery'!$S:$S,"*"&$A21&"*")+COUNTIF('STR - Transaction Testing'!$S:$S,"*"&$A21&"*")+COUNTIF('Error Handling'!$S:$S,"*"&$A21&"*") -> 3 | H21: =IF(G21=0,"NOT COVERED",IF(G21<2,"Partial","Covered")) -> Covered
A22: GR-19 | B22: Game Rules | C22: Play | D22: Bets placed in selected currency | E22: Currency / Balance | F22: PS-FUN-001, PS-FUN-003, PS-FUN-004, PS-FUN-022, PS-EDG-037, PS-EDG-038, PS-UI-017, PS-UI-037 | G22: =COUNTIF('Functional Testing'!$S:$S,"*"&$A22&"*")+COUNTIF('Math Validation'!$S:$S,"*"&$A22&"*")+COUNTIF('Feature Testing'!$S:$S,"*"&$A22&"*")+COUNTIF('Edge & Boundary Cases'!$S:$S,"*"&$A22&"*")+COUNTIF('UI-UX Testing'!$S:$S,"*"&$A22&"*")+COUNTIF('Compatibility Testing'!$S:$S,"*"&$A22&"*")+COUNTIF('Interruption & Recovery'!$S:$S,"*"&$A22&"*")+COUNTIF('STR - Transaction Testing'!$S:$S,"*"&$A22&"*")+COUNTIF('Error Handling'!$S:$S,"*"&$A22&"*") -> 8 | H22: =IF(G22=0,"NOT COVERED",IF(G22<2,"Partial","Covered")) -> Covered
A23: GR-20 | B23: Game Rules | C23: Play | D23: Bet adjustable within min/max via bet button or menu | E23: Bet | F23: PS-FUN-014, PS-FUN-015, PS-FUN-016, PS-FUN-017, PS-FUN-018, PS-FUN-079, PS-EDG-005, PS-EDG-041, PS-STR-012 | G23: =COUNTIF('Functional Testing'!$S:$S,"*"&$A23&"*")+COUNTIF('Math Validation'!$S:$S,"*"&$A23&"*")+COUNTIF('Feature Testing'!$S:$S,"*"&$A23&"*")+COUNTIF('Edge & Boundary Cases'!$S:$S,"*"&$A23&"*")+COUNTIF('UI-UX Testing'!$S:$S,"*"&$A23&"*")+COUNTIF('Compatibility Testing'!$S:$S,"*"&$A23&"*")+COUNTIF('Interruption & Recovery'!$S:$S,"*"&$A23&"*")+COUNTIF('STR - Transaction Testing'!$S:$S,"*"&$A23&"*")+COUNTIF('Error Handling'!$S:$S,"*"&$A23&"*") -> 9 | H23: =IF(G23=0,"NOT COVERED",IF(G23<2,"Partial","Covered")) -> Covered
A24: GR-21 | B24: Game Rules | C24: Play | D24: Total bet displayed in bet field | E24: Bet | F24: PS-FUN-001, PS-FUN-017 | G24: =COUNTIF('Functional Testing'!$S:$S,"*"&$A24&"*")+COUNTIF('Math Validation'!$S:$S,"*"&$A24&"*")+COUNTIF('Feature Testing'!$S:$S,"*"&$A24&"*")+COUNTIF('Edge & Boundary Cases'!$S:$S,"*"&$A24&"*")+COUNTIF('UI-UX Testing'!$S:$S,"*"&$A24&"*")+COUNTIF('Compatibility Testing'!$S:$S,"*"&$A24&"*")+COUNTIF('Interruption & Recovery'!$S:$S,"*"&$A24&"*")+COUNTIF('STR - Transaction Testing'!$S:$S,"*"&$A24&"*")+COUNTIF('Error Handling'!$S:$S,"*"&$A24&"*") -> 2 | H24: =IF(G24=0,"NOT COVERED",IF(G24<2,"Partial","Covered")) -> Covered
A25: GR-22 | B25: Game Rules | C25: Play | D25: Play button starts a round at current bet | E25: Spin | F25: PS-FUN-009, PS-FUN-018, PS-FUN-020, PS-EDG-001, PS-EDG-003, PS-EDG-019, PS-EDG-021, PS-EDG-032, PS-UI-038, PS-CMP-001, PS-CMP-002, PS-CMP-003, PS-CMP-004, PS-CMP-005, PS-CMP-006, PS-CMP-007, PS-CMP-008, PS-CMP-009, PS-CMP-010, PS-CMP-011, PS-CMP-012, PS-CMP-013, PS-STR-001, PS-STR-003, PS-STR-007, PS-STR-008, PS-STR-009, PS-STR-017, PS-STR-018, PS-STR-019, PS-STR-021, PS-STR-022, PS-STR-024, PS-STR-025, PS-STR-027, PS-ERR-001 | G25: =COUNTIF('Functional Testing'!$S:$S,"*"&$A25&"*")+COUNTIF('Math Validation'!$S:$S,"*"&$A25&"*")+COUNTIF('Feature Testing'!$S:$S,"*"&$A25&"*")+COUNTIF('Edge & Boundary Cases'!$S:$S,"*"&$A25&"*")+COUNTIF('UI-UX Testing'!$S:$S,"*"&$A25&"*")+COUNTIF('Compatibility Testing'!$S:$S,"*"&$A25&"*")+COUNTIF('Interruption & Recovery'!$S:$S,"*"&$A25&"*")+COUNTIF('STR - Transaction Testing'!$S:$S,"*"&$A25&"*")+COUNTIF('Error Handling'!$S:$S,"*"&$A25&"*") -> 36 | H25: =IF(G25=0,"NOT COVERED",IF(G25<2,"Partial","Covered")) -> Covered
A26: GR-23 | B26: Game Rules | C26: Win | D26: 2+ high-value or 3+ low-value matching symbols pay | E26: Win Evaluation | F26: PS-FUN-041 | G26: =COUNTIF('Functional Testing'!$S:$S,"*"&$A26&"*")+COUNTIF('Math Validation'!$S:$S,"*"&$A26&"*")+COUNTIF('Feature Testing'!$S:$S,"*"&$A26&"*")+COUNTIF('Edge & Boundary Cases'!$S:$S,"*"&$A26&"*")+COUNTIF('UI-UX Testing'!$S:$S,"*"&$A26&"*")+COUNTIF('Compatibility Testing'!$S:$S,"*"&$A26&"*")+COUNTIF('Interruption & Recovery'!$S:$S,"*"&$A26&"*")+COUNTIF('STR - Transaction Testing'!$S:$S,"*"&$A26&"*")+COUNTIF('Error Handling'!$S:$S,"*"&$A26&"*") -> 1 | H26: =IF(G26=0,"NOT COVERED",IF(G26<2,"Partial","Covered")) -> Partial | I26: OBS-03
A27: GR-24 | B27: Game Rules | C27: Win | D27: Regular symbol wins pay left to right only | E27: Win Evaluation | F27: PS-FUN-038 | G27: =COUNTIF('Functional Testing'!$S:$S,"*"&$A27&"*")+COUNTIF('Math Validation'!$S:$S,"*"&$A27&"*")+COUNTIF('Feature Testing'!$S:$S,"*"&$A27&"*")+COUNTIF('Edge & Boundary Cases'!$S:$S,"*"&$A27&"*")+COUNTIF('UI-UX Testing'!$S:$S,"*"&$A27&"*")+COUNTIF('Compatibility Testing'!$S:$S,"*"&$A27&"*")+COUNTIF('Interruption & Recovery'!$S:$S,"*"&$A27&"*")+COUNTIF('STR - Transaction Testing'!$S:$S,"*"&$A27&"*")+COUNTIF('Error Handling'!$S:$S,"*"&$A27&"*") -> 1 | H27: =IF(G27=0,"NOT COVERED",IF(G27<2,"Partial","Covered")) -> Partial
A28: GR-25 | B28: Game Rules | C28: Win | D28: Wins paid per paytable, displayed in win field | E28: Win Display | F28: PS-FUN-021, PS-FUN-042, PS-EDG-009, PS-EDG-013, PS-UI-018, PS-UI-019, PS-UI-020, PS-UI-021, PS-UI-039, PS-STR-002 | G28: =COUNTIF('Functional Testing'!$S:$S,"*"&$A28&"*")+COUNTIF('Math Validation'!$S:$S,"*"&$A28&"*")+COUNTIF('Feature Testing'!$S:$S,"*"&$A28&"*")+COUNTIF('Edge & Boundary Cases'!$S:$S,"*"&$A28&"*")+COUNTIF('UI-UX Testing'!$S:$S,"*"&$A28&"*")+COUNTIF('Compatibility Testing'!$S:$S,"*"&$A28&"*")+COUNTIF('Interruption & Recovery'!$S:$S,"*"&$A28&"*")+COUNTIF('STR - Transaction Testing'!$S:$S,"*"&$A28&"*")+COUNTIF('Error Handling'!$S:$S,"*"&$A28&"*") -> 10 | H28: =IF(G28=0,"NOT COVERED",IF(G28<2,"Partial","Covered")) -> Covered | I28: OBS-22
A29: GR-26 | B29: Game Rules | C29: Win | D29: Only highest win on each active payline paid | E29: Win Evaluation | F29: PS-FUN-043 | G29: =COUNTIF('Functional Testing'!$S:$S,"*"&$A29&"*")+COUNTIF('Math Validation'!$S:$S,"*"&$A29&"*")+COUNTIF('Feature Testing'!$S:$S,"*"&$A29&"*")+COUNTIF('Edge & Boundary Cases'!$S:$S,"*"&$A29&"*")+COUNTIF('UI-UX Testing'!$S:$S,"*"&$A29&"*")+COUNTIF('Compatibility Testing'!$S:$S,"*"&$A29&"*")+COUNTIF('Interruption & Recovery'!$S:$S,"*"&$A29&"*")+COUNTIF('STR - Transaction Testing'!$S:$S,"*"&$A29&"*")+COUNTIF('Error Handling'!$S:$S,"*"&$A29&"*") -> 1 | H29: =IF(G29=0,"NOT COVERED",IF(G29<2,"Partial","Covered")) -> Partial | I29: OBS-04
A30: GR-27 | B30: Game Rules | C30: Win | D30: More matching symbols award higher payout | E30: Paytable | F30: PS-FUN-043, PS-FUN-044 | G30: =COUNTIF('Functional Testing'!$S:$S,"*"&$A30&"*")+COUNTIF('Math Validation'!$S:$S,"*"&$A30&"*")+COUNTIF('Feature Testing'!$S:$S,"*"&$A30&"*")+COUNTIF('Edge & Boundary Cases'!$S:$S,"*"&$A30&"*")+COUNTIF('UI-UX Testing'!$S:$S,"*"&$A30&"*")+COUNTIF('Compatibility Testing'!$S:$S,"*"&$A30&"*")+COUNTIF('Interruption & Recovery'!$S:$S,"*"&$A30&"*")+COUNTIF('STR - Transaction Testing'!$S:$S,"*"&$A30&"*")+COUNTIF('Error Handling'!$S:$S,"*"&$A30&"*") -> 2 | H30: =IF(G30=0,"NOT COVERED",IF(G30<2,"Partial","Covered")) -> Covered
A31: GR-28 | B31: Game Rules | C31: Bet and Max Win | D31: Min Bet / Max Bet values | E31: Bet | F31: PS-FUN-015, PS-FUN-016, PS-MTH-058, PS-EDG-001, PS-EDG-002, PS-EDG-007, PS-EDG-008, PS-UI-036, PS-STR-012, PS-STR-013 | G31: =COUNTIF('Functional Testing'!$S:$S,"*"&$A31&"*")+COUNTIF('Math Validation'!$S:$S,"*"&$A31&"*")+COUNTIF('Feature Testing'!$S:$S,"*"&$A31&"*")+COUNTIF('Edge & Boundary Cases'!$S:$S,"*"&$A31&"*")+COUNTIF('UI-UX Testing'!$S:$S,"*"&$A31&"*")+COUNTIF('Compatibility Testing'!$S:$S,"*"&$A31&"*")+COUNTIF('Interruption & Recovery'!$S:$S,"*"&$A31&"*")+COUNTIF('STR - Transaction Testing'!$S:$S,"*"&$A31&"*")+COUNTIF('Error Handling'!$S:$S,"*"&$A31&"*") -> 10 | H31: =IF(G31=0,"NOT COVERED",IF(G31<2,"Partial","Covered")) -> Covered | I31: OBS-09
A32: GR-29 | B32: Game Rules | C32: Bet and Max Win | D32: Winnings capped in base and FS; cap credited | E32: Max Win | F32: PS-FUN-086, PS-MTH-053, PS-MTH-054, PS-MTH-055, PS-MTH-056, PS-FEA-012, PS-FEA-024, PS-EDG-010, PS-EDG-011, PS-EDG-012, PS-EDG-014, PS-EDG-015, PS-UI-028, PS-INT-026, PS-STR-023, PS-ERR-019 | G32: =COUNTIF('Functional Testing'!$S:$S,"*"&$A32&"*")+COUNTIF('Math Validation'!$S:$S,"*"&$A32&"*")+COUNTIF('Feature Testing'!$S:$S,"*"&$A32&"*")+COUNTIF('Edge & Boundary Cases'!$S:$S,"*"&$A32&"*")+COUNTIF('UI-UX Testing'!$S:$S,"*"&$A32&"*")+COUNTIF('Compatibility Testing'!$S:$S,"*"&$A32&"*")+COUNTIF('Interruption & Recovery'!$S:$S,"*"&$A32&"*")+COUNTIF('STR - Transaction Testing'!$S:$S,"*"&$A32&"*")+COUNTIF('Error Handling'!$S:$S,"*"&$A32&"*") -> 16 | H32: =IF(G32=0,"NOT COVERED",IF(G32<2,"Partial","Covered")) -> Covered | I32: OBS-09, OBS-12
A33: GR-30 | B33: Game Rules | C33: Quick Spin | D33: Quick Spin speeds up play; jurisdiction dependent | E33: Quick Spin | F33: PS-FUN-067, PS-FUN-068 | G33: =COUNTIF('Functional Testing'!$S:$S,"*"&$A33&"*")+COUNTIF('Math Validation'!$S:$S,"*"&$A33&"*")+COUNTIF('Feature Testing'!$S:$S,"*"&$A33&"*")+COUNTIF('Edge & Boundary Cases'!$S:$S,"*"&$A33&"*")+COUNTIF('UI-UX Testing'!$S:$S,"*"&$A33&"*")+COUNTIF('Compatibility Testing'!$S:$S,"*"&$A33&"*")+COUNTIF('Interruption & Recovery'!$S:$S,"*"&$A33&"*")+COUNTIF('STR - Transaction Testing'!$S:$S,"*"&$A33&"*")+COUNTIF('Error Handling'!$S:$S,"*"&$A33&"*") -> 2 | H33: =IF(G33=0,"NOT COVERED",IF(G33<2,"Partial","Covered")) -> Covered | I33: OBS-18
A34: GR-31 | B34: Game Rules | C34: Quick Stop | D34: Press spin again to stop reels early; jurisdiction dependent | E34: Quick Stop | F34: PS-FUN-012, PS-FUN-013, PS-UI-012, PS-UI-046 | G34: =COUNTIF('Functional Testing'!$S:$S,"*"&$A34&"*")+COUNTIF('Math Validation'!$S:$S,"*"&$A34&"*")+COUNTIF('Feature Testing'!$S:$S,"*"&$A34&"*")+COUNTIF('Edge & Boundary Cases'!$S:$S,"*"&$A34&"*")+COUNTIF('UI-UX Testing'!$S:$S,"*"&$A34&"*")+COUNTIF('Compatibility Testing'!$S:$S,"*"&$A34&"*")+COUNTIF('Interruption & Recovery'!$S:$S,"*"&$A34&"*")+COUNTIF('STR - Transaction Testing'!$S:$S,"*"&$A34&"*")+COUNTIF('Error Handling'!$S:$S,"*"&$A34&"*") -> 4 | H34: =IF(G34=0,"NOT COVERED",IF(G34<2,"Partial","Covered")) -> Covered | I34: OBS-19
A35: GR-32 | B35: Game Rules | C35: Buy Free Spins | D35: Buy Feature opens interface with feature settings | E35: Buy Feature | F35: PS-FUN-057, PS-FUN-060, PS-FUN-064, PS-FEA-048, PS-FEA-052, PS-FEA-053, PS-EDG-023, PS-UI-030, PS-CMP-001, PS-CMP-002, PS-CMP-003, PS-CMP-004, PS-CMP-005, PS-CMP-006, PS-CMP-007, PS-CMP-008, PS-CMP-009, PS-CMP-010, PS-CMP-011, PS-CMP-012, PS-CMP-013 | G35: =COUNTIF('Functional Testing'!$S:$S,"*"&$A35&"*")+COUNTIF('Math Validation'!$S:$S,"*"&$A35&"*")+COUNTIF('Feature Testing'!$S:$S,"*"&$A35&"*")+COUNTIF('Edge & Boundary Cases'!$S:$S,"*"&$A35&"*")+COUNTIF('UI-UX Testing'!$S:$S,"*"&$A35&"*")+COUNTIF('Compatibility Testing'!$S:$S,"*"&$A35&"*")+COUNTIF('Interruption & Recovery'!$S:$S,"*"&$A35&"*")+COUNTIF('STR - Transaction Testing'!$S:$S,"*"&$A35&"*")+COUNTIF('Error Handling'!$S:$S,"*"&$A35&"*") -> 21 | H35: =IF(G35=0,"NOT COVERED",IF(G35<2,"Partial","Covered")) -> Covered | I35: OBS-10
A36: GR-33 | B36: Game Rules | C36: Buy Free Spins | D36: Confirm starts feature-triggering spin at selected bet | E36: Buy Feature | F36: PS-FUN-059, PS-FEA-049, PS-FEA-050, PS-FEA-051 | G36: =COUNTIF('Functional Testing'!$S:$S,"*"&$A36&"*")+COUNTIF('Math Validation'!$S:$S,"*"&$A36&"*")+COUNTIF('Feature Testing'!$S:$S,"*"&$A36&"*")+COUNTIF('Edge & Boundary Cases'!$S:$S,"*"&$A36&"*")+COUNTIF('UI-UX Testing'!$S:$S,"*"&$A36&"*")+COUNTIF('Compatibility Testing'!$S:$S,"*"&$A36&"*")+COUNTIF('Interruption & Recovery'!$S:$S,"*"&$A36&"*")+COUNTIF('STR - Transaction Testing'!$S:$S,"*"&$A36&"*")+COUNTIF('Error Handling'!$S:$S,"*"&$A36&"*") -> 4 | H36: =IF(G36=0,"NOT COVERED",IF(G36<2,"Partial","Covered")) -> Covered
A37: GR-34 | B37: Game Rules | C37: Buy Free Spins | D37: Triggering spin awards applicable wins | E37: Buy Feature | F37: PS-FUN-061, PS-FEA-047 | G37: =COUNTIF('Functional Testing'!$S:$S,"*"&$A37&"*")+COUNTIF('Math Validation'!$S:$S,"*"&$A37&"*")+COUNTIF('Feature Testing'!$S:$S,"*"&$A37&"*")+COUNTIF('Edge & Boundary Cases'!$S:$S,"*"&$A37&"*")+COUNTIF('UI-UX Testing'!$S:$S,"*"&$A37&"*")+COUNTIF('Compatibility Testing'!$S:$S,"*"&$A37&"*")+COUNTIF('Interruption & Recovery'!$S:$S,"*"&$A37&"*")+COUNTIF('STR - Transaction Testing'!$S:$S,"*"&$A37&"*")+COUNTIF('Error Handling'!$S:$S,"*"&$A37&"*") -> 2 | H37: =IF(G37=0,"NOT COVERED",IF(G37<2,"Partial","Covered")) -> Covered
A38: GR-35 | B38: Game Rules | C38: Buy Free Spins | D38: Bet reverts to pre-purchase value after feature | E38: Buy Feature | F38: PS-FUN-062 | G38: =COUNTIF('Functional Testing'!$S:$S,"*"&$A38&"*")+COUNTIF('Math Validation'!$S:$S,"*"&$A38&"*")+COUNTIF('Feature Testing'!$S:$S,"*"&$A38&"*")+COUNTIF('Edge & Boundary Cases'!$S:$S,"*"&$A38&"*")+COUNTIF('UI-UX Testing'!$S:$S,"*"&$A38&"*")+COUNTIF('Compatibility Testing'!$S:$S,"*"&$A38&"*")+COUNTIF('Interruption & Recovery'!$S:$S,"*"&$A38&"*")+COUNTIF('STR - Transaction Testing'!$S:$S,"*"&$A38&"*")+COUNTIF('Error Handling'!$S:$S,"*"&$A38&"*") -> 1 | H38: =IF(G38=0,"NOT COVERED",IF(G38<2,"Partial","Covered")) -> Partial
A39: GR-36 | B39: Game Rules | C39: Buy Free Spins | D39: Buy cost 100x total bet | E39: Buy Feature | F39: PS-FUN-057, PS-FUN-058, PS-FUN-059, PS-FUN-063, PS-FUN-083, PS-FEA-053, PS-EDG-006, PS-EDG-007, PS-EDG-008, PS-STR-004, PS-STR-014, PS-ERR-002 | G39: =COUNTIF('Functional Testing'!$S:$S,"*"&$A39&"*")+COUNTIF('Math Validation'!$S:$S,"*"&$A39&"*")+COUNTIF('Feature Testing'!$S:$S,"*"&$A39&"*")+COUNTIF('Edge & Boundary Cases'!$S:$S,"*"&$A39&"*")+COUNTIF('UI-UX Testing'!$S:$S,"*"&$A39&"*")+COUNTIF('Compatibility Testing'!$S:$S,"*"&$A39&"*")+COUNTIF('Interruption & Recovery'!$S:$S,"*"&$A39&"*")+COUNTIF('STR - Transaction Testing'!$S:$S,"*"&$A39&"*")+COUNTIF('Error Handling'!$S:$S,"*"&$A39&"*") -> 12 | H39: =IF(G39=0,"NOT COVERED",IF(G39<2,"Partial","Covered")) -> Covered
A40: GR-37 | B40: Game Rules | C40: Turbo Spin | D40: Turbo toggle reduces spin and win animation duration | E40: Turbo | F40: PS-FUN-065, PS-FUN-066, PS-FEA-046, PS-UI-016, PS-UI-040 | G40: =COUNTIF('Functional Testing'!$S:$S,"*"&$A40&"*")+COUNTIF('Math Validation'!$S:$S,"*"&$A40&"*")+COUNTIF('Feature Testing'!$S:$S,"*"&$A40&"*")+COUNTIF('Edge & Boundary Cases'!$S:$S,"*"&$A40&"*")+COUNTIF('UI-UX Testing'!$S:$S,"*"&$A40&"*")+COUNTIF('Compatibility Testing'!$S:$S,"*"&$A40&"*")+COUNTIF('Interruption & Recovery'!$S:$S,"*"&$A40&"*")+COUNTIF('STR - Transaction Testing'!$S:$S,"*"&$A40&"*")+COUNTIF('Error Handling'!$S:$S,"*"&$A40&"*") -> 5 | H40: =IF(G40=0,"NOT COVERED",IF(G40<2,"Partial","Covered")) -> Covered | I40: OBS-18
A41: GR-38 | B41: Game Rules | C41: Auto Spin | D41: Desktop: hold Play 2s opens Auto Spin menu | E41: Auto Spin | F41: PS-FUN-069, PS-FUN-070, PS-EDG-025 | G41: =COUNTIF('Functional Testing'!$S:$S,"*"&$A41&"*")+COUNTIF('Math Validation'!$S:$S,"*"&$A41&"*")+COUNTIF('Feature Testing'!$S:$S,"*"&$A41&"*")+COUNTIF('Edge & Boundary Cases'!$S:$S,"*"&$A41&"*")+COUNTIF('UI-UX Testing'!$S:$S,"*"&$A41&"*")+COUNTIF('Compatibility Testing'!$S:$S,"*"&$A41&"*")+COUNTIF('Interruption & Recovery'!$S:$S,"*"&$A41&"*")+COUNTIF('STR - Transaction Testing'!$S:$S,"*"&$A41&"*")+COUNTIF('Error Handling'!$S:$S,"*"&$A41&"*") -> 3 | H41: =IF(G41=0,"NOT COVERED",IF(G41<2,"Partial","Covered")) -> Covered
A42: GR-39 | B42: Game Rules | C42: Auto Spin | D42: Mobile: hold Play 2s, select, tap Start | E42: Auto Spin | F42: PS-FUN-071 | G42: =COUNTIF('Functional Testing'!$S:$S,"*"&$A42&"*")+COUNTIF('Math Validation'!$S:$S,"*"&$A42&"*")+COUNTIF('Feature Testing'!$S:$S,"*"&$A42&"*")+COUNTIF('Edge & Boundary Cases'!$S:$S,"*"&$A42&"*")+COUNTIF('UI-UX Testing'!$S:$S,"*"&$A42&"*")+COUNTIF('Compatibility Testing'!$S:$S,"*"&$A42&"*")+COUNTIF('Interruption & Recovery'!$S:$S,"*"&$A42&"*")+COUNTIF('STR - Transaction Testing'!$S:$S,"*"&$A42&"*")+COUNTIF('Error Handling'!$S:$S,"*"&$A42&"*") -> 1 | H42: =IF(G42=0,"NOT COVERED",IF(G42<2,"Partial","Covered")) -> Partial
A43: GR-40 | B43: Game Rules | C43: Auto Spin | D43: Stop condition based on spend limit | E43: Auto Spin | F43: PS-FUN-076, PS-EDG-024 | G43: =COUNTIF('Functional Testing'!$S:$S,"*"&$A43&"*")+COUNTIF('Math Validation'!$S:$S,"*"&$A43&"*")+COUNTIF('Feature Testing'!$S:$S,"*"&$A43&"*")+COUNTIF('Edge & Boundary Cases'!$S:$S,"*"&$A43&"*")+COUNTIF('UI-UX Testing'!$S:$S,"*"&$A43&"*")+COUNTIF('Compatibility Testing'!$S:$S,"*"&$A43&"*")+COUNTIF('Interruption & Recovery'!$S:$S,"*"&$A43&"*")+COUNTIF('STR - Transaction Testing'!$S:$S,"*"&$A43&"*")+COUNTIF('Error Handling'!$S:$S,"*"&$A43&"*") -> 2 | H43: =IF(G43=0,"NOT COVERED",IF(G43<2,"Partial","Covered")) -> Covered | I43: OBS-21
A44: GR-41 | B44: Game Rules | C44: Auto Spin | D44: Panel shows total, remaining and total win | E44: Auto Spin | F44: PS-FUN-073, PS-UI-031 | G44: =COUNTIF('Functional Testing'!$S:$S,"*"&$A44&"*")+COUNTIF('Math Validation'!$S:$S,"*"&$A44&"*")+COUNTIF('Feature Testing'!$S:$S,"*"&$A44&"*")+COUNTIF('Edge & Boundary Cases'!$S:$S,"*"&$A44&"*")+COUNTIF('UI-UX Testing'!$S:$S,"*"&$A44&"*")+COUNTIF('Compatibility Testing'!$S:$S,"*"&$A44&"*")+COUNTIF('Interruption & Recovery'!$S:$S,"*"&$A44&"*")+COUNTIF('STR - Transaction Testing'!$S:$S,"*"&$A44&"*")+COUNTIF('Error Handling'!$S:$S,"*"&$A44&"*") -> 2 | H44: =IF(G44=0,"NOT COVERED",IF(G44<2,"Partial","Covered")) -> Covered
A45: GR-42 | B45: Game Rules | C45: Auto Spin | D45: Start and Cancel buttons | E45: Auto Spin | F45: PS-FUN-075 | G45: =COUNTIF('Functional Testing'!$S:$S,"*"&$A45&"*")+COUNTIF('Math Validation'!$S:$S,"*"&$A45&"*")+COUNTIF('Feature Testing'!$S:$S,"*"&$A45&"*")+COUNTIF('Edge & Boundary Cases'!$S:$S,"*"&$A45&"*")+COUNTIF('UI-UX Testing'!$S:$S,"*"&$A45&"*")+COUNTIF('Compatibility Testing'!$S:$S,"*"&$A45&"*")+COUNTIF('Interruption & Recovery'!$S:$S,"*"&$A45&"*")+COUNTIF('STR - Transaction Testing'!$S:$S,"*"&$A45&"*")+COUNTIF('Error Handling'!$S:$S,"*"&$A45&"*") -> 1 | H45: =IF(G45=0,"NOT COVERED",IF(G45<2,"Partial","Covered")) -> Partial
A46: GR-43 | B46: Game Rules | C46: Auto Spin | D46: Ends after selected count; Stop anytime | E46: Auto Spin | F46: PS-FUN-072, PS-FUN-074, PS-FUN-077, PS-FUN-078, PS-EDG-026, PS-EDG-027, PS-INT-027 | G46: =COUNTIF('Functional Testing'!$S:$S,"*"&$A46&"*")+COUNTIF('Math Validation'!$S:$S,"*"&$A46&"*")+COUNTIF('Feature Testing'!$S:$S,"*"&$A46&"*")+COUNTIF('Edge & Boundary Cases'!$S:$S,"*"&$A46&"*")+COUNTIF('UI-UX Testing'!$S:$S,"*"&$A46&"*")+COUNTIF('Compatibility Testing'!$S:$S,"*"&$A46&"*")+COUNTIF('Interruption & Recovery'!$S:$S,"*"&$A46&"*")+COUNTIF('STR - Transaction Testing'!$S:$S,"*"&$A46&"*")+COUNTIF('Error Handling'!$S:$S,"*"&$A46&"*") -> 7 | H46: =IF(G46=0,"NOT COVERED",IF(G46<2,"Partial","Covered")) -> Covered | I46: OBS-24
A47: GR-44 | B47: Game Rules | C47: How to Play | D47: Spin via button or space bar | E47: Spin | F47: PS-FUN-010, PS-FUN-011, PS-EDG-020 | G47: =COUNTIF('Functional Testing'!$S:$S,"*"&$A47&"*")+COUNTIF('Math Validation'!$S:$S,"*"&$A47&"*")+COUNTIF('Feature Testing'!$S:$S,"*"&$A47&"*")+COUNTIF('Edge & Boundary Cases'!$S:$S,"*"&$A47&"*")+COUNTIF('UI-UX Testing'!$S:$S,"*"&$A47&"*")+COUNTIF('Compatibility Testing'!$S:$S,"*"&$A47&"*")+COUNTIF('Interruption & Recovery'!$S:$S,"*"&$A47&"*")+COUNTIF('STR - Transaction Testing'!$S:$S,"*"&$A47&"*")+COUNTIF('Error Handling'!$S:$S,"*"&$A47&"*") -> 3 | H47: =IF(G47=0,"NOT COVERED",IF(G47<2,"Partial","Covered")) -> Covered
A48: GR-45 | B48: Game Rules | C48: How to Play | D48: Bet panel controls | E48: Bet | F48: PS-FUN-014 | G48: =COUNTIF('Functional Testing'!$S:$S,"*"&$A48&"*")+COUNTIF('Math Validation'!$S:$S,"*"&$A48&"*")+COUNTIF('Feature Testing'!$S:$S,"*"&$A48&"*")+COUNTIF('Edge & Boundary Cases'!$S:$S,"*"&$A48&"*")+COUNTIF('UI-UX Testing'!$S:$S,"*"&$A48&"*")+COUNTIF('Compatibility Testing'!$S:$S,"*"&$A48&"*")+COUNTIF('Interruption & Recovery'!$S:$S,"*"&$A48&"*")+COUNTIF('STR - Transaction Testing'!$S:$S,"*"&$A48&"*")+COUNTIF('Error Handling'!$S:$S,"*"&$A48&"*") -> 1 | H48: =IF(G48=0,"NOT COVERED",IF(G48<2,"Partial","Covered")) -> Partial
A49: GR-46 | B49: Game Rules | C49: How to Play | D49: Menu options (Lobby, History, Sound, Rules, Splash, Deposit, Promotions) | E49: Menu | F49: PS-FUN-002, PS-FUN-080, PS-FUN-081, PS-EDG-004, PS-UI-027, PS-STR-026 | G49: =COUNTIF('Functional Testing'!$S:$S,"*"&$A49&"*")+COUNTIF('Math Validation'!$S:$S,"*"&$A49&"*")+COUNTIF('Feature Testing'!$S:$S,"*"&$A49&"*")+COUNTIF('Edge & Boundary Cases'!$S:$S,"*"&$A49&"*")+COUNTIF('UI-UX Testing'!$S:$S,"*"&$A49&"*")+COUNTIF('Compatibility Testing'!$S:$S,"*"&$A49&"*")+COUNTIF('Interruption & Recovery'!$S:$S,"*"&$A49&"*")+COUNTIF('STR - Transaction Testing'!$S:$S,"*"&$A49&"*")+COUNTIF('Error Handling'!$S:$S,"*"&$A49&"*") -> 6 | H49: =IF(G49=0,"NOT COVERED",IF(G49<2,"Partial","Covered")) -> Covered
A50: GR-47 | B50: Game Rules | C50: How to Play | D50: History shows result, bet, win, date/time, features | E50: History | F50: PS-FUN-082, PS-FUN-083, PS-EDG-039, PS-STR-020 | G50: =COUNTIF('Functional Testing'!$S:$S,"*"&$A50&"*")+COUNTIF('Math Validation'!$S:$S,"*"&$A50&"*")+COUNTIF('Feature Testing'!$S:$S,"*"&$A50&"*")+COUNTIF('Edge & Boundary Cases'!$S:$S,"*"&$A50&"*")+COUNTIF('UI-UX Testing'!$S:$S,"*"&$A50&"*")+COUNTIF('Compatibility Testing'!$S:$S,"*"&$A50&"*")+COUNTIF('Interruption & Recovery'!$S:$S,"*"&$A50&"*")+COUNTIF('STR - Transaction Testing'!$S:$S,"*"&$A50&"*")+COUNTIF('Error Handling'!$S:$S,"*"&$A50&"*") -> 4 | H50: =IF(G50=0,"NOT COVERED",IF(G50<2,"Partial","Covered")) -> Covered
A51: GR-48 | B51: Game Rules | C51: How to Play | D51: Info button opens rules and paytable | E51: Game Info | F51: PS-FUN-037, PS-FUN-084, PS-UI-032, PS-UI-033, PS-UI-035 | G51: =COUNTIF('Functional Testing'!$S:$S,"*"&$A51&"*")+COUNTIF('Math Validation'!$S:$S,"*"&$A51&"*")+COUNTIF('Feature Testing'!$S:$S,"*"&$A51&"*")+COUNTIF('Edge & Boundary Cases'!$S:$S,"*"&$A51&"*")+COUNTIF('UI-UX Testing'!$S:$S,"*"&$A51&"*")+COUNTIF('Compatibility Testing'!$S:$S,"*"&$A51&"*")+COUNTIF('Interruption & Recovery'!$S:$S,"*"&$A51&"*")+COUNTIF('STR - Transaction Testing'!$S:$S,"*"&$A51&"*")+COUNTIF('Error Handling'!$S:$S,"*"&$A51&"*") -> 5 | H51: =IF(G51=0,"NOT COVERED",IF(G51<2,"Partial","Covered")) -> Covered
A52: GR-49 | B52: Game Rules | C52: How to Play | D52: Sound toggles incl. ambient and effects | E52: Audio | F52: PS-FUN-087, PS-FUN-088, PS-FEA-046, PS-UI-041, PS-UI-042, PS-UI-043, PS-UI-044, PS-UI-045, PS-UI-046, PS-UI-047 | G52: =COUNTIF('Functional Testing'!$S:$S,"*"&$A52&"*")+COUNTIF('Math Validation'!$S:$S,"*"&$A52&"*")+COUNTIF('Feature Testing'!$S:$S,"*"&$A52&"*")+COUNTIF('Edge & Boundary Cases'!$S:$S,"*"&$A52&"*")+COUNTIF('UI-UX Testing'!$S:$S,"*"&$A52&"*")+COUNTIF('Compatibility Testing'!$S:$S,"*"&$A52&"*")+COUNTIF('Interruption & Recovery'!$S:$S,"*"&$A52&"*")+COUNTIF('STR - Transaction Testing'!$S:$S,"*"&$A52&"*")+COUNTIF('Error Handling'!$S:$S,"*"&$A52&"*") -> 10 | H52: =IF(G52=0,"NOT COVERED",IF(G52<2,"Partial","Covered")) -> Covered
A53: GR-50 | B53: Game Rules | C53: Paytable | D53: Paytable values based on current bet | E53: Paytable | F53: PS-FUN-023, PS-FUN-024, PS-FUN-025, PS-FUN-026, PS-FUN-027, PS-FUN-028, PS-FUN-029, PS-FUN-030, PS-FUN-031, PS-FUN-032, PS-FUN-033, PS-FUN-034, PS-UI-032 | G53: =COUNTIF('Functional Testing'!$S:$S,"*"&$A53&"*")+COUNTIF('Math Validation'!$S:$S,"*"&$A53&"*")+COUNTIF('Feature Testing'!$S:$S,"*"&$A53&"*")+COUNTIF('Edge & Boundary Cases'!$S:$S,"*"&$A53&"*")+COUNTIF('UI-UX Testing'!$S:$S,"*"&$A53&"*")+COUNTIF('Compatibility Testing'!$S:$S,"*"&$A53&"*")+COUNTIF('Interruption & Recovery'!$S:$S,"*"&$A53&"*")+COUNTIF('STR - Transaction Testing'!$S:$S,"*"&$A53&"*")+COUNTIF('Error Handling'!$S:$S,"*"&$A53&"*") -> 13 | H53: =IF(G53=0,"NOT COVERED",IF(G53<2,"Partial","Covered")) -> Covered | I53: OBS-15
A54: GR-51 | B54: Game Rules | C54: Paytable | D54: Select symbol on reels to view its paytable | E54: Paytable | F54: PS-FUN-035, PS-FUN-036 | G54: =COUNTIF('Functional Testing'!$S:$S,"*"&$A54&"*")+COUNTIF('Math Validation'!$S:$S,"*"&$A54&"*")+COUNTIF('Feature Testing'!$S:$S,"*"&$A54&"*")+COUNTIF('Edge & Boundary Cases'!$S:$S,"*"&$A54&"*")+COUNTIF('UI-UX Testing'!$S:$S,"*"&$A54&"*")+COUNTIF('Compatibility Testing'!$S:$S,"*"&$A54&"*")+COUNTIF('Interruption & Recovery'!$S:$S,"*"&$A54&"*")+COUNTIF('STR - Transaction Testing'!$S:$S,"*"&$A54&"*")+COUNTIF('Error Handling'!$S:$S,"*"&$A54&"*") -> 2 | H54: =IF(G54=0,"NOT COVERED",IF(G54<2,"Partial","Covered")) -> Covered
A55: GR-52 | B55: Game Rules | C55: Game Controls | D55: Buttons: Play, Stop, Bet, Turbo, Menu, Info, Sound, Close | E55: UI Controls | F55: PS-FUN-014, PS-FUN-060, PS-FUN-065, PS-FUN-069, PS-FUN-074, PS-FUN-080, PS-FUN-084, PS-FUN-087, PS-UI-002, PS-UI-003, PS-UI-004, PS-UI-005, PS-UI-006, PS-UI-007, PS-UI-008, PS-UI-011, PS-UI-012, PS-UI-014, PS-UI-015, PS-UI-016, PS-UI-029, PS-CMP-014, PS-CMP-015, PS-CMP-016, PS-CMP-017, PS-CMP-018, PS-CMP-019, PS-CMP-020, PS-CMP-021 | G55: =COUNTIF('Functional Testing'!$S:$S,"*"&$A55&"*")+COUNTIF('Math Validation'!$S:$S,"*"&$A55&"*")+COUNTIF('Feature Testing'!$S:$S,"*"&$A55&"*")+COUNTIF('Edge & Boundary Cases'!$S:$S,"*"&$A55&"*")+COUNTIF('UI-UX Testing'!$S:$S,"*"&$A55&"*")+COUNTIF('Compatibility Testing'!$S:$S,"*"&$A55&"*")+COUNTIF('Interruption & Recovery'!$S:$S,"*"&$A55&"*")+COUNTIF('STR - Transaction Testing'!$S:$S,"*"&$A55&"*")+COUNTIF('Error Handling'!$S:$S,"*"&$A55&"*") -> 29 | H55: =IF(G55=0,"NOT COVERED",IF(G55<2,"Partial","Covered")) -> Covered | I55: OBS-19
A56: GR-53 | B56: Game Rules | C56: Additional Info | D56: Malfunction voids all pays and plays | E56: Compliance | F56: PS-FUN-089, PS-ERR-020 | G56: =COUNTIF('Functional Testing'!$S:$S,"*"&$A56&"*")+COUNTIF('Math Validation'!$S:$S,"*"&$A56&"*")+COUNTIF('Feature Testing'!$S:$S,"*"&$A56&"*")+COUNTIF('Edge & Boundary Cases'!$S:$S,"*"&$A56&"*")+COUNTIF('UI-UX Testing'!$S:$S,"*"&$A56&"*")+COUNTIF('Compatibility Testing'!$S:$S,"*"&$A56&"*")+COUNTIF('Interruption & Recovery'!$S:$S,"*"&$A56&"*")+COUNTIF('STR - Transaction Testing'!$S:$S,"*"&$A56&"*")+COUNTIF('Error Handling'!$S:$S,"*"&$A56&"*") -> 2 | H56: =IF(G56=0,"NOT COVERED",IF(G56<2,"Partial","Covered")) -> Covered
A57: GR-54 | B57: Game Rules | C57: Additional Info | D57: Theoretical RTP disclosure | E57: Compliance | F57: PS-FUN-085, PS-MTH-001, PS-UI-036 | G57: =COUNTIF('Functional Testing'!$S:$S,"*"&$A57&"*")+COUNTIF('Math Validation'!$S:$S,"*"&$A57&"*")+COUNTIF('Feature Testing'!$S:$S,"*"&$A57&"*")+COUNTIF('Edge & Boundary Cases'!$S:$S,"*"&$A57&"*")+COUNTIF('UI-UX Testing'!$S:$S,"*"&$A57&"*")+COUNTIF('Compatibility Testing'!$S:$S,"*"&$A57&"*")+COUNTIF('Interruption & Recovery'!$S:$S,"*"&$A57&"*")+COUNTIF('STR - Transaction Testing'!$S:$S,"*"&$A57&"*")+COUNTIF('Error Handling'!$S:$S,"*"&$A57&"*") -> 3 | H57: =IF(G57=0,"NOT COVERED",IF(G57<2,"Partial","Covered")) -> Covered | I57: OBS-09
A58: GR-55 | B58: Game Rules | C58: Additional Info | D58: Buy Bonus RTP disclosure | E58: Compliance | F58: PS-FUN-085, PS-MTH-005, PS-MTH-006 | G58: =COUNTIF('Functional Testing'!$S:$S,"*"&$A58&"*")+COUNTIF('Math Validation'!$S:$S,"*"&$A58&"*")+COUNTIF('Feature Testing'!$S:$S,"*"&$A58&"*")+COUNTIF('Edge & Boundary Cases'!$S:$S,"*"&$A58&"*")+COUNTIF('UI-UX Testing'!$S:$S,"*"&$A58&"*")+COUNTIF('Compatibility Testing'!$S:$S,"*"&$A58&"*")+COUNTIF('Interruption & Recovery'!$S:$S,"*"&$A58&"*")+COUNTIF('STR - Transaction Testing'!$S:$S,"*"&$A58&"*")+COUNTIF('Error Handling'!$S:$S,"*"&$A58&"*") -> 3 | H58: =IF(G58=0,"NOT COVERED",IF(G58<2,"Partial","Covered")) -> Covered | I58: OBS-09, OBS-10
A59: GR-56 | B59: Game Rules | C59: Additional Info | D59: Interrupted game resumes from last recorded action | E59: Recovery | F59: PS-FUN-081, PS-FEA-010, PS-FEA-011, PS-FEA-022, PS-FEA-023, PS-FEA-044, PS-FEA-051, PS-FEA-054, PS-FEA-055, PS-FEA-058, PS-FEA-059, PS-EDG-028, PS-EDG-029, PS-EDG-030, PS-EDG-031, PS-EDG-033, PS-EDG-034, PS-EDG-035, PS-EDG-036, PS-INT-001, PS-INT-002, PS-INT-003, PS-INT-004, PS-INT-005, PS-INT-006, PS-INT-007, PS-INT-008, PS-INT-009, PS-INT-010, PS-INT-011, PS-INT-012, PS-INT-013, PS-INT-014, PS-INT-015, PS-INT-016, PS-INT-017, PS-INT-018, PS-INT-019, PS-INT-020, PS-INT-021, PS-INT-022, PS-INT-023, PS-INT-024, PS-INT-025, PS-INT-026, PS-INT-027, PS-INT-028, PS-INT-029, PS-INT-030, PS-ERR-003, PS-ERR-004, PS-ERR-005, PS-ERR-006, PS-ERR-007, PS-ERR-008, PS-ERR-009, PS-ERR-010, PS-ERR-011, PS-ERR-012, PS-ERR-013, PS-ERR-014, PS-ERR-015, PS-ERR-016, PS-ERR-017, PS-ERR-018 | G59: =COUNTIF('Functional Testing'!$S:$S,"*"&$A59&"*")+COUNTIF('Math Validation'!$S:$S,"*"&$A59&"*")+COUNTIF('Feature Testing'!$S:$S,"*"&$A59&"*")+COUNTIF('Edge & Boundary Cases'!$S:$S,"*"&$A59&"*")+COUNTIF('UI-UX Testing'!$S:$S,"*"&$A59&"*")+COUNTIF('Compatibility Testing'!$S:$S,"*"&$A59&"*")+COUNTIF('Interruption & Recovery'!$S:$S,"*"&$A59&"*")+COUNTIF('STR - Transaction Testing'!$S:$S,"*"&$A59&"*")+COUNTIF('Error Handling'!$S:$S,"*"&$A59&"*") -> 65 | H59: =IF(G59=0,"NOT COVERED",IF(G59<2,"Partial","Covered")) -> Covered
A60: GR-57 | B60: Game Rules | C60: Additional Info | D60: Persistent data retained up to 90 days | E60: Recovery | F60: PS-EDG-042 | G60: =COUNTIF('Functional Testing'!$S:$S,"*"&$A60&"*")+COUNTIF('Math Validation'!$S:$S,"*"&$A60&"*")+COUNTIF('Feature Testing'!$S:$S,"*"&$A60&"*")+COUNTIF('Edge & Boundary Cases'!$S:$S,"*"&$A60&"*")+COUNTIF('UI-UX Testing'!$S:$S,"*"&$A60&"*")+COUNTIF('Compatibility Testing'!$S:$S,"*"&$A60&"*")+COUNTIF('Interruption & Recovery'!$S:$S,"*"&$A60&"*")+COUNTIF('STR - Transaction Testing'!$S:$S,"*"&$A60&"*")+COUNTIF('Error Handling'!$S:$S,"*"&$A60&"*") -> 1 | H60: =IF(G60=0,"NOT COVERED",IF(G60<2,"Partial","Covered")) -> Partial
A61: GR-58 | B61: Game Rules | C61: Additional Info | D61: 7-day inactivity may reset game and forfeit unfinished features | E61: Recovery | F61: PS-FEA-056, PS-FEA-057, PS-INT-022 | G61: =COUNTIF('Functional Testing'!$S:$S,"*"&$A61&"*")+COUNTIF('Math Validation'!$S:$S,"*"&$A61&"*")+COUNTIF('Feature Testing'!$S:$S,"*"&$A61&"*")+COUNTIF('Edge & Boundary Cases'!$S:$S,"*"&$A61&"*")+COUNTIF('UI-UX Testing'!$S:$S,"*"&$A61&"*")+COUNTIF('Compatibility Testing'!$S:$S,"*"&$A61&"*")+COUNTIF('Interruption & Recovery'!$S:$S,"*"&$A61&"*")+COUNTIF('STR - Transaction Testing'!$S:$S,"*"&$A61&"*")+COUNTIF('Error Handling'!$S:$S,"*"&$A61&"*") -> 3 | H61: =IF(G61=0,"NOT COVERED",IF(G61<2,"Partial","Covered")) -> Covered | I61: OBS-23
A62: GR-59 | B62: Game Rules | C62: Additional Info | D62: Pay table ID: Pig Style | E62: Compliance | F62: PS-FUN-037, PS-FUN-090 | G62: =COUNTIF('Functional Testing'!$S:$S,"*"&$A62&"*")+COUNTIF('Math Validation'!$S:$S,"*"&$A62&"*")+COUNTIF('Feature Testing'!$S:$S,"*"&$A62&"*")+COUNTIF('Edge & Boundary Cases'!$S:$S,"*"&$A62&"*")+COUNTIF('UI-UX Testing'!$S:$S,"*"&$A62&"*")+COUNTIF('Compatibility Testing'!$S:$S,"*"&$A62&"*")+COUNTIF('Interruption & Recovery'!$S:$S,"*"&$A62&"*")+COUNTIF('STR - Transaction Testing'!$S:$S,"*"&$A62&"*")+COUNTIF('Error Handling'!$S:$S,"*"&$A62&"*") -> 2 | H62: =IF(G62=0,"NOT COVERED",IF(G62<2,"Partial","Covered")) -> Covered | I62: OBS-13
A63: M-01 | B63: Math File | C63: Summary C4:C6, K6 | D63: RTP: base 68.924%, FS 28.065%, total 96.989% | E63: RTP | F63: PS-FUN-085, PS-MTH-001, PS-MTH-002, PS-MTH-003, PS-MTH-004, PS-MTH-007 | G63: =COUNTIF('Functional Testing'!$S:$S,"*"&$A63&"*")+COUNTIF('Math Validation'!$S:$S,"*"&$A63&"*")+COUNTIF('Feature Testing'!$S:$S,"*"&$A63&"*")+COUNTIF('Edge & Boundary Cases'!$S:$S,"*"&$A63&"*")+COUNTIF('UI-UX Testing'!$S:$S,"*"&$A63&"*")+COUNTIF('Compatibility Testing'!$S:$S,"*"&$A63&"*")+COUNTIF('Interruption & Recovery'!$S:$S,"*"&$A63&"*")+COUNTIF('STR - Transaction Testing'!$S:$S,"*"&$A63&"*")+COUNTIF('Error Handling'!$S:$S,"*"&$A63&"*") -> 6 | H63: =IF(G63=0,"NOT COVERED",IF(G63<2,"Partial","Covered")) -> Covered | I63: OBS-14
A64: M-02 | B64: Math File | C64: Summary C9 | D64: Hit frequency 31.6018% | E64: Hit Frequency | F64: PS-MTH-008 | G64: =COUNTIF('Functional Testing'!$S:$S,"*"&$A64&"*")+COUNTIF('Math Validation'!$S:$S,"*"&$A64&"*")+COUNTIF('Feature Testing'!$S:$S,"*"&$A64&"*")+COUNTIF('Edge & Boundary Cases'!$S:$S,"*"&$A64&"*")+COUNTIF('UI-UX Testing'!$S:$S,"*"&$A64&"*")+COUNTIF('Compatibility Testing'!$S:$S,"*"&$A64&"*")+COUNTIF('Interruption & Recovery'!$S:$S,"*"&$A64&"*")+COUNTIF('STR - Transaction Testing'!$S:$S,"*"&$A64&"*")+COUNTIF('Error Handling'!$S:$S,"*"&$A64&"*") -> 1 | H64: =IF(G64=0,"NOT COVERED",IF(G64<2,"Partial","Covered")) -> Partial
A65: M-03 | B65: Math File | C65: Summary C12, K55:K57 | D65: SD 16.80; VI 90/95/99% = 27.64/32.93/43.28 | E65: Volatility | F65: PS-MTH-001, PS-MTH-010 | G65: =COUNTIF('Functional Testing'!$S:$S,"*"&$A65&"*")+COUNTIF('Math Validation'!$S:$S,"*"&$A65&"*")+COUNTIF('Feature Testing'!$S:$S,"*"&$A65&"*")+COUNTIF('Edge & Boundary Cases'!$S:$S,"*"&$A65&"*")+COUNTIF('UI-UX Testing'!$S:$S,"*"&$A65&"*")+COUNTIF('Compatibility Testing'!$S:$S,"*"&$A65&"*")+COUNTIF('Interruption & Recovery'!$S:$S,"*"&$A65&"*")+COUNTIF('STR - Transaction Testing'!$S:$S,"*"&$A65&"*")+COUNTIF('Error Handling'!$S:$S,"*"&$A65&"*") -> 2 | H65: =IF(G65=0,"NOT COVERED",IF(G65<2,"Partial","Covered")) -> Covered
A66: M-04 | B66: Math File | C66: Summary C10:G11 | D66: Max exposure 1,009,091 cr at bet 20 (50,454.55x), 1 in 1e9 | E66: Max Win | F66: PS-FUN-086, PS-MTH-053 | G66: =COUNTIF('Functional Testing'!$S:$S,"*"&$A66&"*")+COUNTIF('Math Validation'!$S:$S,"*"&$A66&"*")+COUNTIF('Feature Testing'!$S:$S,"*"&$A66&"*")+COUNTIF('Edge & Boundary Cases'!$S:$S,"*"&$A66&"*")+COUNTIF('UI-UX Testing'!$S:$S,"*"&$A66&"*")+COUNTIF('Compatibility Testing'!$S:$S,"*"&$A66&"*")+COUNTIF('Interruption & Recovery'!$S:$S,"*"&$A66&"*")+COUNTIF('STR - Transaction Testing'!$S:$S,"*"&$A66&"*")+COUNTIF('Error Handling'!$S:$S,"*"&$A66&"*") -> 2 | H66: =IF(G66=0,"NOT COVERED",IF(G66<2,"Partial","Covered")) -> Covered | I66: OBS-12
A67: M-05 | B67: Math File | C67: BG Calc R3:V14 | D67: Paytable (credits at bet 20) for AA..LL, 3-6 OAK | E67: Paytable | F67: PS-FUN-021, PS-FUN-023, PS-FUN-024, PS-FUN-025, PS-FUN-026, PS-FUN-027, PS-FUN-028, PS-FUN-029, PS-FUN-030, PS-FUN-031, PS-FUN-032, PS-FUN-033, PS-FUN-040, PS-FUN-041, PS-FUN-042, PS-FUN-043, PS-FUN-044, PS-MTH-017, PS-MTH-018, PS-MTH-019, PS-MTH-020, PS-MTH-021, PS-MTH-022, PS-MTH-023, PS-MTH-024, PS-MTH-025, PS-EDG-014 | G67: =COUNTIF('Functional Testing'!$S:$S,"*"&$A67&"*")+COUNTIF('Math Validation'!$S:$S,"*"&$A67&"*")+COUNTIF('Feature Testing'!$S:$S,"*"&$A67&"*")+COUNTIF('Edge & Boundary Cases'!$S:$S,"*"&$A67&"*")+COUNTIF('UI-UX Testing'!$S:$S,"*"&$A67&"*")+COUNTIF('Compatibility Testing'!$S:$S,"*"&$A67&"*")+COUNTIF('Interruption & Recovery'!$S:$S,"*"&$A67&"*")+COUNTIF('STR - Transaction Testing'!$S:$S,"*"&$A67&"*")+COUNTIF('Error Handling'!$S:$S,"*"&$A67&"*") -> 27 | H67: =IF(G67=0,"NOT COVERED",IF(G67<2,"Partial","Covered")) -> Covered | I67: OBS-03, OBS-15
A68: M-06 | B68: Math File | C68: BG Calc AJ19:AL25 | D68: Reel height 2..7 weights Opt0/Opt1 and pattern table | E68: Reels / Ways | F68: PS-FUN-005, PS-FUN-006, PS-FUN-007, PS-FUN-008, PS-MTH-014, PS-MTH-015, PS-MTH-016 | G68: =COUNTIF('Functional Testing'!$S:$S,"*"&$A68&"*")+COUNTIF('Math Validation'!$S:$S,"*"&$A68&"*")+COUNTIF('Feature Testing'!$S:$S,"*"&$A68&"*")+COUNTIF('Edge & Boundary Cases'!$S:$S,"*"&$A68&"*")+COUNTIF('UI-UX Testing'!$S:$S,"*"&$A68&"*")+COUNTIF('Compatibility Testing'!$S:$S,"*"&$A68&"*")+COUNTIF('Interruption & Recovery'!$S:$S,"*"&$A68&"*")+COUNTIF('STR - Transaction Testing'!$S:$S,"*"&$A68&"*")+COUNTIF('Error Handling'!$S:$S,"*"&$A68&"*") -> 7 | H68: =IF(G68=0,"NOT COVERED",IF(G68<2,"Partial","Covered")) -> Covered
A69: M-07 | B69: Math File | C69: BG Calc C3:H3, Z3:AA5 | D69: Base Wild on reels 2-5; multiplier x1/x2/x3 weights 10/5/2 | E69: Wild | F69: PS-FUN-045, PS-FUN-046, PS-FUN-048, PS-FUN-049, PS-MTH-027, PS-MTH-028, PS-MTH-029, PS-MTH-030, PS-MTH-031, PS-MTH-032 | G69: =COUNTIF('Functional Testing'!$S:$S,"*"&$A69&"*")+COUNTIF('Math Validation'!$S:$S,"*"&$A69&"*")+COUNTIF('Feature Testing'!$S:$S,"*"&$A69&"*")+COUNTIF('Edge & Boundary Cases'!$S:$S,"*"&$A69&"*")+COUNTIF('UI-UX Testing'!$S:$S,"*"&$A69&"*")+COUNTIF('Compatibility Testing'!$S:$S,"*"&$A69&"*")+COUNTIF('Interruption & Recovery'!$S:$S,"*"&$A69&"*")+COUNTIF('STR - Transaction Testing'!$S:$S,"*"&$A69&"*")+COUNTIF('Error Handling'!$S:$S,"*"&$A69&"*") -> 10 | H69: =IF(G69=0,"NOT COVERED",IF(G69<2,"Partial","Covered")) -> Covered | I69: OBS-02
A70: M-08 | B70: Math File | C70: BG Calc row 15; FG Calc row 15 | D70: Bonus on reels 1-6 in base; absent in FS strips; pays 0 | E70: Bonus | F70: PS-FUN-047, PS-FUN-052, PS-FUN-053, PS-MTH-047, PS-MTH-062, PS-FEA-006, PS-FEA-018 | G70: =COUNTIF('Functional Testing'!$S:$S,"*"&$A70&"*")+COUNTIF('Math Validation'!$S:$S,"*"&$A70&"*")+COUNTIF('Feature Testing'!$S:$S,"*"&$A70&"*")+COUNTIF('Edge & Boundary Cases'!$S:$S,"*"&$A70&"*")+COUNTIF('UI-UX Testing'!$S:$S,"*"&$A70&"*")+COUNTIF('Compatibility Testing'!$S:$S,"*"&$A70&"*")+COUNTIF('Interruption & Recovery'!$S:$S,"*"&$A70&"*")+COUNTIF('STR - Transaction Testing'!$S:$S,"*"&$A70&"*")+COUNTIF('Error Handling'!$S:$S,"*"&$A70&"*") -> 7 | H70: =IF(G70=0,"NOT COVERED",IF(G70<2,"Partial","Covered")) -> Covered | I70: OBS-16
A71: M-09 | B71: Math File | C71: BG Calc AE3:AF11 | D71: Base reel sets BG1..BG9 weights 23/50/60/2000/475/33/50/50/1000 | E71: Reel Sets | F71: PS-MTH-012, PS-MTH-013, PS-MTH-014 | G71: =COUNTIF('Functional Testing'!$S:$S,"*"&$A71&"*")+COUNTIF('Math Validation'!$S:$S,"*"&$A71&"*")+COUNTIF('Feature Testing'!$S:$S,"*"&$A71&"*")+COUNTIF('Edge & Boundary Cases'!$S:$S,"*"&$A71&"*")+COUNTIF('UI-UX Testing'!$S:$S,"*"&$A71&"*")+COUNTIF('Compatibility Testing'!$S:$S,"*"&$A71&"*")+COUNTIF('Interruption & Recovery'!$S:$S,"*"&$A71&"*")+COUNTIF('STR - Transaction Testing'!$S:$S,"*"&$A71&"*")+COUNTIF('Error Handling'!$S:$S,"*"&$A71&"*") -> 3 | H71: =IF(G71=0,"NOT COVERED",IF(G71<2,"Partial","Covered")) -> Covered
A72: M-10 | B72: Math File | C72: Summary K42:K51 | D72: FS trigger 1 in 268.89 (BG1 57.10, BG6 2.44) | E72: Free Spins Trigger | F72: PS-MTH-011, PS-MTH-012 | G72: =COUNTIF('Functional Testing'!$S:$S,"*"&$A72&"*")+COUNTIF('Math Validation'!$S:$S,"*"&$A72&"*")+COUNTIF('Feature Testing'!$S:$S,"*"&$A72&"*")+COUNTIF('Edge & Boundary Cases'!$S:$S,"*"&$A72&"*")+COUNTIF('UI-UX Testing'!$S:$S,"*"&$A72&"*")+COUNTIF('Compatibility Testing'!$S:$S,"*"&$A72&"*")+COUNTIF('Interruption & Recovery'!$S:$S,"*"&$A72&"*")+COUNTIF('STR - Transaction Testing'!$S:$S,"*"&$A72&"*")+COUNTIF('Error Handling'!$S:$S,"*"&$A72&"*") -> 2 | H72: =IF(G72=0,"NOT COVERED",IF(G72<2,"Partial","Covered")) -> Covered
A73: M-11 | B73: Math File | C73: FG1 Calc | D73: FG1 (Raining): FS 15/18/25/30; wild count 0..6; mult x1/x2/x3 1000/500/189; reels 2-5 | E73: Raining Wilds FS | F73: PS-MTH-033, PS-MTH-036, PS-MTH-042, PS-MTH-043, PS-MTH-044, PS-MTH-045, PS-MTH-048, PS-MTH-049, PS-MTH-063, PS-FEA-013, PS-FEA-014, PS-FEA-035, PS-FEA-037, PS-FEA-039 | G73: =COUNTIF('Functional Testing'!$S:$S,"*"&$A73&"*")+COUNTIF('Math Validation'!$S:$S,"*"&$A73&"*")+COUNTIF('Feature Testing'!$S:$S,"*"&$A73&"*")+COUNTIF('Edge & Boundary Cases'!$S:$S,"*"&$A73&"*")+COUNTIF('UI-UX Testing'!$S:$S,"*"&$A73&"*")+COUNTIF('Compatibility Testing'!$S:$S,"*"&$A73&"*")+COUNTIF('Interruption & Recovery'!$S:$S,"*"&$A73&"*")+COUNTIF('STR - Transaction Testing'!$S:$S,"*"&$A73&"*")+COUNTIF('Error Handling'!$S:$S,"*"&$A73&"*") -> 14 | H73: =IF(G73=0,"NOT COVERED",IF(G73<2,"Partial","Covered")) -> Covered | I73: OBS-01, OBS-05
A74: M-12 | B74: Math File | C74: FG2 Calc | D74: FG2 (Sticky): FS 7/12/15/20; new wilds 0..3; mult 8/2/1; size tables; reels 2-5 | E74: Sticky Wilds FS | F74: PS-MTH-034, PS-MTH-036, PS-MTH-038, PS-MTH-039, PS-MTH-040, PS-MTH-041, PS-MTH-050, PS-MTH-051, PS-MTH-052, PS-MTH-063, PS-FEA-001, PS-FEA-002, PS-FEA-025, PS-FEA-027, PS-FEA-028, PS-FEA-031, PS-FEA-032 | G74: =COUNTIF('Functional Testing'!$S:$S,"*"&$A74&"*")+COUNTIF('Math Validation'!$S:$S,"*"&$A74&"*")+COUNTIF('Feature Testing'!$S:$S,"*"&$A74&"*")+COUNTIF('Edge & Boundary Cases'!$S:$S,"*"&$A74&"*")+COUNTIF('UI-UX Testing'!$S:$S,"*"&$A74&"*")+COUNTIF('Compatibility Testing'!$S:$S,"*"&$A74&"*")+COUNTIF('Interruption & Recovery'!$S:$S,"*"&$A74&"*")+COUNTIF('STR - Transaction Testing'!$S:$S,"*"&$A74&"*")+COUNTIF('Error Handling'!$S:$S,"*"&$A74&"*") -> 17 | H74: =IF(G74=0,"NOT COVERED",IF(G74<2,"Partial","Covered")) -> Covered | I74: OBS-01, OBS-06
A75: M-13 | B75: Math File | C75: StickyWildMovement | D75: Sticky Wild position/row transition table | E75: Sticky Wilds FS | F75: PS-MTH-051, PS-FEA-025, PS-FEA-029, PS-FEA-030, PS-FEA-033 | G75: =COUNTIF('Functional Testing'!$S:$S,"*"&$A75&"*")+COUNTIF('Math Validation'!$S:$S,"*"&$A75&"*")+COUNTIF('Feature Testing'!$S:$S,"*"&$A75&"*")+COUNTIF('Edge & Boundary Cases'!$S:$S,"*"&$A75&"*")+COUNTIF('UI-UX Testing'!$S:$S,"*"&$A75&"*")+COUNTIF('Compatibility Testing'!$S:$S,"*"&$A75&"*")+COUNTIF('Interruption & Recovery'!$S:$S,"*"&$A75&"*")+COUNTIF('STR - Transaction Testing'!$S:$S,"*"&$A75&"*")+COUNTIF('Error Handling'!$S:$S,"*"&$A75&"*") -> 5 | H75: =IF(G75=0,"NOT COVERED",IF(G75<2,"Partial","Covered")) -> Covered | I75: OBS-07
A76: M-14 | B76: Math File | C76: Summary C16:D16 | D76: Buy cost 100x total bet for FG1 and FG2 | E76: Buy Feature | F76: PS-FUN-057, PS-FUN-058 | G76: =COUNTIF('Functional Testing'!$S:$S,"*"&$A76&"*")+COUNTIF('Math Validation'!$S:$S,"*"&$A76&"*")+COUNTIF('Feature Testing'!$S:$S,"*"&$A76&"*")+COUNTIF('Edge & Boundary Cases'!$S:$S,"*"&$A76&"*")+COUNTIF('UI-UX Testing'!$S:$S,"*"&$A76&"*")+COUNTIF('Compatibility Testing'!$S:$S,"*"&$A76&"*")+COUNTIF('Interruption & Recovery'!$S:$S,"*"&$A76&"*")+COUNTIF('STR - Transaction Testing'!$S:$S,"*"&$A76&"*")+COUNTIF('Error Handling'!$S:$S,"*"&$A76&"*") -> 2 | H76: =IF(G76=0,"NOT COVERED",IF(G76<2,"Partial","Covered")) -> Covered
A77: M-15 | B77: Math File | C77: Summary C17:C21, N6:N40 | D77: Buy FG1 RTP 97.084%, HF 99.997%, SD 1.618, max 487,402 cr | E77: Buy Feature | F77: PS-FUN-085, PS-MTH-005, PS-MTH-007, PS-MTH-009, PS-MTH-054, PS-MTH-059, PS-MTH-060, PS-FEA-048, PS-FEA-049 | G77: =COUNTIF('Functional Testing'!$S:$S,"*"&$A77&"*")+COUNTIF('Math Validation'!$S:$S,"*"&$A77&"*")+COUNTIF('Feature Testing'!$S:$S,"*"&$A77&"*")+COUNTIF('Edge & Boundary Cases'!$S:$S,"*"&$A77&"*")+COUNTIF('UI-UX Testing'!$S:$S,"*"&$A77&"*")+COUNTIF('Compatibility Testing'!$S:$S,"*"&$A77&"*")+COUNTIF('Interruption & Recovery'!$S:$S,"*"&$A77&"*")+COUNTIF('STR - Transaction Testing'!$S:$S,"*"&$A77&"*")+COUNTIF('Error Handling'!$S:$S,"*"&$A77&"*") -> 9 | H77: =IF(G77=0,"NOT COVERED",IF(G77<2,"Partial","Covered")) -> Covered | I77: OBS-10
A78: M-16 | B78: Math File | C78: Summary D17:D21, Q6:Q40 | D78: Buy FG2 RTP 97.110%, HF 97.420%, SD 3.711, max 1,674,912 cr | E78: Buy Feature | F78: PS-FUN-085, PS-MTH-006, PS-MTH-007, PS-MTH-009, PS-MTH-054, PS-MTH-059, PS-MTH-060, PS-FEA-048, PS-FEA-049 | G78: =COUNTIF('Functional Testing'!$S:$S,"*"&$A78&"*")+COUNTIF('Math Validation'!$S:$S,"*"&$A78&"*")+COUNTIF('Feature Testing'!$S:$S,"*"&$A78&"*")+COUNTIF('Edge & Boundary Cases'!$S:$S,"*"&$A78&"*")+COUNTIF('UI-UX Testing'!$S:$S,"*"&$A78&"*")+COUNTIF('Compatibility Testing'!$S:$S,"*"&$A78&"*")+COUNTIF('Interruption & Recovery'!$S:$S,"*"&$A78&"*")+COUNTIF('STR - Transaction Testing'!$S:$S,"*"&$A78&"*")+COUNTIF('Error Handling'!$S:$S,"*"&$A78&"*") -> 9 | H78: =IF(G78=0,"NOT COVERED",IF(G78<2,"Partial","Covered")) -> Covered | I78: OBS-10, OBS-12
A79: M-17 | B79: Math File | C79: Buy FG1/FG2 Calc | D79: Buy mode weights differ from natural FS (wild count, multipliers) | E79: Buy Feature | F79: PS-MTH-035, PS-MTH-048, PS-MTH-050 | G79: =COUNTIF('Functional Testing'!$S:$S,"*"&$A79&"*")+COUNTIF('Math Validation'!$S:$S,"*"&$A79&"*")+COUNTIF('Feature Testing'!$S:$S,"*"&$A79&"*")+COUNTIF('Edge & Boundary Cases'!$S:$S,"*"&$A79&"*")+COUNTIF('UI-UX Testing'!$S:$S,"*"&$A79&"*")+COUNTIF('Compatibility Testing'!$S:$S,"*"&$A79&"*")+COUNTIF('Interruption & Recovery'!$S:$S,"*"&$A79&"*")+COUNTIF('STR - Transaction Testing'!$S:$S,"*"&$A79&"*")+COUNTIF('Error Handling'!$S:$S,"*"&$A79&"*") -> 3 | H79: =IF(G79=0,"NOT COVERED",IF(G79<2,"Partial","Covered")) -> Covered | I79: OBS-11
A80: M-18 | B80: Math File | C80: Summary K52:Q53 | D80: Average FS: 12.372 / 16.158 / 8.590; avg stickies at end | E80: FS Award | F80: PS-MTH-003, PS-MTH-046 | G80: =COUNTIF('Functional Testing'!$S:$S,"*"&$A80&"*")+COUNTIF('Math Validation'!$S:$S,"*"&$A80&"*")+COUNTIF('Feature Testing'!$S:$S,"*"&$A80&"*")+COUNTIF('Edge & Boundary Cases'!$S:$S,"*"&$A80&"*")+COUNTIF('UI-UX Testing'!$S:$S,"*"&$A80&"*")+COUNTIF('Compatibility Testing'!$S:$S,"*"&$A80&"*")+COUNTIF('Interruption & Recovery'!$S:$S,"*"&$A80&"*")+COUNTIF('STR - Transaction Testing'!$S:$S,"*"&$A80&"*")+COUNTIF('Error Handling'!$S:$S,"*"&$A80&"*") -> 2 | H80: =IF(G80=0,"NOT COVERED",IF(G80<2,"Partial","Covered")) -> Covered
A81: M-19 | B81: Math File | C81: Summary K4:K5, BG Calc K19 | D81: Bet = 20 credits (Lines Played 20); pay denominator 20 | E81: Bet | F81: PS-FUN-021, PS-FUN-023, PS-FUN-024, PS-FUN-025, PS-FUN-026, PS-FUN-027, PS-FUN-028, PS-FUN-029, PS-FUN-030, PS-FUN-031, PS-FUN-032, PS-FUN-033, PS-FUN-034, PS-MTH-017, PS-MTH-018, PS-MTH-019, PS-MTH-020, PS-MTH-021, PS-MTH-022, PS-MTH-023, PS-MTH-024, PS-MTH-025, PS-MTH-026, PS-MTH-057 | G81: =COUNTIF('Functional Testing'!$S:$S,"*"&$A81&"*")+COUNTIF('Math Validation'!$S:$S,"*"&$A81&"*")+COUNTIF('Feature Testing'!$S:$S,"*"&$A81&"*")+COUNTIF('Edge & Boundary Cases'!$S:$S,"*"&$A81&"*")+COUNTIF('UI-UX Testing'!$S:$S,"*"&$A81&"*")+COUNTIF('Compatibility Testing'!$S:$S,"*"&$A81&"*")+COUNTIF('Interruption & Recovery'!$S:$S,"*"&$A81&"*")+COUNTIF('STR - Transaction Testing'!$S:$S,"*"&$A81&"*")+COUNTIF('Error Handling'!$S:$S,"*"&$A81&"*") -> 24 | H81: =IF(G81=0,"NOT COVERED",IF(G81<2,"Partial","Covered")) -> Covered
A82: M-20 | B82: Math File | C82: Summary K2, B5 | D82: Metadata: Game Name 'DogHouseMegaways9700', 'Wheel Bonus' label | E82: Math File | F82: PS-FUN-090, PS-MTH-061 | G82: =COUNTIF('Functional Testing'!$S:$S,"*"&$A82&"*")+COUNTIF('Math Validation'!$S:$S,"*"&$A82&"*")+COUNTIF('Feature Testing'!$S:$S,"*"&$A82&"*")+COUNTIF('Edge & Boundary Cases'!$S:$S,"*"&$A82&"*")+COUNTIF('UI-UX Testing'!$S:$S,"*"&$A82&"*")+COUNTIF('Compatibility Testing'!$S:$S,"*"&$A82&"*")+COUNTIF('Interruption & Recovery'!$S:$S,"*"&$A82&"*")+COUNTIF('STR - Transaction Testing'!$S:$S,"*"&$A82&"*")+COUNTIF('Error Handling'!$S:$S,"*"&$A82&"*") -> 2 | H82: =IF(G82=0,"NOT COVERED",IF(G82<2,"Partial","Covered")) -> Covered | I82: OBS-13
A84: Gap Analysis
A85: Requirements without coverage | D85: =COUNTIF(H4:H82,"NOT COVERED") -> 0 | E85: Filter column H = NOT COVERED
A86: Requirements with single test case | D86: =COUNTIF(H4:H82,"Partial") -> 9 | E86: Review for additional negative/boundary cases
A87: Math rules without validation | D87: =COUNTIFS(B4:B82,"Math File",H4:H82,"NOT COVERED") -> 0 | E87: Math rows M-xx with no linked case
A88: Game Rules vs Math conflicts | D88: =COUNTIF('Defect-Observation Log'!B:B,"Spec Conflict") -> 6 | E88: See Defect-Observation Log (Type = Spec Conflict)
A89: Missing / ambiguous specification | D89: =COUNTIF('Defect-Observation Log'!B:B,"Missing Spec")+COUNTIF('Defect-Observation Log'!B:B,"Ambiguity") -> 14 | E89: See Defect-Observation Log
A90: Test cases depending on spec confirmation | D90: =COUNTIF('Functional Testing'!I:I,"Requires Specification*")+COUNTIF('Math Validation'!I:I,"Requires Specification*")+COUNTIF('Feature Testing'!I:I,"Requires Specification*")+COUNTIF('Edge & Boundary Cases'!I:I,"Requires Specification*")+COUNTIF('UI-UX Testing'!I:I,"Requires Specification*")+COUNTIF('Compatibility Testing'!I:I,"Requires Specification*")+COUNTIF('Interruption & Recovery'!I:I,"Requires Specification*")+COUNTIF('STR - Transaction Testing'!I:I,"Requires Specification*")+COUNTIF('Error Handling'!I:I,"Requires Specification*") -> 40 | E90: Expected Result starts with 'Requires Specification/Confirmation'
A92: Test cases without a direct Game Rules / Math requirement (industry or platform practice: browser/device, performance, RG/operator, security)
A93: None: every test case carries at least one Ref

Sheet Defect-Observation Log
A1: ID | B1: Type | C1: Area | D1: Description | E1: Game Rules Reference | F1: Math File Reference | G1: Impact | H1: Severity | I1: Priority | J1: Linked Requirements | K1: Linked Test Cases | L1: Recommendation | M1: Status | N1: Owner | O1: Date Raised | P1: Resolution / Comments
A2: OBS-01 | B2: Spec Conflict | C2: Wild Multiplier | D2: Rules state Sticky and Raining Wilds carry x2 or x3 only. Math FG1 weights x1:1000/x2:500/x3:189 and FG2 x1:8/x2:2/x3:1 (Buy FG2 875/200/100) include x1, which is the most likely value. | E2: Sticky/Raining sections: 'random multiplier of x2 or x3' | F2: FG1 Calc Z3:AA5; FG2 Calc Z3:AA5; Buy FG2 Calc Z3:AA5 | G2: Misleading player information; certification failure; RTP described incorrectly | H2: Critical | I2: P0 | J2: GR-07, GR-11, M-11, M-12 | K2: PS-MTH-031, PS-MTH-033, PS-MTH-034, PS-MTH-035, PS-FEA-027, PS-FEA-037 | L2: Update rules to 'x1, x2 or x3' (or remove x1 from math and re-certify). | M2: Open | N2: Game Design / Math Provider | O2: 23 Oct 2026
A3: OBS-02 | B3: Missing Spec | C3: Wild (Base Game) | D3: Math defines Wild (WC) in base game on reels 2-5 with x1/x2/x3 multiplier (weights 10/5/2). Rules do not describe the Wild symbol, what it substitutes for (incl. Bonus), its reels or base game multipliers. | E3: No Wild section in rules | F3: BG Calc C3:H3, Z3:AA5 | G3: Undocumented feature; wins not explainable to player | H3: Critical | I3: P0 | J3: M-07 | K3: PS-FUN-045, PS-FUN-046, PS-FUN-047, PS-FUN-048, PS-FUN-049, PS-MTH-027, PS-MTH-028, PS-MTH-029, PS-MTH-030, PS-MTH-031, PS-MTH-032 | L3: Add Wild section: substitutes for all paying symbols except Bonus, reels 2-5, carries x1/x2/x3 in base game. | M3: Open | N3: Game Design / Math Provider | O3: 23 Oct 2026
A4: OBS-03 | B4: Spec Conflict | C4: Win Evaluation | D4: Rules: '2 or more high-value or 3 or more low-value matching symbols'. Math paytable starts at 3 OAK for all symbols (no 2 OAK pays). High/low value classes not defined. | E4: WIN section bullet 1 | F4: BG Calc R3:V14 (cols 6,5,4,3 only) | G4: Player expects wins that never pay | H4: High | I4: P0 | J4: GR-23, M-05 | K4: PS-FUN-023, PS-FUN-024, PS-FUN-025, PS-FUN-026, PS-FUN-027, PS-FUN-028, PS-FUN-029, PS-FUN-030, PS-FUN-031, PS-FUN-032, PS-FUN-033, PS-FUN-041 | L4: Change to '3 or more matching symbols'. | M4: Open | N4: Game Design / Math Provider | O4: 23 Oct 2026
A5: OBS-04 | B5: Spec Conflict | C5: Win Evaluation | D5: Rules use payline terminology ('active payline', 'Only the highest win on each active payline is paid') for a Megaways ways game. Rules do not explain that wins are multiplied by the number of ways (product of symbol counts per reel). | E5: WIN section | F5: BG Calc hits = product of per-reel counts | G5: Ambiguous win evaluation; cert query | H5: High | I5: P1 | J5: GR-26, GR-01 | K5: PS-FUN-037, PS-FUN-040, PS-MTH-037 | L5: Replace payline wording with ways wording; add ways calculation and 'highest win per symbol per way'. | M5: Open | N5: Game Design / Math Provider | O5: 23 Oct 2026
A6: OBS-05 | B6: Spec Conflict | C6: Raining Wilds | D6: Rules: 'up to 6 Wild symbols of any size in random positions on the reels'. Math: Raining Wilds placed only on reels 2-5; FG1 math contains no wild size definition. | E6: Raining Wilds bullet 2 | F6: FG1 Calc AL3:AM8 'Only Reel 2,3,4,5' | G6: Misleading description | H6: High | I6: P1 | J6: GR-10, M-11 | K6: PS-MTH-049, PS-FEA-038, PS-FEA-039 | L6: State reels 2-5; clarify or remove 'any size'. | M6: Open | N6: Game Design / Math Provider | O6: 23 Oct 2026
A7: OBS-06 | B7: Ambiguity | C7: Sticky Wilds | D7: Rules: 'up to 7 Sticky Wild symbols can land on each reel'. Math: 0..3 new wilds per spin (weights 500/126/50/10), reels 2-5 only; per-reel accumulation tables up to 6 stickies. | E7: Sticky bullet 1 | F7: FG2 Calc AI3:AJ6, Z18:AM25 | G7: Player may expect more wilds per spin | H7: Medium | I7: P1 | J7: GR-06, M-12 | K7: PS-MTH-050, PS-FEA-028, PS-FEA-032 | L7: Reword: up to 3 Sticky Wilds per spin on reels 2-5; accumulate up to reel height. | M7: Open | N7: Game Design / Math Provider | O7: 23 Oct 2026
A8: OBS-07 | B8: Ambiguity | C8: Sticky Wilds | D8: Rules: stickies 'adjust in size as the reels expand'. Math StickyWildMovement includes transitions to fewer rows (e.g. 3 -> 2) with repositioning. | E8: Sticky bullet 4 | F8: StickyWildMovement A:S | G8: Undocumented behaviour on reel shrink | H8: Medium | I8: P1 | J8: GR-08, M-13 | K8: PS-MTH-051, PS-FEA-030 | L8: Describe behaviour when reel height decreases. | M8: Open | N8: Game Design / Math Provider | O8: 23 Oct 2026
A9: OBS-08 | B9: Ambiguity | C9: Free Spins | D9: 'All Free Spins winnings are awarded to the player when the feature ends' sits under Raining Wilds only; unclear if it applies to Sticky Wilds. | E9: Raining Wilds bullet 3 | F9: N/A | G9: Wallet integration and player expectation | H9: Medium | I9: P1 | J9: GR-12 | K9: PS-FEA-009, PS-FEA-021, PS-STR-005 | L9: Move bullet to general FREE SPINS section. | M9: Open | N9: Game Design / Math Provider | O9: 23 Oct 2026
A10: OBS-09 | B10: Missing Spec | C10: Bet / Max Win / RTP | D10: Placeholders {{text1}} for Min Bet, Max Bet, Max Win cap (x2) , RTP and Buy RTP. Rounding rule for sub-cent wins at low bets also undefined. | E10: BET AND MAX WIN; ADDITIONAL INFORMATION | F10: Summary C6, C18:D18, C10 | G10: Blocks certification and many test cases | H10: Critical | I10: P0 | J10: GR-28, GR-29, GR-54, GR-55 | K10: PS-FUN-016, PS-FUN-037, PS-FUN-085, PS-FUN-086, PS-MTH-026, PS-MTH-053, PS-MTH-055, PS-MTH-056, PS-MTH-058, PS-FEA-012, PS-FEA-024, PS-EDG-001, PS-EDG-002, PS-EDG-007, PS-EDG-010, PS-EDG-011, PS-EDG-012, PS-UI-028, PS-UI-036, PS-STR-023, PS-ERR-019 | L10: Populate values per jurisdiction config before submission. | M10: Open | N10: Game Design / Math Provider | O10: 23 Oct 2026
A11: OBS-10 | B11: Spec Conflict | C11: Buy Feature | D11: Math has two Buy configurations (Buy FG1 RTP 97.084%, Buy FG2 RTP 97.110%). Rules give one Buy RTP and do not say whether the FS type is chosen in the Buy interface or after the trigger. | E11: BUY FREE SPINS; ADDITIONAL INFORMATION | F11: Summary M1:Q21 | G11: Incorrect RTP disclosure | H11: High | I11: P0 | J11: GR-32, GR-55, M-15, M-16 | K11: PS-FUN-057, PS-FUN-085, PS-FEA-048 | L11: Disclose both RTPs (or range) and describe the selection flow. | M11: Open | N11: Game Design / Math Provider | O11: 23 Oct 2026
A12: OBS-11 | B12: Information | C12: Buy Feature | D12: Bought FS use different weights from natural FS: FG1 0-wild weight 433 vs 838; FG2 multiplier 875/200/100 vs 8/2/1. Some jurisdictions require disclosure that bought features differ. | E12: N/A | F12: Buy FG1 Calc AJ3; Buy FG2 Calc AA3:AA5 | G12: Compliance disclosure risk | H12: Medium | I12: P2 | J12: M-17 | K12: PS-MTH-035, PS-MTH-048, PS-MTH-050 | L12: Confirm with compliance; disclose if required. | M12: Open | N12: Game Design / Math Provider | O12: 23 Oct 2026
A13: OBS-12 | B13: Risk | C13: Max Win | D13: Buy FG2 max exposure 1,674,912 cr (83,745.6x bet) exceeds whole-game max 1,009,091 cr (50,454.55x). Cap value undefined. | E13: BET AND MAX WIN | F13: Summary C10, C21:D21 | G13: Cap must hold in all modes; liability | H13: High | I13: P0 | J13: GR-29, M-04, M-16 | K13: PS-FUN-086, PS-MTH-053, PS-MTH-054 | L13: Define single cap; verify server enforcement in base, FS and Buy. | M13: Open | N13: Game Design / Math Provider | O13: 23 Oct 2026
... A25: OBS-24 | B25: Missing Spec | C25: Auto Spin | D25: Behaviour of Auto Spin on FS trigger (choice screen) and after reload not specified. | E25: AUTO SPIN | F25: N/A | G25: Ambiguous expected result | H25: Medium | I25: P2 | J25: GR-43, GR-16 | K25: PS-FUN-077, PS-INT-027 | L25: Specify. | M25: Open | N25: Game Design / Math Provider | O25: 23 Oct 2026
A26: PS-DEF-001
A27: PS-DEF-002
A28: PS-DEF-003
A29: PS-DEF-004
A30: PS-DEF-005
A31: PS-DEF-006
A32: PS-DEF-007
A33: PS-DEF-008
A34: PS-DEF-009
A35: PS-DEF-010
A36: PS-DEF-011
A37: PS-DEF-012
... A55: PS-DEF-030

Sheet Test Execution Summary
A1: Test Execution Summary
A2: Live: counts update from the Status column of each sheet. Fill in build details below.
A4: Build / Version
A5: Environment
A6: Execution Start
A7: Execution End
A8: Tester(s)
A9: Math Config Deployed
A10: Jurisdiction / Operator
A13: Sheet | B13: Total | C13: Not Run | D13: Pass | E13: Fail | F13: Blocked | G13: N/A | H13: Spec Confirmation | I13: Executed | J13: Pass Rate | K13: Progress
A14: Functional Testing | B14: =COUNTA('Functional Testing'!A:A)-1 -> 90 | C14: =COUNTIF('Functional Testing'!Q:Q,"Not Run") -> 90 | D14: =COUNTIF('Functional Testing'!Q:Q,"Pass") -> 0 | E14: =COUNTIF('Functional Testing'!Q:Q,"Fail") -> 0 | F14: =COUNTIF('Functional Testing'!Q:Q,"Blocked") -> 0 | G14: =COUNTIF('Functional Testing'!Q:Q,"N/A") -> 0 | H14: =COUNTIF('Functional Testing'!Q:Q,"Spec Confirmation") -> 0 | I14: =B14-C14 -> 0 | J14: =IF(I14=0,0,D14/I14) -> 0 | K14: =IF(B14=0,0,I14/B14) -> 0
A15: Math Validation | B15: =COUNTA('Math Validation'!A:A)-1 -> 63 | C15: =COUNTIF('Math Validation'!Q:Q,"Not Run") -> 63 | D15: =COUNTIF('Math Validation'!Q:Q,"Pass") -> 0 | E15: =COUNTIF('Math Validation'!Q:Q,"Fail") -> 0 | F15: =COUNTIF('Math Validation'!Q:Q,"Blocked") -> 0 | G15: =COUNTIF('Math Validation'!Q:Q,"N/A") -> 0 | H15: =COUNTIF('Math Validation'!Q:Q,"Spec Confirmation") -> 0 | I15: =B15-C15 -> 0 | J15: =IF(I15=0,0,D15/I15) -> 0 | K15: =IF(B15=0,0,I15/B15) -> 0
A16: Feature Testing | B16: =COUNTA('Feature Testing'!A:A)-1 -> 59 | C16: =COUNTIF('Feature Testing'!Q:Q,"Not Run") -> 59 | D16: =COUNTIF('Feature Testing'!Q:Q,"Pass") -> 0 | E16: =COUNTIF('Feature Testing'!Q:Q,"Fail") -> 0 | F16: =COUNTIF('Feature Testing'!Q:Q,"Blocked") -> 0 | G16: =COUNTIF('Feature Testing'!Q:Q,"N/A") -> 0 | H16: =COUNTIF('Feature Testing'!Q:Q,"Spec Confirmation") -> 0 | I16: =B16-C16 -> 0 | J16: =IF(I16=0,0,D16/I16) -> 0 | K16: =IF(B16=0,0,I16/B16) -> 0
A17: Edge & Boundary Cases | B17: =COUNTA('Edge & Boundary Cases'!A:A)-1 -> 42 | C17: =COUNTIF('Edge & Boundary Cases'!Q:Q,"Not Run") -> 42 | D17: =COUNTIF('Edge & Boundary Cases'!Q:Q,"Pass") -> 0 | E17: =COUNTIF('Edge & Boundary Cases'!Q:Q,"Fail") -> 0 | F17: =COUNTIF('Edge & Boundary Cases'!Q:Q,"Blocked") -> 0 | G17: =COUNTIF('Edge & Boundary Cases'!Q:Q,"N/A") -> 0 | H17: =COUNTIF('Edge & Boundary Cases'!Q:Q,"Spec Confirmation") -> 0 | I17: =B17-C17 -> 0 | J17: =IF(I17=0,0,D17/I17) -> 0 | K17: =IF(B17=0,0,I17/B17) -> 0
A18: Regression Suite | B18: =COUNTA('Regression Suite'!A:A)-1 -> 162 | C18: =COUNTIF('Regression Suite'!Q:Q,"Not Run") -> 162 | D18: =COUNTIF('Regression Suite'!Q:Q,"Pass") -> 0 | E18: =COUNTIF('Regression Suite'!Q:Q,"Fail") -> 0 | F18: =COUNTIF('Regression Suite'!Q:Q,"Blocked") -> 0 | G18: =COUNTIF('Regression Suite'!Q:Q,"N/A") -> 0 | H18: =COUNTIF('Regression Suite'!Q:Q,"Spec Confirmation") -> 0 | I18: =B18-C18 -> 0 | J18: =IF(I18=0,0,D18/I18) -> 0 | K18: =IF(B18=0,0,I18/B18) -> 0
A19: UI-UX Testing | B19: =COUNTA('UI-UX Testing'!A:A)-1 -> 47 | C19: =COUNTIF('UI-UX Testing'!Q:Q,"Not Run") -> 47 | D19: =COUNTIF('UI-UX Testing'!Q:Q,"Pass") -> 0 | E19: =COUNTIF('UI-UX Testing'!Q:Q,"Fail") -> 0 | F19: =COUNTIF('UI-UX Testing'!Q:Q,"Blocked") -> 0 | G19: =COUNTIF('UI-UX Testing'!Q:Q,"N/A") -> 0 | H19: =COUNTIF('UI-UX Testing'!Q:Q,"Spec Confirmation") -> 0 | I19: =B19-C19 -> 0 | J19: =IF(I19=0,0,D19/I19) -> 0 | K19: =IF(B19=0,0,I19/B19) -> 0
A20: Compatibility Testing | B20: =COUNTA('Compatibility Testing'!A:A)-1 -> 21 | C20: =COUNTIF('Compatibility Testing'!Q:Q,"Not Run") -> 21 | D20: =COUNTIF('Compatibility Testing'!Q:Q,"Pass") -> 0 | E20: =COUNTIF('Compatibility Testing'!Q:Q,"Fail") -> 0 | F20: =COUNTIF('Compatibility Testing'!Q:Q,"Blocked") -> 0 | G20: =COUNTIF('Compatibility Testing'!Q:Q,"N/A") -> 0 | H20: =COUNTIF('Compatibility Testing'!Q:Q,"Spec Confirmation") -> 0 | I20: =B20-C20 -> 0 | J20: =IF(I20=0,0,D20/I20) -> 0 | K20: =IF(B20=0,0,I20/B20) -> 0
A21: Interruption & Recovery | B21: =COUNTA('Interruption & Recovery'!A:A)-1 -> 30 | C21: =COUNTIF('Interruption & Recovery'!Q:Q,"Not Run") -> 30 | D21: =COUNTIF('Interruption & Recovery'!Q:Q,"Pass") -> 0 | E21: =COUNTIF('Interruption & Recovery'!Q:Q,"Fail") -> 0 | F21: =COUNTIF('Interruption & Recovery'!Q:Q,"Blocked") -> 0 | G21: =COUNTIF('Interruption & Recovery'!Q:Q,"N/A") -> 0 | H21: =COUNTIF('Interruption & Recovery'!Q:Q,"Spec Confirmation") -> 0 | I21: =B21-C21 -> 0 | J21: =IF(I21=0,0,D21/I21) -> 0 | K21: =IF(B21=0,0,I21/B21) -> 0
A22: STR - Transaction Testing | B22: =COUNTA('STR - Transaction Testing'!A:A)-1 -> 27 | C22: =COUNTIF('STR - Transaction Testing'!Q:Q,"Not Run") -> 27 | D22: =COUNTIF('STR - Transaction Testing'!Q:Q,"Pass") -> 0 | E22: =COUNTIF('STR - Transaction Testing'!Q:Q,"Fail") -> 0 | F22: =COUNTIF('STR - Transaction Testing'!Q:Q,"Blocked") -> 0 | G22: =COUNTIF('STR - Transaction Testing'!Q:Q,"N/A") -> 0 | H22: =COUNTIF('STR - Transaction Testing'!Q:Q,"Spec Confirmation") -> 0 | I22: =B22-C22 -> 0 | J22: =IF(I22=0,0,D22/I22) -> 0 | K22: =IF(B22=0,0,I22/B22) -> 0
A23: Error Handling | B23: =COUNTA('Error Handling'!A:A)-1 -> 20 | C23: =COUNTIF('Error Handling'!Q:Q,"Not Run") -> 20 | D23: =COUNTIF('Error Handling'!Q:Q,"Pass") -> 0 | E23: =COUNTIF('Error Handling'!Q:Q,"Fail") -> 0 | F23: =COUNTIF('Error Handling'!Q:Q,"Blocked") -> 0 | G23: =COUNTIF('Error Handling'!Q:Q,"N/A") -> 0 | H23: =COUNTIF('Error Handling'!Q:Q,"Spec Confirmation") -> 0 | I23: =B23-C23 -> 0 | J23: =IF(I23=0,0,D23/I23) -> 0 | K23: =IF(B23=0,0,I23/B23) -> 0
A24: Total | B24: =SUM(B14:B23) -> 561 | C24: =SUM(C14:C23) -> 561 | D24: =SUM(D14:D23) -> 0 | E24: =SUM(E14:E23) -> 0 | F24: =SUM(F14:F23) -> 0 | G24: =SUM(G14:G23) -> 0 | H24: =SUM(H14:H23) -> 0 | I24: =SUM(I14:I23) -> 0 | J24: =IF(I24=0,0,D24/I24) -> 0 | K24: =IF(B24=0,0,I24/B24) -> 0
A26: P0 status (release gate)
A27: Sheet | B27: P0 Total | C27: P0 Pass | D27: P0 Fail | E27: P0 Open (Not Run/Blocked)
A28: Functional Testing | B28: =COUNTIF('Functional Testing'!K:K,"P0") -> 49 | C28: =COUNTIFS('Functional Testing'!K:K,"P0",'Functional Testing'!Q:Q,"Pass") -> 0 | D28: =COUNTIFS('Functional Testing'!K:K,"P0",'Functional Testing'!Q:Q,"Fail") -> 0 | E28: =COUNTIFS('Functional Testing'!K:K,"P0",'Functional Testing'!Q:Q,"Not Run")+COUNTIFS('Functional Testing'!K:K,"P0",'Functional Testing'!Q:Q,"Blocked") -> 49
A29: Math Validation | B29: =COUNTIF('Math Validation'!K:K,"P0") -> 45 | C29: =COUNTIFS('Math Validation'!K:K,"P0",'Math Validation'!Q:Q,"Pass") -> 0 | D29: =COUNTIFS('Math Validation'!K:K,"P0",'Math Validation'!Q:Q,"Fail") -> 0 | E29: =COUNTIFS('Math Validation'!K:K,"P0",'Math Validation'!Q:Q,"Not Run")+COUNTIFS('Math Validation'!K:K,"P0",'Math Validation'!Q:Q,"Blocked") -> 45
A30: Feature Testing | B30: =COUNTIF('Feature Testing'!K:K,"P0") -> 40 | C30: =COUNTIFS('Feature Testing'!K:K,"P0",'Feature Testing'!Q:Q,"Pass") -> 0 | D30: =COUNTIFS('Feature Testing'!K:K,"P0",'Feature Testing'!Q:Q,"Fail") -> 0 | E30: =COUNTIFS('Feature Testing'!K:K,"P0",'Feature Testing'!Q:Q,"Not Run")+COUNTIFS('Feature Testing'!K:K,"P0",'Feature Testing'!Q:Q,"Blocked") -> 40
A31: Edge & Boundary Cases | B31: =COUNTIF('Edge & Boundary Cases'!K:K,"P0") -> 16 | C31: =COUNTIFS('Edge & Boundary Cases'!K:K,"P0",'Edge & Boundary Cases'!Q:Q,"Pass") -> 0 | D31: =COUNTIFS('Edge & Boundary Cases'!K:K,"P0",'Edge & Boundary Cases'!Q:Q,"Fail") -> 0 | E31: =COUNTIFS('Edge & Boundary Cases'!K:K,"P0",'Edge & Boundary Cases'!Q:Q,"Not Run")+COUNTIFS('Edge & Boundary Cases'!K:K,"P0",'Edge & Boundary Cases'!Q:Q,"Blocked") -> 16
A32: UI-UX Testing | B32: =COUNTIF('UI-UX Testing'!K:K,"P0") -> 1 | C32: =COUNTIFS('UI-UX Testing'!K:K,"P0",'UI-UX Testing'!Q:Q,"Pass") -> 0 | D32: =COUNTIFS('UI-UX Testing'!K:K,"P0",'UI-UX Testing'!Q:Q,"Fail") -> 0 | E32: =COUNTIFS('UI-UX Testing'!K:K,"P0",'UI-UX Testing'!Q:Q,"Not Run")+COUNTIFS('UI-UX Testing'!K:K,"P0",'UI-UX Testing'!Q:Q,"Blocked") -> 1
A33: Compatibility Testing | B33: =COUNTIF('Compatibility Testing'!K:K,"P0") -> 3 | C33: =COUNTIFS('Compatibility Testing'!K:K,"P0",'Compatibility Testing'!Q:Q,"Pass") -> 0 | D33: =COUNTIFS('Compatibility Testing'!K:K,"P0",'Compatibility Testing'!Q:Q,"Fail") -> 0 | E33: =COUNTIFS('Compatibility Testing'!K:K,"P0",'Compatibility Testing'!Q:Q,"Not Run")+COUNTIFS('Compatibility Testing'!K:K,"P0",'Compatibility Testing'!Q:Q,"Blocked") -> 3
A34: Interruption & Recovery | B34: =COUNTIF('Interruption & Recovery'!K:K,"P0") -> 24 | C34: =COUNTIFS('Interruption & Recovery'!K:K,"P0",'Interruption & Recovery'!Q:Q,"Pass") -> 0 | D34: =COUNTIFS('Interruption & Recovery'!K:K,"P0",'Interruption & Recovery'!Q:Q,"Fail") -> 0 | E34: =COUNTIFS('Interruption & Recovery'!K:K,"P0",'Interruption & Recovery'!Q:Q,"Not Run")+COUNTIFS('Interruption & Recovery'!K:K,"P0",'Interruption & Recovery'!Q:Q,"Blocked") -> 24
A35: STR - Transaction Testing | B35: =COUNTIF('STR - Transaction Testing'!K:K,"P0") -> 23 | C35: =COUNTIFS('STR - Transaction Testing'!K:K,"P0",'STR - Transaction Testing'!Q:Q,"Pass") -> 0 | D35: =COUNTIFS('STR - Transaction Testing'!K:K,"P0",'STR - Transaction Testing'!Q:Q,"Fail") -> 0 | E35: =COUNTIFS('STR - Transaction Testing'!K:K,"P0",'STR - Transaction Testing'!Q:Q,"Not Run")+COUNTIFS('STR - Transaction Testing'!K:K,"P0",'STR - Transaction Testing'!Q:Q,"Blocked") -> 23
A36: Error Handling | B36: =COUNTIF('Error Handling'!K:K,"P0") -> 8 | C36: =COUNTIFS('Error Handling'!K:K,"P0",'Error Handling'!Q:Q,"Pass") -> 0 | D36: =COUNTIFS('Error Handling'!K:K,"P0",'Error Handling'!Q:Q,"Fail") -> 0 | E36: =COUNTIFS('Error Handling'!K:K,"P0",'Error Handling'!Q:Q,"Not Run")+COUNTIFS('Error Handling'!K:K,"P0",'Error Handling'!Q:Q,"Blocked") -> 8
A37: Release gate | B37: =IF(AND(SUM(D28:D36)=0,SUM(E28:E36)=0),"GO (all P0 passed)","NO GO") -> NO GO
A39: Defects and observations by severity
A40: Severity | B40: Observations (spec) | C40: Defects (PS-DEF) | D40: Open total
A41: Critical | B41: =COUNTIFS('Defect-Observation Log'!H:H,"Critical",'Defect-Observation Log'!A:A,"OBS-*") -> 3 | C41: =COUNTIFS('Defect-Observation Log'!H:H,"Critical",'Defect-Observation Log'!A:A,"PS-DEF-*") -> 0 | D41: =COUNTIFS('Defect-Observation Log'!H:H,"Critical",'Defect-Observation Log'!M:M,"Open")+COUNTIFS('Defect-Observation Log'!H:H,"Critical",'Defect-Observation Log'!M:M,"In Progress") -> 3
A42: High | B42: =COUNTIFS('Defect-Observation Log'!H:H,"High",'Defect-Observation Log'!A:A,"OBS-*") -> 8 | C42: =COUNTIFS('Defect-Observation Log'!H:H,"High",'Defect-Observation Log'!A:A,"PS-DEF-*") -> 0 | D42: =COUNTIFS('Defect-Observation Log'!H:H,"High",'Defect-Observation Log'!M:M,"Open")+COUNTIFS('Defect-Observation Log'!H:H,"High",'Defect-Observation Log'!M:M,"In Progress") -> 8
A43: Medium | B43: =COUNTIFS('Defect-Observation Log'!H:H,"Medium",'Defect-Observation Log'!A:A,"OBS-*") -> 8 | C43: =COUNTIFS('Defect-Observation Log'!H:H,"Medium",'Defect-Observation Log'!A:A,"PS-DEF-*") -> 0 | D43: =COUNTIFS('Defect-Observation Log'!H:H,"Medium",'Defect-Observation Log'!M:M,"Open")+COUNTIFS('Defect-Observation Log'!H:H,"Medium",'Defect-Observation Log'!M:M,"In Progress") -> 8
A44: Low | B44: =COUNTIFS('Defect-Observation Log'!H:H,"Low",'Defect-Observation Log'!A:A,"OBS-*") -> 5 | C44: =COUNTIFS('Defect-Observation Log'!H:H,"Low",'Defect-Observation Log'!A:A,"PS-DEF-*") -> 0 | D44: =COUNTIFS('Defect-Observation Log'!H:H,"Low",'Defect-Observation Log'!M:M,"Open")+COUNTIFS('Defect-Observation Log'!H:H,"Low",'Defect-Observation Log'!M:M,"In Progress") -> 5

Sheet Math Reference
A1: Math Reference (extracted from pig_style_R7_1.xlsx)
A2: Blue values are inputs copied from the math file (source cell noted). Black values are formulas.
A4: Total bet in credits (Summary K5) | B4: 20
A5: Example bet (currency) | B5: 1
A7: Paytable (BG Calc R3:V14)
A8: Symbol | B8: 6 OAK (cr) | C8: 5 OAK (cr) | D8: 4 OAK (cr) | E8: 3 OAK (cr) | F8: 6 OAK x bet | G8: 5 OAK x bet | H8: 4 OAK x bet | I8: 3 OAK x bet | J8: 6 OAK @ example bet | K8: 3 OAK @ example bet
A9: AA | B9: 150 | C9: 60 | D9: 40 | E9: 15 | F9: =B9/$B$4 -> 7.5 | G9: =C9/$B$4 -> 3 | H9: =D9/$B$4 -> 2 | I9: =E9/$B$4 -> 0.75 | J9: =F9*$B$5 -> 7.5 | K9: =I9*$B$5 -> 0.75
A10: BB | B10: 60 | C10: 30 | D10: 20 | E10: 10 | F10: =B10/$B$4 -> 3 | G10: =C10/$B$4 -> 1.5 | H10: =D10/$B$4 -> 1 | I10: =E10/$B$4 -> 0.5 | J10: =F10*$B$5 -> 3 | K10: =I10*$B$5 -> 0.5
A11: CC | B11: 40 | C11: 20 | D11: 15 | E11: 7 | F11: =B11/$B$4 -> 2 | G11: =C11/$B$4 -> 1 | H11: =D11/$B$4 -> 0.75 | I11: =E11/$B$4 -> 0.35 | J11: =F11*$B$5 -> 2 | K11: =I11*$B$5 -> 0.35
A12: DD | B12: 30 | C12: 15 | D12: 10 | E12: 4 | F12: =B12/$B$4 -> 1.5 | G12: =C12/$B$4 -> 0.75 | H12: =D12/$B$4 -> 0.5 | I12: =E12/$B$4 -> 0.2 | J12: =F12*$B$5 -> 1.5 | K12: =I12*$B$5 -> 0.2
A13: EE | B13: 30 | C13: 10 | D13: 8 | E13: 3 | F13: =B13/$B$4 -> 1.5 | G13: =C13/$B$4 -> 0.5 | H13: =D13/$B$4 -> 0.4 | I13: =E13/$B$4 -> 0.15 | J13: =F13*$B$5 -> 1.5 | K13: =I13*$B$5 -> 0.15
A14: FF | B14: 30 | C14: 10 | D14: 8 | E14: 3 | F14: =B14/$B$4 -> 1.5 | G14: =C14/$B$4 -> 0.5 | H14: =D14/$B$4 -> 0.4 | I14: =E14/$B$4 -> 0.15 | J14: =F14*$B$5 -> 1.5 | K14: =I14*$B$5 -> 0.15
A15: GG | B15: 20 | C15: 6 | D15: 4 | E15: 2 | F15: =B15/$B$4 -> 1 | G15: =C15/$B$4 -> 0.3 | H15: =D15/$B$4 -> 0.2 | I15: =E15/$B$4 -> 0.1 | J15: =F15*$B$5 -> 1 | K15: =I15*$B$5 -> 0.1
A16: HH | B16: 20 | C16: 6 | D16: 4 | E16: 2 | F16: =B16/$B$4 -> 1 | G16: =C16/$B$4 -> 0.3 | H16: =D16/$B$4 -> 0.2 | I16: =E16/$B$4 -> 0.1 | J16: =F16*$B$5 -> 1 | K16: =I16*$B$5 -> 0.1
A17: JJ | B17: 20 | C17: 6 | D17: 4 | E17: 2 | F17: =B17/$B$4 -> 1 | G17: =C17/$B$4 -> 0.3 | H17: =D17/$B$4 -> 0.2 | I17: =E17/$B$4 -> 0.1 | J17: =F17*$B$5 -> 1 | K17: =I17*$B$5 -> 0.1
A18: KK | B18: 10 | C18: 4 | D18: 2 | E18: 1 | F18: =B18/$B$4 -> 0.5 | G18: =C18/$B$4 -> 0.2 | H18: =D18/$B$4 -> 0.1 | I18: =E18/$B$4 -> 0.05 | J18: =F18*$B$5 -> 0.5 | K18: =I18*$B$5 -> 0.05
A19: LL | B19: 10 | C19: 4 | D19: 2 | E19: 1 | F19: =B19/$B$4 -> 0.5 | G19: =C19/$B$4 -> 0.2 | H19: =D19/$B$4 -> 0.1 | I19: =E19/$B$4 -> 0.05 | J19: =F19*$B$5 -> 0.5 | K19: =I19*$B$5 -> 0.05
A21: Free Spins awards (FG1 Calc AD3:AE6, FG2 Calc AD3:AE6)
A22: Bonus count | B22: Raining Wilds (FG1) | C22: Sticky Wilds (FG2)
A23: 3 | B23: 15 | C23: 7
A24: 4 | B24: 18 | C24: 12
A25: 5 | B25: 25 | C25: 15
A26: 6 | B26: 30 | C26: 20
A28: Wild multiplier weights
A29: Mode (source) | B29: x1 weight | C29: x2 weight | D29: x3 weight | E29: x1 % | F29: x2 % | G29: x3 % | H29: Mean multiplier
A30: Base game (BG Calc Z3:AA5) | B30: 10 | C30: 5 | D30: 2 | E30: =B30/SUM($B30:$D30) -> 0.58823529 | F30: =C30/SUM($B30:$D30) -> 0.29411765 | G30: =D30/SUM($B30:$D30) -> 0.11764706 | H30: =(B30*1+C30*2+D30*3)/SUM(B30:D30) -> 1.5294118
A31: Raining FG1 (FG1 Calc Z3:AA5) | B31: 1000 | C31: 500 | D31: 189 | E31: =B31/SUM($B31:$D31) -> 0.59206631 | F31: =C31/SUM($B31:$D31) -> 0.29603316 | G31: =D31/SUM($B31:$D31) -> 0.11190053 | H31: =(B31*1+C31*2+D31*3)/SUM(B31:D31) -> 1.5198342
A32: Buy FG1 (Buy FG1 Calc Z3:AA5) | B32: 1000 | C32: 500 | D32: 189 | E32: =B32/SUM($B32:$D32) -> 0.59206631 | F32: =C32/SUM($B32:$D32) -> 0.29603316 | G32: =D32/SUM($B32:$D32) -> 0.11190053 | H32: =(B32*1+C32*2+D32*3)/SUM(B32:D32) -> 1.5198342
A33: Sticky FG2 (FG2 Calc Z3:AA5) | B33: 8 | C33: 2 | D33: 1 | E33: =B33/SUM($B33:$D33) -> 0.72727273 | F33: =C33/SUM($B33:$D33) -> 0.18181818 | G33: =D33/SUM($B33:$D33) -> 0.090909091 | H33: =(B33*1+C33*2+D33*3)/SUM(B33:D33) -> 1.3636364
A34: Buy FG2 (Buy FG2 Calc Z3:AA5) | B34: 875 | C34: 200 | D34: 100 | E34: =B34/SUM($B34:$D34) -> 0.74468085 | F34: =C34/SUM($B34:$D34) -> 0.17021277 | G34: =D34/SUM($B34:$D34) -> 0.085106383 | H34: =(B34*1+C34*2+D34*3)/SUM(B34:D34) -> 1.3404255
A36: Wilds per Free Spin (reels 2-5 only)
A37: Mode (source) | B37: 0 | C37: 1 | D37: 2 | E37: 3 | F37: 4 | G37: 5 | H37: 6 | I37: P(0 wilds) | J37: Mean wilds
A38: Raining FG1 (FG1 Calc AI3:AJ9) | B38: 838 | C38: 200 | D38: 500 | E38: 200 | F38: 50 | G38: 25 | H38: 10 | I38: =B38/SUM(B38:H38) -> 0.45968184 | J38: =SUMPRODUCT(B38:H38,{0,1,2,3,4,5,6})/SUM(B38:H38) -> 1.1985738
A39: Buy FG1 (Buy FG1 Calc AI3:AJ9) | B39: 433 | C39: 200 | D39: 500 | E39: 200 | F39: 50 | G39: 25 | H39: 10 | I39: =B39/SUM(B39:H39) -> 0.30535966 | J39: =SUMPRODUCT(B39:H39,{0,1,2,3,4,5,6})/SUM(B39:H39) -> 1.5409027
A40: Sticky FG2 new per spin (FG2 Calc AI3:AJ6) | B40: 500 | C40: 126 | D40: 50 | E40: 10 | F40: 0 | G40: 0 | H40: 0 | I40: =B40/SUM(B40:H40) -> 0.72886297 | J40: =SUMPRODUCT(B40:H40,{0,1,2,3,4,5,6})/SUM(B40:H40) -> 0.37317784
A41: Buy FG2 new per spin (Buy FG2 Calc AI3:AJ6) | B41: 424 | C41: 126 | D41: 50 | E41: 10 | F41: 0 | G41: 0 | H41: 0 | I41: =B41/SUM(B41:H41) -> 0.69508197 | J41: =SUMPRODUCT(B41:H41,{0,1,2,3,4,5,6})/SUM(B41:H41) -> 0.41967213
A43: Base game reel set weights (BG Calc AE3:AF11)
A44: Reel set | B44: Weight | C44: Probability | D44: FS trigger odds (Summary K43:K51)
A45: BG1 | B45: 23 | C45: =B45/SUM($B$45:$B$53) -> 0.0061480887 | D45: 1 in 57.10
A46: BG2 | B46: 50 | C46: =B46/SUM($B$45:$B$53) -> 0.01336541 | D46: none
A47: BG3 | B47: 60 | C47: =B47/SUM($B$45:$B$53) -> 0.016038492 | D47: none
A48: BG4 | B48: 2000 | C48: =B48/SUM($B$45:$B$53) -> 0.53461641 | D48: none
A49: BG5 | B49: 475 | C49: =B49/SUM($B$45:$B$53) -> 0.1269714 | D49: none
A50: BG6 | B50: 33 | C50: =B50/SUM($B$45:$B$53) -> 0.0088211708 | D50: 1 in 2.44
A51: BG7 | B51: 50 | C51: =B51/SUM($B$45:$B$53) -> 0.01336541 | D51: none
A52: BG8 | B52: 50 | C52: =B52/SUM($B$45:$B$53) -> 0.01336541 | D52: none
A53: BG9 | B53: 1000 | C53: =B53/SUM($B$45:$B$53) -> 0.26730821 | D53: none
A55: Reel heights (BG Calc AJ20:AL25)
A56: Rows | B56: Opt0 weight | C56: Opt1 weight | D56: Opt0 % | E56: Opt1 %
A57: 2 | B57: 100 | C57: 25 | D57: =B57/SUM(B$57:B$62) -> 0.22222222 | E57: =C57/SUM(C$57:C$62) -> 0.0625
A58: 3 | B58: 200 | C58: 75 | D58: =B58/SUM(B$57:B$62) -> 0.44444444 | E58: =C58/SUM(C$57:C$62) -> 0.1875
A59: 4 | B59: 75 | C59: 75 | D59: =B59/SUM(B$57:B$62) -> 0.16666667 | E59: =C59/SUM(C$57:C$62) -> 0.1875
A60: 5 | B60: 50 | C60: 75 | D60: =B60/SUM(B$57:B$62) -> 0.11111111 | E60: =C60/SUM(C$57:C$62) -> 0.1875
A61: 6 | B61: 15 | C61: 75 | D61: =B61/SUM(B$57:B$62) -> 0.033333333 | E61: =C61/SUM(C$57:C$62) -> 0.1875
A62: 7 | B62: 10 | C62: 75 | D62: =B62/SUM(B$57:B$62) -> 0.022222222 | E62: =C62/SUM(C$57:C$62) -> 0.1875
A64: Key statistics (Summary sheet)
A65: Metric | B65: Base game (whole) | C65: Buy FG1 | D65: Buy FG2 | E65: Unit / note
A66: Total RTP | B66: 0.9698864 | C66: 0.9708362 | D66: 0.9710962 | E66: %
A67: Base component RTP | B67: 0.6892386 | C67: 0.0213131 | D67: 0.0213002 | E67: %
A68: FS component RTP | B68: 0.2806479 | C68: 0.9495232 | D68: 0.949796 | E68: %
A69: Hit frequency | B69: 0.316018 | C69: 0.9999702 | D69: 0.9741966 | E69: %
A70: SD (x bet / x cost) | B70: 16.802388 | C70: 1.6184133 | D70: 3.7108163 | E70: multiple
A71: Max exposure (credits) | B71: 1009091 | C71: 487402 | D71: 1674912 | E71: credits at bet 20 (Buy: cost 2000)
A72: FS trigger odds (1 in) | B72: 268.89187 | C72: 1 | D72: 1 | E72: spins
A73: Avg FS awarded | B73: 12.372 | C73: 16.15818 | D73: 8.59024 | E73: spins
A74: Buy cost (x bet) | C74: 100 | D74: 100 | E74: x total bet
A75: Max exposure (x total bet) | B75: =B71/$B$4 -> 50454.55 | C75: =C71/$B$4 -> 24370.1 | D75: =D71/$B$4 -> 83745.6 | E75: Buy values relative to base bet (cost 2000 = 100 x 20)
